Workbook

Sheet Jan 26
A1: Customer | B1: Q Number | C1: Region | D1: Payment Date | E1: Production Start Day | F1: Stage | G1: DEPOSIT | H1: FINAL | I1: TOTAL | J1: BOM Dep | K1: Dep to Rev | L1: New Dep this Month
A2: Advanced Windows:Golden Hill | B2: 84541 | C2: MD-C | D2: 45943 | E2: =VLOOKUP(B2,'[2]Month Total'!$B:$E,4,FALSE) -> Pre-Production | F2: =VLOOKUP(B2,'[2]Month Total'!$B:$F,5,FALSE) -> Pre-Production | G2: 10262 | H2: =I2-G2 -> 9172 | I2: 19434 | J2: 10262 | K2: =IF(G2=0,J2-G2,0) -> 0 | L2: =IF(G2>0,G2-J2,"Invoiced this Month") -> 0
A3: Akis Doganis:Doganis Residence | B3: 87185 | C3: NV-R | D3: 12/04/2025 | E3: =VLOOKUP(B3,'[2]Month Total'!$B:$E,4,FALSE) -> Pre-Production | F3: =VLOOKUP(B3,'[2]Month Total'!$B:$F,5,FALSE) -> Pre-Production | G3: 31515 | H3: =I3-G3 -> 31514 | I3: 63029 | J3: 31515 | K3: =IF(G3=0,J3-G3,0) -> 0 | L3: =IF(G3>0,G3-J3,"Invoiced this Month") -> 0
A4: All New Glass:201 Fillmore | B4: 78377 | C4: WA-C | D4: 02/24/2025 | E4: =VLOOKUP(B4,'[2]Month Total'!$B:$E,4,FALSE) -> 46007 | F4: =VLOOKUP(B4,'[2]Month Total'!$B:$F,5,FALSE) -> Powder coat | G4: 342623.5 | H4: =I4-G4 -> 342623.5 | I4: 685247 | J4: 342623.5 | K4: =IF(G4=0,J4-G4,0) -> 0 | L4: =IF(G4>0,G4-J4,"Invoiced this Month") -> 0
A5: All New Glass:201 Fillmore 1st Floor | B5: 86050 | C5: WA-C | D5: 45954 | E5: 46050 | F5: =VLOOKUP(B5,'[2]Month Total'!$B:$F,5,FALSE) -> Pre-Production | G5: 68086 | H5: =I5-G5 -> 67560 | I5: 135646 | J5: 34043 | K5: =IF(G5=0,J5-G5,0) -> 0 | L5: =IF(G5>0,G5-J5,"Invoiced this Month") -> 34043
A6: All New Glass:Chanel UTC | B6: 83846 | C6: WA-C | D6: 45880 | E6: =VLOOKUP(B6,'[2]Month Total'!$B:$E,4,FALSE) -> Pre-Production | F6: =VLOOKUP(B6,'[2]Month Total'!$B:$F,5,FALSE) -> Pre-Production | G6: 77743 | H6: =I6-G6 -> 77742 | I6: 155485 | J6: 77743 | K6: =IF(G6=0,J6-G6,0) -> 0 | L6: =IF(G6>0,G6-J6,"Invoiced this Month") -> 0
A7: American Glass - Livermore:Sunset Clubhouse-2 | B7: 85639 | C7: CA-C | D7: 45805 | E7: =VLOOKUP(B7,'[2]Month Total'!$B:$E,4,FALSE) -> 46015 | F7: =VLOOKUP(B7,'[2]Month Total'!$B:$F,5,FALSE) -> Pull Material | G7: 11673 | H7: =I7-G7 -> 11672 | I7: 23345 | J7: 11673 | K7: =IF(G7=0,J7-G7,0) -> 0 | L7: =IF(G7>0,G7-J7,"Invoiced this Month") -> 0
A8: American Products Inc (API):Lululemon Boston | B8: 86924 | C8: NA-C | D8: 45965 | E8: =VLOOKUP(B8,'[2]Month Total'!$B:$E,4,FALSE) -> 46013 | F8: =VLOOKUP(B8,'[2]Month Total'!$B:$F,5,FALSE) -> Powder coat | G8: 40090 | H8: =I8-G8 -> 40089 | I8: 80179 | J8: 40090 | K8: =IF(G8=0,J8-G8,0) -> 0 | L8: =IF(G8>0,G8-J8,"Invoiced this Month") -> 0
A9: Aragon Construction, Inc.:Penta (1) Interior | B9: 84044 | C9: CA-C | D9: 45811 | E9: =VLOOKUP(B9,'[2]Month Total'!$B:$E,4,FALSE) -> 46002 | F9: =VLOOKUP(B9,'[2]Month Total'!$B:$F,5,FALSE) -> Coating | G9: 93528 | H9: =I9-G9 -> -28848 | I9: 64680 | J9: 93528 | K9: =IF(G9=0,J9-G9,0) -> 0 | L9: =IF(G9>0,G9-J9,"Invoiced this Month") -> 0
A10: Aragon Construction, Inc.:Penta (2) Exterior | B10: 84046 | C10: CA-C | D10: 45811 | E10: =VLOOKUP(B10,'[2]Month Total'!$B:$E,4,FALSE) -> 46002 | F10: =VLOOKUP(B10,'[2]Month Total'!$B:$F,5,FALSE) -> Coating | G10: 97035 | H10: =I10-G10 -> 38165 | I10: 135200 | J10: 97035 | K10: =IF(G10=0,J10-G10,0) -> 0 | L10: =IF(G10>0,G10-J10,"Invoiced this Month") -> 0
A11: Aragon Construction, Inc.:Puente Hills | B11: 82690 | C11: CA-C | D11: 11/17/2025 | E11: =VLOOKUP(B11,'[2]Month Total'!$B:$E,4,FALSE) -> Pre-Production | F11: =VLOOKUP(B11,'[2]Month Total'!$B:$F,5,FALSE) -> Pre-Production | G11: 13744 | H11: =I11-G11 -> 12649 | I11: 26393 | J11: 13744 | K11: =IF(G11=0,J11-G11,0) -> 0 | L11: =IF(G11>0,G11-J11,"Invoiced this Month") -> 0
A12: Avatar Design Build LLC:Avatar Custom Home | B12: 84790 | C12: MD-R | D12: 45890 | E12: =VLOOKUP(B12,'[2]Month Total'!$B:$E,4,FALSE) -> 45973 | F12: =VLOOKUP(B12,'[2]Month Total'!$B:$F,5,FALSE) -> Powder coat | G12: 37869 | H12: =I12-G12 -> 37868 | I12: 75737 | J12: 37869 | K12: =IF(G12=0,J12-G12,0) -> 0 | L12: =IF(G12>0,G12-J12,"Invoiced this Month") -> 0
A13: Barbara Bellio:Bellio Residence | B13: 87402 | C13: NV-R | D13: 45939 | E13: =VLOOKUP(B13,'[2]Month Total'!$B:$E,4,FALSE) -> Pre-Production | F13: =VLOOKUP(B13,'[2]Month Total'!$B:$F,5,FALSE) -> Pre-Production | G13: 20000 | H13: =I13-G13 -> 19516 | I13: 39516 | J13: 20000 | K13: =IF(G13=0,J13-G13,0) -> 0 | L13: =IF(G13>0,G13-J13,"Invoiced this Month") -> 0
A14: Best Contracting LLC:UCSB San Benito Housing | B14: 87022 | C14: CA-C | D14: 11/20/2025 | E14: =VLOOKUP(B14,'[2]Month Total'!$B:$E,4,FALSE) -> Pre-Production | F14: =VLOOKUP(B14,'[2]Month Total'!$B:$F,5,FALSE) -> Pre-Production | G14: 60823 | H14: =I14-G14 -> 60822 | I14: 121645 | J14: 60823 | K14: =IF(G14=0,J14-G14,0) -> 0 | L14: =IF(G14>0,G14-J14,"Invoiced this Month") -> 0
A15: Biery Cheese Company:Silo Radius | B15: 87104 | C15: OH-C | D15: 45939 | E15: =VLOOKUP(B15,'[2]Month Total'!$B:$E,4,FALSE) -> Pre-Production | F15: =VLOOKUP(B15,'[2]Month Total'!$B:$F,5,FALSE) -> Pre-Production | G15: 24528.82 | H15: =I15-G15 -> 0 | I15: 24528.82 | J15: 24528.82 | K15: =IF(G15=0,J15-G15,0) -> 0 | L15: =IF(G15>0,G15-J15,"Invoiced this Month") -> 0
A16: BMG Door & Glass:Zamora Residence | B16: 88921 | C16: NV-R | D16: 01/30/2026 | E16: Pre-Production | F16: Pre-Production | G16: 18436 | H16: =I16-G16 -> 18436 | I16: 36872 | J16: 0 | L16: =IF(G16>0,G16-J16,"Invoiced this Month") -> 18436
A17: Builders Direct Supply:4545 North-Studio | B17: 85791 | C17: CA-R | D17: 45959 | E17: =VLOOKUP(B17,'[2]Month Total'!$B:$E,4,FALSE) -> Pre-Production | F17: =VLOOKUP(B17,'[2]Month Total'!$B:$F,5,FALSE) -> Pre-Production | G17: 8977.7 | H17: =I17-G17 -> 80799.3 | I17: 89777 | J17: 8977.7 | K17: =IF(G17=0,J17-G17,0) -> 0 | L17: =IF(G17>0,G17-J17,"Invoiced this Month") -> 0
A18: Builders Direct Supply:Direct Doors | B18: 87898 | C18: CA-R | D18: 45967 | E18: =VLOOKUP(B18,'[2]Month Total'!$B:$E,4,FALSE) -> 46000 | F18: =VLOOKUP(B18,'[2]Month Total'!$B:$F,5,FALSE) -> Coating | G18: 6997.5 | H18: =I18-G18 -> 6997.5 | I18: 13995 | J18: 6997.5 | K18: =IF(G18=0,J18-G18,0) -> 0 | L18: =IF(G18>0,G18-J18,"Invoiced this Month") -> 0
A19: Builders Direct Supply:North 4545 | B19: 83690 | C19: CA-R | D19: 45959 | E19: =VLOOKUP(B19,'[2]Month Total'!$B:$E,4,FALSE) -> Pre-Production | F19: =VLOOKUP(B19,'[2]Month Total'!$B:$F,5,FALSE) -> Pre-Production | G19: 41681.4 | H19: =I19-G19 -> 375132.6 | I19: 416814 | J19: 41681.4 | K19: =IF(G19=0,J19-G19,0) -> 0 | L19: =IF(G19>0,G19-J19,"Invoiced this Month") -> 0
A20: Builders Direct Supply:Snell and Wilmer | B20: 86318 | C20: CA-C | D20: 01/08/2026 | E20: Pre-Production | F20: Pre-Production | G20: 26483.5 | H20: =I20-G20 -> 26483.5 | I20: 52967 | J20: 0 | L20: =IF(G20>0,G20-J20,"Invoiced this Month") -> 26483.5
A21: Builders FirstSource/Dixieline Lumber & Home Center:Jody Doors | B21: 88100 | C21: CA-R | D21: 12/29/2025 | E21: =VLOOKUP(B21,'[2]Month Total'!$B:$E,4,FALSE) -> Pre-Production | F21: =VLOOKUP(B21,'[2]Month Total'!$B:$F,5,FALSE) -> Pre-Production | G21: 8674 | H21: =I21-G21 -> 8673 | I21: 17347 | J21: 8674 | K21: =IF(G21=0,J21-G21,0) -> 0 | L21: =IF(G21>0,G21-J21,"Invoiced this Month") -> 0
A22: Bulldog Diversified Construction:Bulldog Folding Door | B22: 88570 | C22: AZ-R | D22: 01/20/2026 | E22: Pre-Production | F22: Pre-Production | G22: 8743 | H22: =I22-G22 -> 8743 | I22: 17486 | J22: 0 | L22: =IF(G22>0,G22-J22,"Invoiced this Month") -> 8743
A23: C Thru Glass:Caesars Republic Pool Club Lounge | B23: 87633 | C23: NV-C | D23: 01/08/2026 | E23: Pre-Production | F23: Pre-Production | G23: 39028 | H23: =I23-G23 -> 39027 | I23: 78055 | J23: 0 | L23: =IF(G23>0,G23-J23,"Invoiced this Month") -> 39028
A24: Capitol Glass Company:99 Rhode Island | B24: 85440 | C24: CA-C | D24: 11/19/2025 | E24: 46044 | F24: =VLOOKUP(B24,'[2]Month Total'!$B:$F,5,FALSE) -> Pre-Production | G24: 15439 | H24: =I24-G24 -> 15438 | I24: 30877 | J24: 15439 | K24: =IF(G24=0,J24-G24,0) -> 0 | L24: =IF(G24>0,G24-J24,"Invoiced this Month") -> 0
A25: Capitol Glass Company:Sunnydale Block 7 | B25: 88227 | C25: CA-C | D25: 12/29/2025 | E25: =VLOOKUP(B25,'[2]Month Total'!$B:$E,4,FALSE) -> Pre-Production | F25: =VLOOKUP(B25,'[2]Month Total'!$B:$F,5,FALSE) -> Pre-Production | G25: 32005 | H25: =I25-G25 -> 32005 | I25: 64010 | J25: 32005 | K25: =IF(G25=0,J25-G25,0) -> 0 | L25: =IF(G25>0,G25-J25,"Invoiced this Month") -> 0
A26: Caribbean Windows International:Seagrapes 2 | B26: 87308 | C26: CAR-R | D26: 45918 | E26: =VLOOKUP(B26,'[2]Month Total'!$B:$E,4,FALSE) -> 45996 | F26: =VLOOKUP(B26,'[2]Month Total'!$B:$F,5,FALSE) -> Powder coat | G26: 57207 | H26: =I26-G26 -> 57327 | I26: 114534 | J26: 57207 | K26: =IF(G26=0,J26-G26,0) -> 0 | L26: =IF(G26>0,G26-J26,"Invoiced this Month") -> 0
A27: Castle House Distributors Inc.:Nila Bugala Door | B27: 88130 | C27: CA-R | D27: 11/24/2025 | E27: =VLOOKUP(B27,'[2]Month Total'!$B:$E,4,FALSE) -> 46000 | F27: 46045 | G27: 0 | J27: 7472.5 | K27: =IF(G27=0,J27-G27,0) -> 7472.5 | L27: =IF(G27>0,G27-J27,"Invoiced this Month") -> Invoiced this Month
A28: Catalyst Acoustics Group | B28: Unknown | D28: 05/31/2022 | E28: =VLOOKUP(B28,'[2]Month Total'!$B:$E,4,FALSE) -> Pre-Production | F28: =VLOOKUP(B28,'[2]Month Total'!$B:$F,5,FALSE) -> Pre-Production | G28: 4108 | H28: =I28-G28 -> 0 | I28: 4108 | J28: 4108 | K28: =IF(G28=0,J28-G28,0) -> 0 | L28: =IF(G28>0,G28-J28,"Invoiced this Month") -> 0
A29: Cheryl Partee:Partee Residence | B29: 86866 | C29: CA-R | D29: 11/25/2025 | E29: =VLOOKUP(B29,'[2]Month Total'!$B:$E,4,FALSE) -> 46015 | F29: =VLOOKUP(B29,'[2]Month Total'!$B:$F,5,FALSE) -> Powder coat | G29: 12000 | H29: =I29-G29 -> 10694 | I29: 22694 | J29: 12000 | K29: =IF(G29=0,J29-G29,0) -> 0 | L29: =IF(G29>0,G29-J29,"Invoiced this Month") -> 0
A30: Classic Carpentry Inc.:CC Project / 262 Mermaid's Bight | B30: 88131 | C30: FL-R | D30: 01/20/2026 | E30: Pre-Production | F30: Pre-Production | G30: 33237 | H30: =I30-G30 -> 33236 | I30: 66473 | J30: 0 | L30: =IF(G30>0,G30-J30,"Invoiced this Month") -> 33237
A31: Coltin Craigo:Alphorn Road | B31: 87218 | C31: WI-R | D31: 12/19/2025 | E31: 46028 | F31: =VLOOKUP(B31,'[2]Month Total'!$B:$F,5,FALSE) -> Pre-Production | G31: 7433 | H31: =I31-G31 -> 7432 | I31: 14865 | J31: 7433 | K31: =IF(G31=0,J31-G31,0) -> 0 | L31: =IF(G31>0,G31-J31,"Invoiced this Month") -> 0
A32: Constructa:Nuevo Proyecto en Punta Mita | B32: 83937 | C32: MX-C | D32: 11/20/2025 | E32: =VLOOKUP(B32,'[2]Month Total'!$B:$E,4,FALSE) -> Pre-Production | F32: =VLOOKUP(B32,'[2]Month Total'!$B:$F,5,FALSE) -> Pre-Production | G32: 59570.5 | H32: =I32-G32 -> 59590.5 | I32: 119161 | J32: 59570.5 | K32: =IF(G32=0,J32-G32,0) -> 0 | L32: =IF(G32>0,G32-J32,"Invoiced this Month") -> 0
A33: Crystal Glass Inc.:New Logan Elementry | B33: 83108 | C33: MI-C | D33: 04/17/2025 | E33: =VLOOKUP(B33,'[2]Month Total'!$B:$E,4,FALSE) -> Pre-Production | F33: =VLOOKUP(B33,'[2]Month Total'!$B:$F,5,FALSE) -> Pre-Production | G33: 172204.5 | H33: =I33-G33 -> 172204.5 | I33: 344409 | J33: 172204.5 | K33: =IF(G33=0,J33-G33,0) -> 0 | L33: =IF(G33>0,G33-J33,"Invoiced this Month") -> 0
A34: D & R Glass:Cedar and Sage | B34: 84134 | C34: CA-C | D34: 45945 | E34: =VLOOKUP(B34,'[2]Month Total'!$B:$E,4,FALSE) -> Pre-Production | F34: =VLOOKUP(B34,'[2]Month Total'!$B:$F,5,FALSE) -> Pre-Production | G34: 64205 | H34: =I34-G34 -> 61477 | I34: 125682 | J34: 64205 | K34: =IF(G34=0,J34-G34,0) -> 0 | L34: =IF(G34>0,G34-J34,"Invoiced this Month") -> 0
A35: D&A Glass:Camas Grill T.I. | B35: 87768 | C35: ID-C | D35: 45971 | E35: =VLOOKUP(B35,'[2]Month Total'!$B:$E,4,FALSE) -> 46000 | F35: =VLOOKUP(B35,'[2]Month Total'!$B:$F,5,FALSE) -> Coating | G35: 25537 | H35: =I35-G35 -> 25537 | I35: 51074 | J35: 25537 | K35: =IF(G35=0,J35-G35,0) -> 0 | L35: =IF(G35>0,G35-J35,"Invoiced this Month") -> 0
A36: D&A Glass:Turf Club | B36: 87822 | C36: ID-C | D36: 11/24/2025 | E36: =VLOOKUP(B36,'[2]Month Total'!$B:$E,4,FALSE) -> 46001 | F36: =VLOOKUP(B36,'[2]Month Total'!$B:$F,5,FALSE) -> Powder coat | G36: 115956 | H36: =I36-G36 -> 126839 | I36: 242795 | J36: 115956 | K36: =IF(G36=0,J36-G36,0) -> 0 | L36: =IF(G36>0,G36-J36,"Invoiced this Month") -> 0
A37: Danco Group:4441 N Jokake House | B37: 86461 | C37: AZ-R | D37: 45960 | E37: =VLOOKUP(B37,'[2]Month Total'!$B:$E,4,FALSE) -> Pre-Production | F37: Canceled 1/14 | G37: 0 | J37: 199193 | K37: =IF(G37=0,J37-G37,0) -> 199193 | L37: =IF(G37>0,G37-J37,"Invoiced this Month") -> Invoiced this Month
A38: Danco Group:4441 N Jokake Lift and Slide | B38: 86656 | C38: AZ-R | D38: 45890 | E38: =VLOOKUP(B38,'[2]Month Total'!$B:$E,4,FALSE) -> Pre-Production | F38: Canceled 1/14 | G38: 0 | J38: 113144 | K38: =IF(G38=0,J38-G38,0) -> 113144 | L38: =IF(G38>0,G38-J38,"Invoiced this Month") -> Invoiced this Month
A39: David Shuldiner Inc:450 Lexington | B39: 83623 | C39: NY-C | D39: 45859 | E39: =VLOOKUP(B39,'[2]Month Total'!$B:$E,4,FALSE) -> 46020 | F39: =VLOOKUP(B39,'[2]Month Total'!$B:$F,5,FALSE) -> Pull Material | G39: 75227 | H39: =I39-G39 -> 75226 | I39: 150453 | J39: 75227 | K39: =IF(G39=0,J39-G39,0) -> 0 | L39: =IF(G39>0,G39-J39,"Invoiced this Month") -> 0
A40: Debbie Piliero:46 Upper Rd | B40: 87161 | C40: CA-R | D40: 45924 | E40: =VLOOKUP(B40,'[2]Month Total'!$B:$E,4,FALSE) -> 45992 | F40: =VLOOKUP(B40,'[2]Month Total'!$B:$F,5,FALSE) -> Steel Job | G40: 17417 | H40: =I40-G40 -> 17417 | I40: 34834 | J40: 17417 | K40: =IF(G40=0,J40-G40,0) -> 0 | L40: =IF(G40>0,G40-J40,"Invoiced this Month") -> 0
A41: DGB Glass Inc.:Hotel Grey | B41: 86965 | C41: TX-C | D41: 45924 | E41: 46048 | F41: =VLOOKUP(B41,'[2]Month Total'!$B:$F,5,FALSE) -> Pre-Production | G41: 49026 | H41: =I41-G41 -> 51328 | I41: 100354 | J41: 12283.8 | K41: =IF(G41=0,J41-G41,0) -> 0 | L41: =IF(G41>0,G41-J41,"Invoiced this Month") -> 36742.2
A42: Dugally Oberfeld, Inc.:Cox | B42: 83729 | C42: CA-R | D42: 01/06/2026 | E42: Pre-Production | F42: Pre-Production | G42: 31223 | H42: =I42-G42 -> 27501 | I42: 58724 | J42: 0 | L42: =IF(G42>0,G42-J42,"Invoiced this Month") -> 31223
A43: E & Z Glass & Window:Sfondrini Residence | B43: 88210 | C43: TX-R | D43: 12/02/2025 | E43: =VLOOKUP(B43,'[2]Month Total'!$B:$E,4,FALSE) -> 46015 | F43: =VLOOKUP(B43,'[2]Month Total'!$B:$F,5,FALSE) -> Powder coat | G43: 14200 | H43: =I43-G43 -> 14458 | I43: 28658 | J43: 14200 | K43: =IF(G43=0,J43-G43,0) -> 0 | L43: =IF(G43>0,G43-J43,"Invoiced this Month") -> 0
A44: Eagle Glass Service LLC:Bullard King | B44: 86439 | C44: CO-R | D44: 45964 | E44: =VLOOKUP(B44,'[2]Month Total'!$B:$E,4,FALSE) -> 46015 | F44: =VLOOKUP(B44,'[2]Month Total'!$B:$F,5,FALSE) -> Pull Material | G44: 54101 | H44: =I44-G44 -> 54100 | I44: 108201 | J44: 54101 | K44: =IF(G44=0,J44-G44,0) -> 0 | L44: =IF(G44>0,G44-J44,"Invoiced this Month") -> 0
A45: EAP Glass:4th Street North Apts | B45: 85454 | C45: CO-C | D45: 12/30/2025 | E45: 46044 | F45: =VLOOKUP(B45,'[2]Month Total'!$B:$F,5,FALSE) -> Pre-Production | G45: 14438 | H45: =I45-G45 -> 14438 | I45: 28876 | J45: 14438 | K45: =IF(G45=0,J45-G45,0) -> 0 | L45: =IF(G45>0,G45-J45,"Invoiced this Month") -> 0
A46: Elaine Fitzpatrick:Fitzpatrick Residence | B46: 85838 | C46: NV-R | D46: 01/23/2026 | E46: Pre-Production | F46: Pre-Production | G46: 3386 | H46: =I46-G46 -> 3385 | I46: 6771 | J46: 0 | L46: =IF(G46>0,G46-J46,"Invoiced this Month") -> 3386
A47: Element Facades 13:299 MILWAUKEE | B47: 86960 | C47: CO-C | D47: 11/25/2025 | E47: =VLOOKUP(B47,'[2]Month Total'!$B:$E,4,FALSE) -> Pre-Production | F47: =VLOOKUP(B47,'[2]Month Total'!$B:$F,5,FALSE) -> Pre-Production | G47: 8962 | H47: =I47-G47 -> 26885 | I47: 35847 | J47: 8962 | K47: =IF(G47=0,J47-G47,0) -> 0 | L47: =IF(G47>0,G47-J47,"Invoiced this Month") -> 0
A48: Environmental Glass Inc:Mitchell Elementary | B48: 81492-R1 | C48: MI-C | D48: 45868 | E48: Pre-Production | F48: Pre-Production | G48: 57487 | H48: =I48-G48 -> 172460 | I48: 229947 | J48: 104308.92 | K48: =IF(G48=0,J48-G48,0) -> 0 | L48: =IF(G48>0,G48-J48,"Invoiced this Month") -> -46821.92
A49: Environmental Glass Inc:Ann Arbor Thurston | B49: 84161 | C49: MI-C | D49: 46013 | E49: Pre-Production | F49: Pre-Production | G49: 46821.92 | H49: =I49-G49 -> 306551.08 | I49: 353373
A50: Fast Glass:Brockway | B50: 87121 | C50: NV-R | D50: 12/19/2025 | E50: =VLOOKUP(B50,'[2]Month Total'!$B:$E,4,FALSE) -> Pre-Production | F50: =VLOOKUP(B50,'[2]Month Total'!$B:$F,5,FALSE) -> Pre-Production | G50: 8901 | H50: =I50-G50 -> 0 | I50: 8901 | J50: 8901 | K50: =IF(G50=0,J50-G50,0) -> 0 | L50: =IF(G50>0,G50-J50,"Invoiced this Month") -> 0
A51: Gen 3 Hospitality:Richardson House | B51: 88603 | C51: NV-R | D51: 01/06/2026 | E51: Pre-Production | F51: Pre-Production | G51: 23396 | H51: =I51-G51 -> 23396 | I51: 46792 | J51: 0 | L51: =IF(G51>0,G51-J51,"Invoiced this Month") -> 23396
A52: Glass Edge Inc.:51 Commons | B52: 83172 | C52: NE-C | D52: 02/28/2025 | E52: =VLOOKUP(B52,'[2]Month Total'!$B:$E,4,FALSE) -> 46003 | F52: =VLOOKUP(B52,'[2]Month Total'!$B:$F,5,FALSE) -> Powder coat | G52: 18356 | H52: =I52-G52 -> -29 | I52: 18327 | J52: 9164 | K52: =IF(G52=0,J52-G52,0) -> 0 | L52: =IF(G52>0,G52-J52,"Invoiced this Month") -> 9192
A53: Golden Glass Inc.:Pepperdine University | B53: 76624 | C53: CA-C | D53: 04/19/2024 | E53: 46038 | F53: =VLOOKUP(B53,'[2]Month Total'!$B:$F,5,FALSE) -> Pre-Production | G53: 82176 | H53: =I53-G53 -> 82176 | I53: 164352 | J53: 41088 | K53: =IF(G53=0,J53-G53,0) -> 0 | L53: =IF(G53>0,G53-J53,"Invoiced this Month") -> 41088
A54: GP Glass & Mirror LLC:Windows & Sliders | B54: 87296 | C54: NV-R | D54: 45937 | E54: =VLOOKUP(B54,'[2]Month Total'!$B:$E,4,FALSE) -> 45968 | F54: 46045 | G54: 0 | J54: 35000 | K54: =IF(G54=0,J54-G54,0) -> 35000 | L54: =IF(G54>0,G54-J54,"Invoiced this Month") -> Invoiced this Month
A55: Hardman Glazing Management LLC:Brown Shop | B55: 87128 | C55: ID-R | D55: 01/12/2026 | E55: Pre-Production | F55: Pre-Production | G55: 25470 | H55: =I55-G55 -> 25467 | I55: 50937 | J55: 0 | L55: =IF(G55>0,G55-J55,"Invoiced this Month") -> 25470
A56: Hasco Constrution:Sperryn Jones | B56: 82632 | C56: SN-R | D56: 04/11/2025 | E56: =VLOOKUP(B56,'[2]Month Total'!$B:$E,4,FALSE) -> Pre-Production | F56: =VLOOKUP(B56,'[2]Month Total'!$B:$F,5,FALSE) -> Pre-Production | G56: 99911 | H56: =I56-G56 -> 99911 | I56: 199822 | J56: 99911 | K56: =IF(G56=0,J56-G56,0) -> 0 | L56: =IF(G56>0,G56-J56,"Invoiced this Month") -> 0
A57: Heart of America Aston LLC:592 Aston | B57: 84210 | C57: IL-C | D57: 45876 | E57: =VLOOKUP(B57,'[2]Month Total'!$B:$E,4,FALSE) -> Pre-Production | F57: =VLOOKUP(B57,'[2]Month Total'!$B:$F,5,FALSE) -> Pre-Production | G57: 31567 | H57: =I57-G57 -> 46437 | I57: 78004 | J57: 31567 | K57: =IF(G57=0,J57-G57,0) -> 0 | L57: =IF(G57>0,G57-J57,"Invoiced this Month") -> 0
A58: Helou Construction:Rosebowl South Endzone Club | B58: 88433 | C58: CA-C | D58: 01/14/2026 | E58: Pre-Production | F58: Pre-Production | G58: 80538 | H58: =I58-G58 -> 80538 | I58: 161076 | J58: 0 | L58: =IF(G58>0,G58-J58,"Invoiced this Month") -> 80538
A59: Heritage Glass:DCI Pittock | B59: 87577 | C59: OR-C | D59: 01/16/2026 | E59: Pre-Production | F59: Pre-Production | G59: 11785 | H59: =I59-G59 -> 11782 | I59: 23567 | J59: 0 | L59: =IF(G59>0,G59-J59,"Invoiced this Month") -> 11785
A60: Ikirkpatrick Construction:Stewart Residence 3 | B60: 87792 | C60: HI-R | D60: 12/01/2025 | E60: 46045 | F60: =VLOOKUP(B60,'[2]Month Total'!$B:$F,5,FALSE) -> Pre-Production | G60: 49733 | H60: =I60-G60 -> 49713 | I60: 99446 | J60: 49733 | K60: =IF(G60=0,J60-G60,0) -> 0 | L60: =IF(G60>0,G60-J60,"Invoiced this Month") -> 0
A61: Image Builders Of Central Florida:Radius Finley Res | B61: 75830 | C61: FL-R | D61: 45834 | E61: =VLOOKUP(B61,'[2]Month Total'!$B:$E,4,FALSE) -> 45967 | F61: 46045 | G61: 0 | J61: 87339 | K61: =IF(G61=0,J61-G61,0) -> 87339 | L61: =IF(G61>0,G61-J61,"Invoiced this Month") -> Invoiced this Month
A62: Infinity Group:Wilson Residence 77 | B62: 85175 | C62: CT-R | D62: 45805 | E62: =VLOOKUP(B62,'[2]Month Total'!$B:$E,4,FALSE) -> 45992 | F62: 46052 | G62: 0 | J62: 280256 | K62: =IF(G62=0,J62-G62,0) -> 280256 | L62: =IF(G62>0,G62-J62,"Invoiced this Month") -> Invoiced this Month
A63: Integrated Glass Concepts, Inc:Diablo Valley College | B63: 87488 | C63: CA-C | D63: 12/16/2025 | E63: =VLOOKUP(B63,'[2]Month Total'!$B:$E,4,FALSE) -> Pre-Production | F63: =VLOOKUP(B63,'[2]Month Total'!$B:$F,5,FALSE) -> Pre-Production | G63: 17613 | H63: =I63-G63 -> 17612 | I63: 35225 | J63: 17613 | K63: =IF(G63=0,J63-G63,0) -> 0 | L63: =IF(G63>0,G63-J63,"Invoiced this Month") -> 0
A64: J Shuman Door Installation:Andrew Nguyen | B64: 86855 | C64: CA-R | D64: 45966 | E64: =VLOOKUP(B64,'[2]Month Total'!$B:$E,4,FALSE) -> 46020 | F64: =VLOOKUP(B64,'[2]Month Total'!$B:$F,5,FALSE) -> Powder coat | G64: 9717 | H64: =I64-G64 -> 9717 | I64: 19434 | J64: 9717 | K64: =IF(G64=0,J64-G64,0) -> 0 | L64: =IF(G64>0,G64-J64,"Invoiced this Month") -> 0
A65: J Shuman Door Installation:Liubov Residence | B65: 86415 | C65: CA-R | D65: 45951 | E65: =VLOOKUP(B65,'[2]Month Total'!$B:$E,4,FALSE) -> 46009 | F65: 46052 | G65: 0 | J65: 9678 | K65: =IF(G65=0,J65-G65,0) -> 9678 | L65: =IF(G65>0,G65-J65,"Invoiced this Month") -> Invoiced this Month
A66: Jackson Design Home Remodeling:Multi-Slide Corner | B66: 88258 | C66: CA-R | D66: 12/01/2025 | E66: =VLOOKUP(B66,'[2]Month Total'!$B:$E,4,FALSE) -> Pre-Production | F66: =VLOOKUP(B66,'[2]Month Total'!$B:$F,5,FALSE) -> Pre-Production | G66: 9467 | H66: =I66-G66 -> 9467 | I66: 18934 | J66: 9467 | K66: =IF(G66=0,J66-G66,0) -> 0 | L66: =IF(G66>0,G66-J66,"Invoiced this Month") -> 0
A67: Jonah Monroe:Monroe Residence | B67: 87636 | C67: MD-R | D67: 11/19/2025 | E67: =VLOOKUP(B67,'[2]Month Total'!$B:$E,4,FALSE) -> 46010 | F67: =VLOOKUP(B67,'[2]Month Total'!$B:$F,5,FALSE) -> On Hold Drawing Change/Cutting | G67: 45837 | H67: =I67-G67 -> 44121 | I67: 89958 | J67: 45837 | K67: =IF(G67=0,J67-G67,0) -> 0 | L67: =IF(G67>0,G67-J67,"Invoiced this Month") -> 0
A68: Jungsten Construction Inc.:TNT Project | B68: 87431 | C68: CA-R | D68: 45937 | E68: =VLOOKUP(B68,'[2]Month Total'!$B:$E,4,FALSE) -> 45995 | F68: 46052 | G68: 0 | J68: 12742 | K68: =IF(G68=0,J68-G68,0) -> 12742 | L68: =IF(G68>0,G68-J68,"Invoiced this Month") -> Invoiced this Month
A69: Keith Starkey:Starkey Residence | B69: 78503 | C69: NY-R | D69: 45825 | E69: =VLOOKUP(B69,'[2]Month Total'!$B:$E,4,FALSE) -> Pre-Production | F69: =VLOOKUP(B69,'[2]Month Total'!$B:$F,5,FALSE) -> Pre-Production | G69: 15815 | H69: =I69-G69 -> 15814 | I69: 31629 | J69: 15815 | K69: =IF(G69=0,J69-G69,0) -> 0 | L69: =IF(G69>0,G69-J69,"Invoiced this Month") -> 0
A70: Ken Caryl Glass:Barrett Residence | B70: 84268 | C70: CO-R | D70: 45870 | E70: =VLOOKUP(B70,'[2]Month Total'!$B:$E,4,FALSE) -> Pre-Production | F70: 46043 | G70: 0 | J70: 14024 | K70: =IF(G70=0,J70-G70,0) -> 14024 | L70: =IF(G70>0,G70-J70,"Invoiced this Month") -> Invoiced this Month
A71: Keystone Distribution:The Holland | B71: 87077 | C71: TX-R | D71: 01/30/2026 | E71: Pre-Production | F71: Pre-Production | G71: 11448 | H71: =I71-G71 -> 320 | I71: 11768 | J71: 0 | L71: =IF(G71>0,G71-J71,"Invoiced this Month") -> 11448
A72: L.P. Glazing & Consulting:San Ysidro | B72: 87242 | C72: CA-C | D72: 01/23/2026 | E72: Pre-Production | F72: Pre-Production | G72: 44650 | H72: =I72-G72 -> 45536 | I72: 90186 | J72: 0 | L72: =IF(G72>0,G72-J72,"Invoiced this Month") -> 44650
A73: Lake Glass:Hotel Bozeman | B73: 85352 | C73: MT-C | D73: 45952 | E73: =VLOOKUP(B73,'[2]Month Total'!$B:$E,4,FALSE) -> Pre-Production | F73: =VLOOKUP(B73,'[2]Month Total'!$B:$F,5,FALSE) -> Pre-Production | G73: 16954 | H73: =I73-G73 -> 53082 | I73: 70036 | J73: 16954 | K73: =IF(G73=0,J73-G73,0) -> 0 | L73: =IF(G73>0,G73-J73,"Invoiced this Month") -> 0
A74: Larry Walsh:Walsh Project | B74: 88618 | C74: NV-R | D74: 01/29/2026 | E74: Pre-Production | F74: Pre-Production | G74: 6845 | H74: =I74-G74 -> 6844 | I74: 13689 | J74: 0 | L74: =IF(G74>0,G74-J74,"Invoiced this Month") -> 6845
A75: Lindsay Glass Systems:Print Shop | B75: 87830 | C75: TX-C | D75: 46002 | E75: =VLOOKUP(B75,'[2]Month Total'!$B:$E,4,FALSE) -> Pre-Production | F75: =VLOOKUP(B75,'[2]Month Total'!$B:$F,5,FALSE) -> Pre-Production | G75: 7852 | H75: =I75-G75 -> 7852 | I75: 15704 | J75: 7852 | K75: =IF(G75=0,J75-G75,0) -> 0 | L75: =IF(G75>0,G75-J75,"Invoiced this Month") -> 0
A76: Lite Building Services:1420 King Street 6th Floor Ribbon Window | B76: 85604 | C76: VA-C | D76: 45881 | E76: =VLOOKUP(B76,'[2]Month Total'!$B:$E,4,FALSE) -> Pre-Production | F76: =VLOOKUP(B76,'[2]Month Total'!$B:$F,5,FALSE) -> Pre-Production | G76: 80676.28 | H76: =I76-G76 -> -4388.28 | I76: 76288 | J76: 80676.28 | K76: =IF(G76=0,J76-G76,0) -> 0 | L76: =IF(G76>0,G76-J76,"Invoiced this Month") -> 0
A77: LiveMetta Pilates:LiveMetta Encinitas | B77: 87595 | C77: CA-C | D77: 45959 | E77: =VLOOKUP(B77,'[2]Month Total'!$B:$E,4,FALSE) -> Pre-Production | F77: =VLOOKUP(B77,'[2]Month Total'!$B:$F,5,FALSE) -> Pre-Production | G77: 13979.5 | H77: =I77-G77 -> 13979.5 | I77: 27959 | J77: 13979.5 | K77: =IF(G77=0,J77-G77,0) -> 0 | L77: =IF(G77>0,G77-J77,"Invoiced this Month") -> 0
A78: Lunstrum Windows:ARE Fitness | B78: 88335 | C78: CA-C | D78: 12/04/2025 | E78: =VLOOKUP(B78,'[2]Month Total'!$B:$E,4,FALSE) -> Pre-Production | F78: =VLOOKUP(B78,'[2]Month Total'!$B:$F,5,FALSE) -> Pre-Production | G78: 21104 | H78: =I78-G78 -> 21104 | I78: 42208 | J78: 21104 | K78: =IF(G78=0,J78-G78,0) -> 0 | L78: =IF(G78>0,G78-J78,"Invoiced this Month") -> 0
A79: Lunstrum Windows:Park Summit | B79: 79059 | C79: CA-C | D79: 12/17/2024 | E79: =VLOOKUP(B79,'[2]Month Total'!$B:$E,4,FALSE) -> Pre-Production | F79: =VLOOKUP(B79,'[2]Month Total'!$B:$F,5,FALSE) -> Pre-Production | G79: 43711 | H79: =I79-G79 -> 131132 | I79: 174843 | J79: 43711 | K79: =IF(G79=0,J79-G79,0) -> 0 | L79: =IF(G79>0,G79-J79,"Invoiced this Month") -> 0
A80: Lunstrum Windows:Park Summit (2) | B80: 83698 | C80: CA-C | D80: 45904 | E80: =VLOOKUP(B80,'[2]Month Total'!$B:$E,4,FALSE) -> Pre-Production | F80: =VLOOKUP(B80,'[2]Month Total'!$B:$F,5,FALSE) -> Pre-Production | G80: 7860 | H80: =I80-G80 -> 6740 | I80: 14600 | J80: 7860 | K80: =IF(G80=0,J80-G80,0) -> 0 | L80: =IF(G80>0,G80-J80,"Invoiced this Month") -> 0
A81: Lunstrum Windows:Park Summit-1 | B81: 87641 | C81: CA-C | D81: 46013 | E81: =VLOOKUP(B81,'[2]Month Total'!$B:$E,4,FALSE) -> Pre-Production | F81: =VLOOKUP(B81,'[2]Month Total'!$B:$F,5,FALSE) -> Pre-Production | G81: 13019 | H81: =I81-G81 -> 13018 | I81: 26037 | J81: 13019 | K81: =IF(G81=0,J81-G81,0) -> 0 | L81: =IF(G81>0,G81-J81,"Invoiced this Month") -> 0
A82: M2M Logistics LLC:Kuau | B82: 86716 | C82: HI-R | D82: 08/27/2025 | E82: 45940 | F82: Sanding | G82: 71405 | H82: =I82-G82 -> 77624.32 | I82: 149029.32 | J82: 71405 | K82: =IF(G82=0,J82-G82,0) -> 0 | L82: =IF(G82>0,G82-J82,"Invoiced this Month") -> 0
A83: Marcel Martins:Laguna Doors | B83: 86292 | C83: CA-R | D83: 09/29/2025 | E83: =VLOOKUP(B83,'[2]Month Total'!$B:$E,4,FALSE) -> 45986 | F83: 46038 | G83: 0 | J83: 28000 | K83: =IF(G83=0,J83-G83,0) -> 28000 | L83: =IF(G83>0,G83-J83,"Invoiced this Month") -> Invoiced this Month
A84: Mark Industries LTD:Worth SD P27 | B84: 80858 | C84: IL-C | D84: 11/26/2024 | E84: =VLOOKUP(B84,'[2]Month Total'!$B:$E,4,FALSE) -> Pre-Production | F84: =VLOOKUP(B84,'[2]Month Total'!$B:$F,5,FALSE) -> Pre-Production | G84: 6843 | H84: =I84-G84 -> 6843 | I84: 13686 | J84: 6843 | K84: =IF(G84=0,J84-G84,0) -> 0 | L84: =IF(G84>0,G84-J84,"Invoiced this Month") -> 0
A85: Michelle Kay:The Kay Residence | B85: 86420 | C85: TX-R | D85: 45910 | E85: =VLOOKUP(B85,'[2]Month Total'!$B:$E,4,FALSE) -> 45992 | F85: =VLOOKUP(B85,'[2]Month Total'!$B:$F,5,FALSE) -> Cutting | G85: 120942 | H85: =I85-G85 -> 120942 | I85: 241884 | J85: 120942 | K85: =IF(G85=0,J85-G85,0) -> 0 | L85: =IF(G85>0,G85-J85,"Invoiced this Month") -> 0
A86: Midway Glass & Metal Installers, Inc.:Saddle River Day School | B86: 81326 | C86: NJ-C | D86: 04/28/2025 | E86: 46037 | F86: =VLOOKUP(B86,'[2]Month Total'!$B:$F,5,FALSE) -> Pre-Production | G86: 7693 | H86: =I86-G86 -> 7693 | I86: 15386 | J86: 7693 | K86: =IF(G86=0,J86-G86,0) -> 0 | L86: =IF(G86>0,G86-J86,"Invoiced this Month") -> 0
A87: MP Service:37 Painted Feather Way -77's Tracks | B87: 87704 | C87: NV-R | D87: 46001 | E87: 46034 | F87: =VLOOKUP(B87,'[2]Month Total'!$B:$F,5,FALSE) -> Pre-Production | G87: 11648.15 | H87: =I87-G87 -> 0 | I87: 11648.15 | J87: 11648.15 | K87: =IF(G87=0,J87-G87,0) -> 0 | L87: 11648.15
A88: Natural Domain Interiors, LLC:Brooks Project | B88: 86639 | C88: NV-R | D88: 01/08/2026 | E88: Pre-Production | F88: Pre-Production | G88: 29037 | H88: =I88-G88 -> 29037 | I88: 58074 | J88: 0 | L88: =IF(G88>0,G88-J88,"Invoiced this Month") -> 29037
A89: Nosan Signature Homes | B89: 86537 | C89: MI-R | D89: 01/22/2026 | E89: Pre-Production | F89: Pre-Production | G89: 10013 | H89: =I89-G89 -> 10012 | I89: 20025 | J89: 0 | L89: =IF(G89>0,G89-J89,"Invoiced this Month") -> 10013
A90: Onsite Products:Perrotta - Hoboken | B90: 80783 | C90: NJ-R | D90: 46003 | E90: 46031 | F90: =VLOOKUP(B90,'[2]Month Total'!$B:$F,5,FALSE) -> Pre-Production | G90: 7110 | H90: =I90-G90 -> 8595 | I90: 15705 | J90: 7110 | K90: =IF(G90=0,J90-G90,0) -> 0 | L90: =IF(G90>0,G90-J90,"Invoiced this Month") -> 0
A91: Orange Mirror and Glass:Kitchen / Bar | B91: 80262 | C91: CA-C | D91: 45855 | E91: 46038 | F91: =VLOOKUP(B91,'[2]Month Total'!$B:$F,5,FALSE) -> Pre-Production | G91: 5445 | H91: =I91-G91 -> 5446 | I91: 10891 | J91: 5445 | K91: =IF(G91=0,J91-G91,0) -> 0 | L91: =IF(G91>0,G91-J91,"Invoiced this Month") -> 0
A92: Pella Windows and Doors - OH:Edwards Steel Project | B92: 86090 | C92: OH-R | D92: 45936 | E92: =VLOOKUP(B92,'[2]Month Total'!$B:$E,4,FALSE) -> 45975 | F92: =VLOOKUP(B92,'[2]Month Total'!$B:$F,5,FALSE) -> Coating | G92: 50633.5 | H92: =I92-G92 -> 50633.5 | I92: 101267 | J92: 50633.5 | K92: =IF(G92=0,J92-G92,0) -> 0 | L92: =IF(G92>0,G92-J92,"Invoiced this Month") -> 0
A93: Phoenix Glass Company:Top of Crystal | B93: 87645 | C93: CA-C | D93: 45971 | E93: 46027 | F93: =VLOOKUP(B93,'[2]Month Total'!$B:$F,5,FALSE) -> Pre-Production | G93: 13500 | H93: =I93-G93 -> 10193 | I93: 23693 | J93: 13500 | K93: =IF(G93=0,J93-G93,0) -> 0 | L93: =IF(G93>0,G93-J93,"Invoiced this Month") -> 0
A94: PM Steel Fabrication, LLC:Empire Glass | B94: 87446 | C94: TX-C | D94: 45971 | E94: =VLOOKUP(B94,'[2]Month Total'!$B:$E,4,FALSE) -> Pre-Production | F94: =VLOOKUP(B94,'[2]Month Total'!$B:$F,5,FALSE) -> Pre-Production | G94: 20000 | H94: =I94-G94 -> 7230 | I94: 27230 | J94: 20000 | K94: =IF(G94=0,J94-G94,0) -> 0 | L94: =IF(G94>0,G94-J94,"Invoiced this Month") -> 0
A95: Polk Architectural:100 Lighthouse Dr | B95: 85104 | C95: TX-R | D95: 45922 | E95: =VLOOKUP(B95,'[2]Month Total'!$B:$E,4,FALSE) -> 46001 | F95: 46038 | G95: 0 | J95: 9299.5 | K95: =IF(G95=0,J95-G95,0) -> 9299.5 | L95: =IF(G95>0,G95-J95,"Invoiced this Month") -> Invoiced this Month
A96: Portalais:Micron B42 | B96: 86087 | C96: UT-C | D96: 09/30/2025 | E96: =VLOOKUP(B96,'[2]Month Total'!$B:$E,4,FALSE) -> Pre-Production | F96: =VLOOKUP(B96,'[2]Month Total'!$B:$F,5,FALSE) -> Pre-Production | G96: 16786 | H96: =I96-G96 -> 16786 | I96: 33572 | J96: 16786 | K96: =IF(G96=0,J96-G96,0) -> 0 | L96: =IF(G96>0,G96-J96,"Invoiced this Month") -> 0
A97: Precision Glass Co.:2340 Gamay | B97: 86944 | C97: CA-R | D97: 12/15/2025 | E97: 46030 | F97: =VLOOKUP(B97,'[2]Month Total'!$B:$F,5,FALSE) -> Pre-Production | G97: 10965 | H97: =I97-G97 -> 10965 | I97: 21930 | J97: 10965 | K97: =IF(G97=0,J97-G97,0) -> 0 | L97: =IF(G97>0,G97-J97,"Invoiced this Month") -> 0
A98: Prestige Island Exports:ADR Entry Pivot Door | B98: 80158 | C98: FL-R | D98: 10/09/2024 | E98: 45940 | F98: 46036 | G98: 0 | J98: 58887 | K98: =IF(G98=0,J98-G98,0) -> 58887 | L98: =IF(G98>0,G98-J98,"Invoiced this Month") -> Invoiced this Month
A99: Primary Glazing:Callan - Bldg B | B99: 88810 | C99: CA-C | D99: 01/28/2026 | E99: Pre-Production | F99: Pre-Production | G99: 22507 | H99: =I99-G99 -> 22506 | I99: 45013 | J99: 0 | L99: =IF(G99>0,G99-J99,"Invoiced this Month") -> 22507
A100: Progress Glass:1515 South Van Ness | B100: 81910 | C100: CA-C | D100: 45859 | E100: =VLOOKUP(B100,'[2]Month Total'!$B:$E,4,FALSE) -> Pre-Production | F100: =VLOOKUP(B100,'[2]Month Total'!$B:$F,5,FALSE) -> Pre-Production | G100: 13876 | H100: =I100-G100 -> 13875 | I100: 27751 | J100: 13876 | K100: =IF(G100=0,J100-G100,0) -> 0 | L100: =IF(G100>0,G100-J100,"Invoiced this Month") -> 0
...

Sheet Feb 26
A1: Customer | B1: Q Number | C1: Region | D1: Payment Date | E1: Production Start Day | F1: Stage | G1: DEPOSIT | H1: FINAL | I1: TOTAL | J1: BOM Dep | K1: Dep to Rev | L1: New Dep this Month
A2: Advanced Windows:1990 K Street | B2: 87616 | C2: MD-C | D2: 02/16/2026 | E2: Pre-Production | F2: Pre-Production | G2: 35586 | H2: =I2-G2 -> 9375 | I2: 44961 | J2: 0 | K2: =IF(G2=0,J2-G2,0) -> 0 | L2: =IF(G2>0,G2-J2,"Invoiced this Month") -> 35586
A3: Advanced Windows:Golden Hill | B3: 84541 | C3: MD-C | D3: 45943 | E3: Pre-Production | F3: Pre-Production | G3: 10262 | H3: =I3-G3 -> 10261 | I3: 20523 | J3: =VLOOKUP(A3,'Feb 26'!A:G,7,FALSE) -> 10262 | K3: =IF(G3=0,J3-G3,0) -> 0 | L3: =IF(G3>0,G3-J3,"Invoiced this Month") -> 0
A4: Akis Doganis:Doganis Residence | B4: 87185 | C4: NV-R | D4: 12/04/2025 | E4: Pre-Production | F4: Pre-Production | G4: 31515 | H4: =I4-G4 -> 31514 | I4: 63029 | J4: =VLOOKUP(A4,'Jan 26'!A:G,7,FALSE) -> 31515 | K4: =IF(G4=0,J4-G4,0) -> 0 | L4: =IF(G4>0,G4-J4,"Invoiced this Month") -> 0
A5: All New Glass:201 Fillmore | B5: 78377 | C5: WA-C | D5: 02/24/2025 | E5: 46007 | F5: Powder coat | G5: 342623.5 | H5: =I5-G5 -> 342623.5 | I5: 685247 | J5: =VLOOKUP(A5,'Jan 26'!A:G,7,FALSE) -> 342623.5 | K5: =IF(G5=0,J5-G5,0) -> 0 | L5: =IF(G5>0,G5-J5,"Invoiced this Month") -> 0
A6: All New Glass:201 Fillmore 1st Floor | B6: 86050 | C6: WA-C | D6: 45954 | E6: 46030 | F6: 46072 | G6: 0 | J6: =VLOOKUP(A6,'Jan 26'!A:G,7,FALSE) -> 68086 | K6: =IF(G6=0,J6-G6,0) -> 68086 | L6: =IF(G6>0,G6-J6,"Invoiced this Month") -> Invoiced this Month
A7: All New Glass:Chanel UTC | B7: 83846 | C7: WA-C | D7: 45880 | E7: 46076 | F7: Pre-Production | G7: =77743+30779.5 -> 108522.5 | H7: =I7-G7 -> 108521.5 | I7: 217044 | J7: =VLOOKUP(A7,'Jan 26'!A:G,7,FALSE) -> 77743 | K7: =IF(G7=0,J7-G7,0) -> 0 | L7: =IF(G7>0,G7-J7,"Invoiced this Month") -> 30779.5
A8: American Glass - Livermore:Sunset Clubhouse-2 | B8: 85639 | C8: CA-C | D8: 45805 | E8: 46015 | F8: Coating | G8: 11673 | H8: =I8-G8 -> 11672 | I8: 23345 | J8: =VLOOKUP(A8,'Jan 26'!A:G,7,FALSE) -> 11673 | K8: =IF(G8=0,J8-G8,0) -> 0 | L8: =IF(G8>0,G8-J8,"Invoiced this Month") -> 0
A9: American Products Inc (API):Lululemon Boston | B9: 86924 | C9: NA-C | D9: 45965 | E9: 46013 | F9: 46057 | G9: 0 | J9: =VLOOKUP(A9,'Jan 26'!A:G,7,FALSE) -> 40090 | K9: =IF(G9=0,J9-G9,0) -> 40090 | L9: =IF(G9>0,G9-J9,"Invoiced this Month") -> Invoiced this Month
A10: Aragon Construction, Inc.:Penta (1) Interior | B10: 84044 | C10: CA-C | D10: 45811 | E10: 46002 | F10: Cutting | G10: 93528 | H10: =I10-G10 -> -28848 | I10: 64680 | J10: =VLOOKUP(A10,'Jan 26'!A:G,7,FALSE) -> 93528 | K10: =IF(G10=0,J10-G10,0) -> 0 | L10: =IF(G10>0,G10-J10,"Invoiced this Month") -> 0
A11: Aragon Construction, Inc.:Penta (2) Exterior | B11: 84046 | C11: CA-C | D11: 45811 | E11: 46002 | F11: Cutting | G11: 97035 | H11: =I11-G11 -> 38165 | I11: 135200 | J11: =VLOOKUP(A11,'Jan 26'!A:G,7,FALSE) -> 97035 | K11: =IF(G11=0,J11-G11,0) -> 0 | L11: =IF(G11>0,G11-J11,"Invoiced this Month") -> 0
A12: Aragon Construction, Inc.:Puente Hills | B12: 82690 | C12: CA-C | D12: 11/17/2025 | E12: Pre-Production | F12: Pre-Production | G12: 13744 | H12: =I12-G12 -> 12649 | I12: 26393 | J12: =VLOOKUP(A12,'Jan 26'!A:G,7,FALSE) -> 13744 | K12: =IF(G12=0,J12-G12,0) -> 0 | L12: =IF(G12>0,G12-J12,"Invoiced this Month") -> 0
A13: Avatar Design Build LLC:Avatar Custom Home | B13: 84790 | C13: MD-R | D13: 45890 | E13: 45973 | F13: 46069 | G13: 0 | J13: =VLOOKUP(A13,'Jan 26'!A:G,7,FALSE) -> 37869 | K13: =IF(G13=0,J13-G13,0) -> 37869 | L13: =IF(G13>0,G13-J13,"Invoiced this Month") -> Invoiced this Month
A14: Barbara Bellio:Bellio Residence | B14: 87402 | C14: NV-R | D14: 45939 | E14: Pre-Production | F14: Pre-Production | G14: 20000 | H14: =I14-G14 -> 19516 | I14: 39516 | J14: =VLOOKUP(A14,'Jan 26'!A:G,7,FALSE) -> 20000 | K14: =IF(G14=0,J14-G14,0) -> 0 | L14: =IF(G14>0,G14-J14,"Invoiced this Month") -> 0
A15: Best Contracting LLC:UCSB San Benito Housing | B15: 87022 | C15: CA-C | D15: 11/20/2025 | E15: Pre-Production | F15: Pre-Production | G15: 60823 | H15: =I15-G15 -> 60822 | I15: 121645 | J15: =VLOOKUP(A15,'Jan 26'!A:G,7,FALSE) -> 60823 | K15: =IF(G15=0,J15-G15,0) -> 0 | L15: =IF(G15>0,G15-J15,"Invoiced this Month") -> 0
A16: Biery Cheese Company:Silo Radius | B16: 87104 | C16: OH-C | D16: 45939 | E16: 46072 | F16: Pre-Production | G16: 24528.82 | H16: =I16-G16 -> 0 | I16: 24528.82 | J16: =VLOOKUP(A16,'Jan 26'!A:G,7,FALSE) -> 24528.82 | K16: =IF(G16=0,J16-G16,0) -> 0 | L16: =IF(G16>0,G16-J16,"Invoiced this Month") -> 0
A17: BMG Door & Glass:Rowley | B17: 88961 | C17: AZ-R | D17: 46062 | E17: Pre-Production | F17: Pre-Production | G17: 22865 | H17: =I17-G17 -> 22864 | I17: 45729 | J17: 0 | K17: =IF(G17=0,J17-G17,0) -> 0 | L17: =IF(G17>0,G17-J17,"Invoiced this Month") -> 22865
A18: BMG Door & Glass:Zamora Residence | B18: 88921 | C18: NV-R | D18: 01/30/2026 | E18: Pre-Production | F18: Pre-Production | G18: 18436 | H18: =I18-G18 -> 18436 | I18: 36872 | J18: =VLOOKUP(A18,'Jan 26'!A:G,7,FALSE) -> 18436 | L18: =IF(G18>0,G18-J18,"Invoiced this Month") -> 0
A19: Brad Lager:Palmer | B19: 87591 | C19: MO-R | D19: 46058 | E19: Pre-Production | F19: Pre-Production | G19: 25317 | H19: =I19-G19 -> 25316 | I19: 50633 | J19: 0 | K19: =IF(G19=0,J19-G19,0) -> 0 | L19: =IF(G19>0,G19-J19,"Invoiced this Month") -> 25317
A20: Brett Hill Construction, Inc:4895 Kalanianaole | B20: 88674 | C20: HI-R | D20: 46055 | E20: Pre-Production | F20: Pre-Production | G20: 238760 | H20: =I20-G20 -> 238759 | I20: 477519 | J20: 0 | K20: =IF(G20=0,J20-G20,0) -> 0 | L20: =IF(G20>0,G20-J20,"Invoiced this Month") -> 238760
A21: Builders Direct Supply:4545 North-Studio | B21: 85791 | C21: CA-R | D21: 45959 | E21: Pre-Production | F21: Pre-Production | G21: 8977.7 | H21: =I21-G21 -> 80799.3 | I21: 89777 | J21: =VLOOKUP(A21,'Jan 26'!A:G,7,FALSE) -> 8977.7 | K21: =IF(G21=0,J21-G21,0) -> 0 | L21: =IF(G21>0,G21-J21,"Invoiced this Month") -> 0
A22: Builders Direct Supply:Direct Doors | B22: 87898 | C22: CA-R | D22: 45967 | E22: 46000 | F22: 46063 | G22: 0 | J22: =VLOOKUP(A22,'Jan 26'!A:G,7,FALSE) -> 6997.5 | K22: =IF(G22=0,J22-G22,0) -> 6997.5 | L22: =IF(G22>0,G22-J22,"Invoiced this Month") -> Invoiced this Month
A23: Builders Direct Supply:Larroque Door | B23: 88582 | C23: CA-R | D23: 02/16/2026 | E23: Pre-Production | F23: Pre-Production | G23: 4551 | H23: =I23-G23 -> 4551 | I23: 9102 | J23: 0 | K23: =IF(G23=0,J23-G23,0) -> 0 | L23: =IF(G23>0,G23-J23,"Invoiced this Month") -> 4551
A24: Builders Direct Supply:Marriott | B24: 88115 | C24: CA-C | D24: 46059 | E24: Pre-Production | F24: Pre-Production | G24: 62150.5 | H24: =I24-G24 -> 62150.5 | I24: 124301 | J24: 0 | K24: =IF(G24=0,J24-G24,0) -> 0 | L24: =IF(G24>0,G24-J24,"Invoiced this Month") -> 62150.5
A25: Builders Direct Supply:North 4545 | B25: 83690 | C25: CA-R | D25: 45959 | E25: Pre-Production | F25: Pre-Production | G25: 41681.4 | H25: =I25-G25 -> 375132.6 | I25: 416814 | J25: =VLOOKUP(A25,'Jan 26'!A:G,7,FALSE) -> 41681.4 | K25: =IF(G25=0,J25-G25,0) -> 0 | L25: =IF(G25>0,G25-J25,"Invoiced this Month") -> 0
A26: Builders Direct Supply:Snell and Wilmer | B26: 86318 | C26: CA-C | D26: 01/08/2026 | E26: Pre-Production | F26: Pre-Production | G26: 26483.5 | H26: =I26-G26 -> 26483.5 | I26: 52967 | J26: =VLOOKUP(A26,'Jan 26'!A:G,7,FALSE) -> 26483.5 | L26: =IF(G26>0,G26-J26,"Invoiced this Month") -> 0
A27: Builders FirstSource/Dixieline Lumber & Home Center:Jody Doors | B27: 88100 | C27: CA-R | D27: 12/29/2025 | E27: 46062 | F27: Pre-Production | G27: 8674 | H27: =I27-G27 -> 8673 | I27: 17347 | J27: =VLOOKUP(A27,'Jan 26'!A:G,7,FALSE) -> 8674 | K27: =IF(G27=0,J27-G27,0) -> 0 | L27: =IF(G27>0,G27-J27,"Invoiced this Month") -> 0
A28: Bulldog Diversified Construction:Bulldog Folding Door | B28: 88570 | C28: AZ-R | D28: 01/20/2026 | E28: 46055 | F28: 46077 | G28: 0 | J28: =VLOOKUP(A28,'Jan 26'!A:G,7,FALSE) -> 8743 | K28: =IF(G28=0,J28-G28,0) -> 8743 | L28: =IF(G28>0,G28-J28,"Invoiced this Month") -> Invoiced this Month
A29: C Thru Glass:Caesars Republic Pool Club Lounge | B29: 87633 | C29: NV-C | D29: 01/08/2026 | E29: 46072 | F29: Pre-Production | G29: 39028 | H29: =I29-G29 -> 39027 | I29: 78055 | J29: =VLOOKUP(A29,'Jan 26'!A:G,7,FALSE) -> 39028 | L29: =IF(G29>0,G29-J29,"Invoiced this Month") -> 0
A30: Capitol Glass & Aluminum Co.:Cypress Village | B30: 88240 | C30: FL-C | D30: 46062 | E30: Pre-Production | F30: Pre-Production | G30: 16435.5 | H30: =I30-G30 -> 16435.5 | I30: 32871 | J30: 0 | K30: =IF(G30=0,J30-G30,0) -> 0 | L30: =IF(G30>0,G30-J30,"Invoiced this Month") -> 16435.5
A31: Capitol Glass Company:99 Rhode Island | B31: 85440 | C31: CA-C | D31: 11/19/2025 | E31: 46044 | F31: Cutting | G31: 15439 | H31: =I31-G31 -> 15438 | I31: 30877 | J31: =VLOOKUP(A31,'Jan 26'!A:G,7,FALSE) -> 15439 | K31: =IF(G31=0,J31-G31,0) -> 0 | L31: =IF(G31>0,G31-J31,"Invoiced this Month") -> 0
A32: Capitol Glass Company:Sunnydale Block 7 | B32: 88227 | C32: CA-C | D32: 12/29/2025 | E32: Pre-Production | F32: Pre-Production | G32: 32005 | H32: =I32-G32 -> 32005 | I32: 64010 | J32: =VLOOKUP(A32,'Jan 26'!A:G,7,FALSE) -> 32005 | K32: =IF(G32=0,J32-G32,0) -> 0 | L32: =IF(G32>0,G32-J32,"Invoiced this Month") -> 0
A33: Caribbean Windows International:Seagrapes 2 | B33: 87308 | C33: CAR-R | D33: 45918 | E33: 45996 | F33: 46071 | G33: 0 | J33: =VLOOKUP(A33,'Jan 26'!A:G,7,FALSE) -> 57207 | K33: =IF(G33=0,J33-G33,0) -> 57207 | L33: =IF(G33>0,G33-J33,"Invoiced this Month") -> Invoiced this Month
A34: Catalyst Acoustics Group | B34: Unknown | D34: 05/31/2022 | E34: Pre-Production | F34: Pre-Production | G34: 4108 | H34: =I34-G34 -> 0 | I34: 4108 | J34: =VLOOKUP(A34,'Jan 26'!A:G,7,FALSE) -> 4108 | K34: =IF(G34=0,J34-G34,0) -> 0 | L34: =IF(G34>0,G34-J34,"Invoiced this Month") -> 0
A35: Cheryl Partee:Partee Residence | B35: 86866 | C35: CA-R | D35: 11/25/2025 | E35: 46015 | F35: 46072 | G35: 0 | J35: =VLOOKUP(A35,'Jan 26'!A:G,7,FALSE) -> 12000 | K35: =IF(G35=0,J35-G35,0) -> 12000 | L35: =IF(G35>0,G35-J35,"Invoiced this Month") -> Invoiced this Month
A36: Chris & Kareen Brown:By Woods Door | B36: 86825 | C36: MD-R | D36: 02/23/2026 | E36: Pre-Production | F36: Pre-Production | G36: 6409 | H36: =I36-G36 -> 6408 | I36: 12817 | J36: 0 | K36: =IF(G36=0,J36-G36,0) -> 0 | L36: =IF(G36>0,G36-J36,"Invoiced this Month") -> 6409
A37: CK2 Contracting:1221 W. Washington | B37: 88868 | C37: IL-R | D37: 46059 | E37: Pre-Production | F37: Pre-Production | G37: 17321 | H37: =I37-G37 -> 17321 | I37: 34642 | J37: 0 | K37: =IF(G37=0,J37-G37,0) -> 0 | L37: =IF(G37>0,G37-J37,"Invoiced this Month") -> 17321
A38: Classic Carpentry Inc.:CC Project / 262 Mermaid's Bight | B38: 88131 | C38: FL-R | D38: 01/20/2026 | E38: 46076 | F38: Pre-Production | G38: 33237 | H38: =I38-G38 -> 33236 | I38: 66473 | J38: =VLOOKUP(A38,'Jan 26'!A:G,7,FALSE) -> 33237 | L38: =IF(G38>0,G38-J38,"Invoiced this Month") -> 0
A39: Coltin Craigo:Alphorn Road | B39: 87218 | C39: WI-R | D39: 12/19/2025 | E39: 46028 | F39: Assembly | G39: 7433 | H39: =I39-G39 -> 7432 | I39: 14865 | J39: =VLOOKUP(A39,'Jan 26'!A:G,7,FALSE) -> 7433 | K39: =IF(G39=0,J39-G39,0) -> 0 | L39: =IF(G39>0,G39-J39,"Invoiced this Month") -> 0
A40: Constructa:Nuevo Proyecto en Punta Mita | B40: 83937 | C40: MX-C | D40: 11/20/2025 | E40: 46071 | F40: Pre-Production | G40: 59570.5 | H40: =I40-G40 -> 59590.5 | I40: 119161 | J40: =VLOOKUP(A40,'Jan 26'!A:G,7,FALSE) -> 59570.5 | K40: =IF(G40=0,J40-G40,0) -> 0 | L40: =IF(G40>0,G40-J40,"Invoiced this Month") -> 0
A41: Crystal Glass Inc.:New Logan Elementry | B41: 83108 | C41: MI-C | D41: 04/17/2025 | E41: Pre-Production | F41: Pre-Production | G41: 172204.5 | H41: =I41-G41 -> 172204.5 | I41: 344409 | J41: =VLOOKUP(A41,'Jan 26'!A:G,7,FALSE) -> 172204.5 | K41: =IF(G41=0,J41-G41,0) -> 0 | L41: =IF(G41>0,G41-J41,"Invoiced this Month") -> 0
A42: D & R Glass:Cedar and Sage | B42: 84134 | C42: CA-C | D42: 45945 | E42: Pre-Production | F42: Pre-Production | G42: 64205 | H42: =I42-G42 -> 61477 | I42: 125682 | J42: =VLOOKUP(A42,'Jan 26'!A:G,7,FALSE) -> 64205 | K42: =IF(G42=0,J42-G42,0) -> 0 | L42: =IF(G42>0,G42-J42,"Invoiced this Month") -> 0
A43: D&A Glass:Camas Grill T.I. | B43: 87768 | C43: ID-C | D43: 45971 | E43: 46000 | F43: 46064 | J43: =VLOOKUP(A43,'Jan 26'!A:G,7,FALSE) -> 25537 | K43: =IF(G43=0,J43-G43,0) -> 25537 | L43: =IF(G43>0,G43-J43,"Invoiced this Month") -> Invoiced this Month
A44: D&A Glass:Turf Club | B44: 87822 | C44: ID-C | D44: 11/24/2025 | E44: 46001 | F44: 46058 | G44: 0 | J44: =VLOOKUP(A44,'Jan 26'!A:G,7,FALSE) -> 115956 | K44: =IF(G44=0,J44-G44,0) -> 115956 | L44: =IF(G44>0,G44-J44,"Invoiced this Month") -> Invoiced this Month
A45: David Ostrander:Ostrander Residence Remodel | B45: 88087 | C45: MN-R | D45: 02/11/2026 | E45: Pre-Production | F45: Pre-Production | G45: 123085 | H45: =I45-G45 -> 123084 | I45: 246169 | J45: 0 | K45: =IF(G45=0,J45-G45,0) -> 0 | L45: =IF(G45>0,G45-J45,"Invoiced this Month") -> 123085
A46: David Shuldiner Inc:450 Lexington | B46: 83623 | C46: NY-C | D46: 45859 | E46: 46020 | F46: Coating | G46: 75227 | H46: =I46-G46 -> 75226 | I46: 150453 | J46: =VLOOKUP(A46,'Jan 26'!A:G,7,FALSE) -> 75227 | K46: =IF(G46=0,J46-G46,0) -> 0 | L46: =IF(G46>0,G46-J46,"Invoiced this Month") -> 0
A47: Debbie Piliero:46 Upper Rd | B47: 87161 | C47: CA-R | D47: 45924 | E47: 45992 | F47: Pull Material | G47: 17417 | H47: =I47-G47 -> 17417 | I47: 34834 | J47: =VLOOKUP(A47,'Jan 26'!A:G,7,FALSE) -> 17417 | K47: =IF(G47=0,J47-G47,0) -> 0 | L47: =IF(G47>0,G47-J47,"Invoiced this Month") -> 0
A48: Desert Window Systems:Lennar | B48: 88180 | C48: NV-R | D48: 02/25/2026 | E48: Pre-Production | F48: Pre-Production | G48: 38957 | H48: =I48-G48 -> 38957 | I48: 77914 | J48: 0 | K48: =IF(G48=0,J48-G48,0) -> 0 | L48: =IF(G48>0,G48-J48,"Invoiced this Month") -> 38957
A49: DGB Glass Inc.:Hotel Grey | B49: 86965 | C49: TX-C | D49: 45924 | E49: 46048 | F49: Pull Material | G49: 49026 | H49: =I49-G49 -> 51328 | I49: 100354 | J49: =VLOOKUP(A49,'Jan 26'!A:G,7,FALSE) -> 49026 | K49: =IF(G49=0,J49-G49,0) -> 0 | L49: =IF(G49>0,G49-J49,"Invoiced this Month") -> 0
A50: Doors, Etc.:Doors Etc HSW | B50: 88511 | C50: CA-R | D50: 02/19/2026 | E50: Pre-Production | F50: Pre-Production | G50: 19222 | H50: =I50-G50 -> 19222 | I50: 38444 | J50: 0 | K50: =IF(G50=0,J50-G50,0) -> 0 | L50: =IF(G50>0,G50-J50,"Invoiced this Month") -> 19222
A51: Dugally Oberfeld, Inc.:Cox | B51: 83729 | C51: CA-R | D51: 01/06/2026 | E51: Pre-Production | F51: Pre-Production | G51: 31223 | H51: =I51-G51 -> 27501 | I51: 58724 | J51: =VLOOKUP(A51,'Jan 26'!A:G,7,FALSE) -> 31223 | L51: =IF(G51>0,G51-J51,"Invoiced this Month") -> 0
A52: E & Z Glass & Window:Sfondrini Residence | B52: 88210 | C52: TX-R | D52: 12/02/2025 | E52: 46015 | F52: 46069 | G52: 0 | J52: =VLOOKUP(A52,'Jan 26'!A:G,7,FALSE) -> 14200 | K52: =IF(G52=0,J52-G52,0) -> 14200 | L52: =IF(G52>0,G52-J52,"Invoiced this Month") -> Invoiced this Month
A53: Eagle Glass Service LLC:Bullard King | B53: 86439 | C53: CO-R | D53: 45964 | E53: 46015 | F53: 46062 | G53: 0 | J53: =VLOOKUP(A53,'Jan 26'!A:G,7,FALSE) -> 54101 | K53: =IF(G53=0,J53-G53,0) -> 54101 | L53: =IF(G53>0,G53-J53,"Invoiced this Month") -> Invoiced this Month
A54: EAP Glass:4th Street North Apts | B54: 85454 | C54: CO-C | D54: 12/30/2025 | E54: 46044 | F54: Sanding | G54: 14438 | H54: =I54-G54 -> 14438 | I54: 28876 | J54: =VLOOKUP(A54,'Jan 26'!A:G,7,FALSE) -> 14438 | K54: =IF(G54=0,J54-G54,0) -> 0 | L54: =IF(G54>0,G54-J54,"Invoiced this Month") -> 0
A55: Elaine Fitzpatrick:Fitzpatrick Residence | B55: 85838 | C55: NV-R | D55: 01/23/2026 | E55: 46077 | F55: Pre-Production | G55: 3386 | H55: =I55-G55 -> 3385 | I55: 6771 | J55: =VLOOKUP(A55,'Jan 26'!A:G,7,FALSE) -> 3386 | L55: =IF(G55>0,G55-J55,"Invoiced this Month") -> 0
A56: Element Facades 13:299 MILWAUKEE | B56: 86960 | C56: CO-C | D56: 11/25/2025 | E56: Pre-Production | F56: Pre-Production | G56: 8962 | H56: =I56-G56 -> 26885 | I56: 35847 | J56: =VLOOKUP(A56,'Jan 26'!A:G,7,FALSE) -> 8962 | K56: =IF(G56=0,J56-G56,0) -> 0 | L56: =IF(G56>0,G56-J56,"Invoiced this Month") -> 0
A57: Emerald Glass:The Frank | B57: 84692 | C57: WA-C | D57: 02/23/2026 | E57: Pre-Production | F57: Pre-Production | G57: 5345 | H57: =I57-G57 -> 5344 | I57: 10689 | J57: 0 | K57: =IF(G57=0,J57-G57,0) -> 0 | L57: =IF(G57>0,G57-J57,"Invoiced this Month") -> 5345
A58: Environmental Glass Inc:Ann Arbor Thurston | B58: 84161 | C58: MI-C | D58: 46013 | E58: Pre-Production | F58: Pre-Production | G58: 46821.92 | H58: =I58-G58 -> 306551.08 | I58: 353373
A59: Environmental Glass Inc:Mitchell Elementary | B59: 81492-R1 | C59: MI-C | D59: 45868 | E59: Pre-Production | F59: Pre-Production | G59: 57487 | H59: =I59-G59 -> 172460 | I59: 229947 | J59: =VLOOKUP(A59,'Jan 26'!A:G,7,FALSE) -> 57487 | K59: =IF(G59=0,J59-G59,0) -> 0 | L59: =IF(G59>0,G59-J59,"Invoiced this Month") -> 0
A60: Fast Glass:Brockway | B60: 87121 | C60: NV-R | D60: 12/19/2025 | E60: 46079 | F60: Pre-Production | G60: 8901 | H60: =I60-G60 -> 0 | I60: 8901 | J60: =VLOOKUP(A60,'Jan 26'!A:G,7,FALSE) -> 8901 | K60: =IF(G60=0,J60-G60,0) -> 0 | L60: =IF(G60>0,G60-J60,"Invoiced this Month") -> 0
A61: Ford Metro Inc:Chapter / Ann Arbor | B61: 87492 | C61: MN-R | D61: 02/10/2026 | E61: Pre-Production | F61: Pre-Production | G61: 22079 | H61: =I61-G61 -> 22079 | I61: 44158 | J61: 0 | K61: =IF(G61=0,J61-G61,0) -> 0 | L61: =IF(G61>0,G61-J61,"Invoiced this Month") -> 22079
A62: Franklin Herbas:Herbas Folding | B62: 89313 | C62: CA-R | D62: 02/26/2026 | E62: Pre-Production | F62: Pre-Production | G62: 8773 | H62: =I62-G62 -> 8773 | I62: 17546 | J62: 0 | K62: =IF(G62=0,J62-G62,0) -> 0 | L62: =IF(G62>0,G62-J62,"Invoiced this Month") -> 8773
A63: Gen 3 Hospitality:Richardson House | B63: 88603 | C63: NV-R | D63: 01/06/2026 | E63: Pre-Production | F63: Pre-Production | G63: 23396 | H63: =I63-G63 -> 23396 | I63: 46792 | J63: =VLOOKUP(A63,'Jan 26'!A:G,7,FALSE) -> 23396 | L63: =IF(G63>0,G63-J63,"Invoiced this Month") -> 0
A64: Giroux Glass:SoCalGas Loggia | B64: 88082 | C64: CA-C | D64: 02/23/2026 | E64: Pre-Production | F64: Pre-Production | G64: 35295 | H64: =I64-G64 -> 35294 | I64: 70589 | J64: 0 | K64: =IF(G64=0,J64-G64,0) -> 0 | L64: =IF(G64>0,G64-J64,"Invoiced this Month") -> 35295
A65: Glass Edge Inc.:51 Commons | B65: 83172 | C65: NE-C | D65: 02/28/2025 | E65: 46003 | F65: 46057 | G65: 0 | J65: =VLOOKUP(A65,'Jan 26'!A:G,7,FALSE) -> 18356 | K65: =IF(G65=0,J65-G65,0) -> 18356 | L65: =IF(G65>0,G65-J65,"Invoiced this Month") -> Invoiced this Month
A66: Golden Glass Inc.:Pepperdine University | B66: 76624 | C66: CA-C | D66: 04/19/2024 | E66: 46038 | F66: Coating | G66: 82176 | H66: =I66-G66 -> 82176 | I66: 164352 | J66: =VLOOKUP(A66,'Jan 26'!A:G,7,FALSE) -> 82176 | K66: =IF(G66=0,J66-G66,0) -> 0 | L66: =IF(G66>0,G66-J66,"Invoiced this Month") -> 0
A67: GP Glass & Mirror LLC:George_Additional Windows | B67: 89187 | C67: NV-R | D67: 02/26/2026 | E67: Pre-Production | F67: Pre-Production | G67: 3000 | H67: =I67-G67 -> 3288 | I67: 6288 | J67: 0 | K67: =IF(G67=0,J67-G67,0) -> 0 | L67: =IF(G67>0,G67-J67,"Invoiced this Month") -> 3000
A68: Hardman Glazing Management LLC:Brown Shop | B68: 87128 | C68: ID-R | D68: 01/12/2026 | E68: Pre-Production | F68: Pre-Production | G68: 25470 | H68: =I68-G68 -> 25467 | I68: 50937 | J68: =VLOOKUP(A68,'Jan 26'!A:G,7,FALSE) -> 25470 | L68: =IF(G68>0,G68-J68,"Invoiced this Month") -> 0
A69: Hardman Glazing Management LLC:Hinged Door | B69: 89121 | C69: CA-R | D69: 46062 | E69: Pre-Production | F69: Pre-Production | G69: 2712 | H69: =I69-G69 -> 3336 | I69: 6048 | J69: 0 | K69: =IF(G69=0,J69-G69,0) -> 0 | L69: =IF(G69>0,G69-J69,"Invoiced this Month") -> 2712
A70: Hasco Constrution:Sperryn Jones | B70: 82632 | C70: SN-R | D70: 04/11/2025 | E70: Pre-Production | F70: Pre-Production | G70: 99911 | H70: =I70-G70 -> 99911 | I70: 199822 | J70: =VLOOKUP(A70,'Jan 26'!A:G,7,FALSE) -> 99911 | K70: =IF(G70=0,J70-G70,0) -> 0 | L70: =IF(G70>0,G70-J70,"Invoiced this Month") -> 0
A71: Heart of America Aston LLC:592 Aston | B71: 84210 | C71: IL-C | D71: 45876 | E71: Pre-Production | F71: Pre-Production | G71: 31567 | H71: =I71-G71 -> 46437 | I71: 78004 | J71: =VLOOKUP(A71,'Jan 26'!A:G,7,FALSE) -> 31567 | K71: =IF(G71=0,J71-G71,0) -> 0 | L71: =IF(G71>0,G71-J71,"Invoiced this Month") -> 0
A72: Helou Construction:Rosebowl South Endzone Club | B72: 88433 | C72: CA-C | D72: 01/14/2026 | E72: Pre-Production | F72: Pre-Production | G72: 80538 | H72: =I72-G72 -> 80538 | I72: 161076 | J72: =VLOOKUP(A72,'Jan 26'!A:G,7,FALSE) -> 80538 | L72: =IF(G72>0,G72-J72,"Invoiced this Month") -> 0
A73: Henry Grause:Grause Residence | B73: 88896 | C73: FL-R | D73: 46058 | E73: Pre-Production | F73: Pre-Production | G73: 10238 | H73: =I73-G73 -> 10237 | I73: 20475 | J73: 0 | K73: =IF(G73=0,J73-G73,0) -> 0 | L73: =IF(G73>0,G73-J73,"Invoiced this Month") -> 10238
A74: Heritage Glass:DCI Pittock | B74: 87577 | C74: OR-C | D74: 01/16/2026 | E74: 46072 | F74: Pre-Production | G74: 11785 | H74: =I74-G74 -> 11782 | I74: 23567 | J74: =VLOOKUP(A74,'Jan 26'!A:G,7,FALSE) -> 11785 | L74: =IF(G74>0,G74-J74,"Invoiced this Month") -> 0
A75: Ikirkpatrick Construction:Stewart Residence 3 | B75: 87792 | C75: HI-R | D75: 12/01/2025 | E75: 46045 | F75: Pull Material | G75: 49733 | H75: =I75-G75 -> 49713 | I75: 99446 | J75: =VLOOKUP(A75,'Jan 26'!A:G,7,FALSE) -> 49733 | K75: =IF(G75=0,J75-G75,0) -> 0 | L75: =IF(G75>0,G75-J75,"Invoiced this Month") -> 0
A76: Integrated Glass Concepts, Inc:Diablo Valley College | B76: 87488 | C76: CA-C | D76: 12/16/2025 | E76: Pre-Production | F76: Pre-Production | G76: 17613 | H76: =I76-G76 -> 17612 | I76: 35225 | J76: =VLOOKUP(A76,'Jan 26'!A:G,7,FALSE) -> 17613 | K76: =IF(G76=0,J76-G76,0) -> 0 | L76: =IF(G76>0,G76-J76,"Invoiced this Month") -> 0
A77: J Shuman Door Installation:Andrew Nguyen | B77: 86855 | C77: CA-R | D77: 45966 | E77: 46020 | F77: 46065 | G77: 0 | J77: =VLOOKUP(A77,'Jan 26'!A:G,7,FALSE) -> 9717 | K77: =IF(G77=0,J77-G77,0) -> 9717 | L77: =IF(G77>0,G77-J77,"Invoiced this Month") -> Invoiced this Month
A78: Jackson Design Home Remodeling:Multi-Slide Corner | B78: 88258 | C78: CA-R | D78: 12/01/2025 | E78: 46064 | F78: Pre-Production | G78: 9467 | H78: =I78-G78 -> 9467 | I78: 18934 | J78: =VLOOKUP(A78,'Jan 26'!A:G,7,FALSE) -> 9467 | K78: =IF(G78=0,J78-G78,0) -> 0 | L78: =IF(G78>0,G78-J78,"Invoiced this Month") -> 0
A79: Jonah Monroe:Monroe Residence | B79: 87636 | C79: MD-R | D79: 11/19/2025 | E79: 46010 | F79: Pull Material | G79: 45837 | H79: =I79-G79 -> 44121 | I79: 89958 | J79: =VLOOKUP(A79,'Jan 26'!A:G,7,FALSE) -> 45837 | K79: =IF(G79=0,J79-G79,0) -> 0 | L79: =IF(G79>0,G79-J79,"Invoiced this Month") -> 0
A80: Keith Starkey:Starkey Residence | B80: 78503 | C80: NY-R | D80: 45825 | E80: Pre-Production | F80: Pre-Production | G80: 15815 | H80: =I80-G80 -> 15814 | I80: 31629 | J80: =VLOOKUP(A80,'Jan 26'!A:G,7,FALSE) -> 15815 | K80: =IF(G80=0,J80-G80,0) -> 0 | L80: =IF(G80>0,G80-J80,"Invoiced this Month") -> 0
A81: Keystone Distribution:The Holland | B81: 87077 | C81: TX-R | D81: 01/30/2026 | E81: Pre-Production | F81: Pre-Production | G81: 11448 | H81: =I81-G81 -> 3238 | I81: 14686 | J81: =VLOOKUP(A81,'Jan 26'!A:G,7,FALSE) -> 11448 | L81: =IF(G81>0,G81-J81,"Invoiced this Month") -> 0
A82: L.P. Glazing & Consulting:San Ysidro | B82: 87242 | C82: CA-C | D82: 01/23/2026 | E82: Pre-Production | F82: Pre-Production | G82: 44650 | H82: =I82-G82 -> 45536 | I82: 90186 | J82: =VLOOKUP(A82,'Jan 26'!A:G,7,FALSE) -> 44650 | L82: =IF(G82>0,G82-J82,"Invoiced this Month") -> 0
A83: Lake Glass:Hotel Bozeman | B83: 85352 | C83: MT-C | D83: 45952 | E83: 46065 | F83: Pre-Production | G83: =16954+18064 -> 35018 | H83: =I83-G83 -> 35018 | I83: 70036 | J83: =VLOOKUP(A83,'Jan 26'!A:G,7,FALSE) -> 16954 | K83: =IF(G83=0,J83-G83,0) -> 0 | L83: =IF(G83>0,G83-J83,"Invoiced this Month") -> 18064
A84: Larry Walsh:Walsh Project | B84: 88618 | C84: NV-R | D84: 01/29/2026 | E84: Pre-Production | F84: Pre-Production | G84: 6845 | H84: =I84-G84 -> 6844 | I84: 13689 | J84: =VLOOKUP(A84,'Jan 26'!A:G,7,FALSE) -> 6845 | L84: =IF(G84>0,G84-J84,"Invoiced this Month") -> 0
A85: Lindsay Glass Systems:Print Shop | B85: 87830 | C85: TX-C | D85: 46002 | E85: 46069 | F85: Pre-Production | G85: 7852 | H85: =I85-G85 -> 7852 | I85: 15704 | J85: =VLOOKUP(A85,'Jan 26'!A:G,7,FALSE) -> 7852 | K85: =IF(G85=0,J85-G85,0) -> 0 | L85: =IF(G85>0,G85-J85,"Invoiced this Month") -> 0
A86: Lite Building Services:1420 King Street 6th Floor Ribbon Window | B86: 85604 | C86: VA-C | D86: 45881 | E86: Pre-Production | F86: Pre-Production | G86: 80676.28 | H86: =I86-G86 -> -4388.28 | I86: 76288 | J86: =VLOOKUP(A86,'Jan 26'!A:G,7,FALSE) -> 80676.28 | K86: =IF(G86=0,J86-G86,0) -> 0 | L86: =IF(G86>0,G86-J86,"Invoiced this Month") -> 0
A87: LiveMetta Pilates:LiveMetta Encinitas | B87: 87595 | C87: CA-C | D87: 45959 | E87: 46077 | F87: Pre-Production | G87: 13979.5 | H87: =I87-G87 -> 13979.5 | I87: 27959 | J87: =VLOOKUP(A87,'Jan 26'!A:G,7,FALSE) -> 13979.5 | K87: =IF(G87=0,J87-G87,0) -> 0 | L87: =IF(G87>0,G87-J87,"Invoiced this Month") -> 0
A88: Lunstrum Windows:ARE Fitness | B88: 88335 | C88: CA-C | D88: 12/04/2025 | E88: 46055 | F88: Pre-Production | G88: 21104 | H88: =I88-G88 -> 21104 | I88: 42208 | J88: =VLOOKUP(A88,'Jan 26'!A:G,7,FALSE) -> 21104 | K88: =IF(G88=0,J88-G88,0) -> 0 | L88: =IF(G88>0,G88-J88,"Invoiced this Month") -> 0
A89: Lunstrum Windows:Park Summit | B89: 79059 | C89: CA-C | D89: 12/17/2024 | E89: 46057 | F89: Pre-Production | G89: 43711 | H89: =I89-G89 -> 131132 | I89: 174843 | J89: =VLOOKUP(A89,'Jan 26'!A:G,7,FALSE) -> 43711 | K89: =IF(G89=0,J89-G89,0) -> 0 | L89: =IF(G89>0,G89-J89,"Invoiced this Month") -> 0
A90: Lunstrum Windows:Park Summit (2) | B90: 83698 | C90: CA-C | D90: 45904 | E90: 46057 | F90: Pre-Production | G90: 7860 | H90: =I90-G90 -> 6740 | I90: 14600 | J90: =VLOOKUP(A90,'Jan 26'!A:G,7,FALSE) -> 7860 | K90: =IF(G90=0,J90-G90,0) -> 0 | L90: =IF(G90>0,G90-J90,"Invoiced this Month") -> 0
A91: Lunstrum Windows:Park Summit-1 | B91: 87641 | C91: CA-C | D91: 46013 | E91: Pre-Production | F91: Pre-Production | G91: 13019 | H91: =I91-G91 -> 13018 | I91: 26037 | J91: =VLOOKUP(A91,'Jan 26'!A:G,7,FALSE) -> 13019 | K91: =IF(G91=0,J91-G91,0) -> 0 | L91: =IF(G91>0,G91-J91,"Invoiced this Month") -> 0
A92: M2M Logistics LLC:Kuau | B92: 86716 | C92: HI-R | D92: 08/27/2025 | E92: 45940 | F92: 46057 | G92: 0 | J92: =VLOOKUP(A92,'Jan 26'!A:G,7,FALSE) -> 71405 | K92: =IF(G92=0,J92-G92,0) -> 71405 | L92: =IF(G92>0,G92-J92,"Invoiced this Month") -> Invoiced this Month
A93: Mark Industries LTD:Worth SD P27 | B93: 80858 | C93: IL-C | D93: 11/26/2024 | E93: Pre-Production | F93: Pre-Production | G93: 6843 | H93: =I93-G93 -> 6843 | I93: 13686 | J93: =VLOOKUP(A93,'Jan 26'!A:G,7,FALSE) -> 6843 | K93: =IF(G93=0,J93-G93,0) -> 0 | L93: =IF(G93>0,G93-J93,"Invoiced this Month") -> 0
A94: Mazzarino Construction & Development, LTD:Park City Project | B94: 87078 | C94: UT-R | D94: 02/11/2026 | E94: Pre-Production | F94: Pre-Production | G94: 12457 | H94: =I94-G94 -> 12457 | I94: 24914 | J94: 0 | K94: =IF(G94=0,J94-G94,0) -> 0 | L94: =IF(G94>0,G94-J94,"Invoiced this Month") -> 12457
A95: Merlin Custom Home Builders:Rumbolz | B95: 86134 | C95: NV-R | D95: 02/17/2026 | E95: Pre-Production | F95: Pre-Production | G95: 5151 | H95: =I95-G95 -> 12016 | I95: 17167 | J95: 0 | K95: =IF(G95=0,J95-G95,0) -> 0 | L95: =IF(G95>0,G95-J95,"Invoiced this Month") -> 5151
A96: Mesa Properties:4901 Lakeshore Dr. | B96: 87824 | C96: CO-R | D96: 02/26/2026 | E96: Pre-Production | F96: Pre-Production | G96: 109880 | H96: =I96-G96 -> 109880 | I96: 219760 | J96: 0 | K96: =IF(G96=0,J96-G96,0) -> 0 | L96: =IF(G96>0,G96-J96,"Invoiced this Month") -> 109880
A97: Michelle Kay:The Kay Residence | B97: 86420 | C97: TX-R | D97: 45910 | E97: 45992 | F97: 46062 | G97: 0 | J97: =VLOOKUP(A97,'Jan 26'!A:G,7,FALSE) -> 120942 | K97: =IF(G97=0,J97-G97,0) -> 120942 | L97: =IF(G97>0,G97-J97,"Invoiced this Month") -> Invoiced this Month
A98: Midway Glass & Metal Installers, Inc.:Saddle River Day School | B98: 81326 | C98: NJ-C | D98: 04/28/2025 | E98: 46037 | F98: 46058 | G98: 0 | J98: =VLOOKUP(A98,'Jan 26'!A:G,7,FALSE) -> 7693 | K98: =IF(G98=0,J98-G98,0) -> 7693 | L98: =IF(G98>0,G98-J98,"Invoiced this Month") -> Invoiced this Month
A99: MP Service:37 Painted Feather Way -77's Tracks | B99: 87704 | C99: NV-R | D99: 46001 | E99: 46034 | F99: 46058 | G99: 0 | J99: =VLOOKUP(A99,'Jan 26'!A:G,7,FALSE) -> 11648.15 | K99: =IF(G99=0,J99-G99,0) -> 11648.15 | L99: 11648.15
A100: Natural Domain Interiors, LLC:Brooks Project | B100: 86639 | C100: NV-R | D100: 01/08/2026 | E100: 46070 | F100: Pre-Production | G100: 29037 | H100: =I100-G100 -> 29037 | I100: 58074 | J100: =VLOOKUP(A100,'Jan 26'!A:G,7,FALSE) -> 29037 | L100: =IF(G100>0,G100-J100,"Invoiced this Month") -> 0
...

Sheet Mar 26
A1: Customer | B1: Q Number | C1: Region | D1: Payment Date | E1: Production Start Day | F1: Stage | G1: DEPOSIT | H1: FINAL | I1: TOTAL | J1: BOM Dep | K1: Dep to Rev | L1: New Dep this Month
A2: 1st Choice Glass:MUSC - Clemson | B2: 88562 | C2: NC-C | D2: 46091 | E2: Pre-Production | G2: 51110.14 | H2: =I2-G2 -> 0 | I2: 51110.14 | K2: =IF(G2=0,J2-G2,0) -> 0 | L2: =IF(G2>0,G2-J2,"Invoiced this Month") -> 51110.14 | M2: =L2-K2 -> 51110.14
A3: A&A Window Products Inc:45 Littles Road | B3: 88556 | C3: MA-R | D3: 46086 | E3: Pre-Production | G3: 11662 | H3: =I3-G3 -> 11662 | I3: 23324 | K3: =IF(G3=0,J3-G3,0) -> 0 | L3: =IF(G3>0,G3-J3,"Invoiced this Month") -> 11662 | M3: =L3-K3 -> 11662
A4: Advanced Windows:1990 K Street | B4: 87616 | C4: MD-C | D4: 02/16/2026 | E4: Pre-Production | F4: Pre-Production | G4: 35586 | H4: =I4-G4 -> 9375 | I4: 44961 | J4: =VLOOKUP(A4,'Feb 26'!A:G,7,FALSE) -> 35586 | K4: =IF(G4=0,J4-G4,0) -> 0 | L4: =IF(G4>0,G4-J4,"Invoiced this Month") -> 0 | M4: =L4-K4 -> 0
A5: Advanced Windows:Golden Hill | B5: 84541 | C5: MD-C | D5: 45943 | E5: Pre-Production | F5: Pre-Production | G5: 10262 | H5: =I5-G5 -> 10261 | I5: 20523 | J5: =VLOOKUP(A5,'Feb 26'!A:G,7,FALSE) -> 10262 | K5: =IF(G5=0,J5-G5,0) -> 0 | L5: =IF(G5>0,G5-J5,"Invoiced this Month") -> 0 | M5: =L5-K5 -> 0
A6: Ajay Glass & Mirror Co., Inc.:Billitier | B6: 89718 | C6: NY-R | D6: 46105 | E6: Pre-Production | G6: 9796.19 | H6: =I6-G6 -> 9796.18 | I6: 19592.37 | K6: =IF(G6=0,J6-G6,0) -> 0 | L6: =IF(G6>0,G6-J6,"Invoiced this Month") -> 9796.19 | M6: =L6-K6 -> 9796.19
A7: Akis Doganis:Doganis Residence | B7: 87185 | C7: NV-R | D7: 12/04/2025 | E7: Pre-Production | F7: Pre-Production | G7: 31515 | H7: =I7-G7 -> 31514 | I7: 63029 | J7: =VLOOKUP(A7,'Feb 26'!A:G,7,FALSE) -> 31515 | K7: =IF(G7=0,J7-G7,0) -> 0 | L7: =IF(G7>0,G7-J7,"Invoiced this Month") -> 0 | M7: =L7-K7 -> 0
A8: All New Glass:201 Fillmore | B8: 78377 | C8: WA-C | D8: 02/24/2025 | E8: 46007 | F8: 46093 | J8: =VLOOKUP(A8,'Feb 26'!A:G,7,FALSE) -> 342623.5 | K8: =IF(G8=0,J8-G8,0) -> 342623.5 | L8: =IF(G8>0,G8-J8,"Invoiced this Month") -> Invoiced this Month | M8: =-K8 -> -342623.5
A9: All New Glass:Chanel UTC | B9: 83846 | C9: WA-C | D9: 45880 | E9: 46076 | F9: Pre-Production | G9: =77743+30779.5 -> 108522.5 | H9: =I9-G9 -> 108521.5 | I9: 217044 | J9: =VLOOKUP(A9,'Feb 26'!A:G,7,FALSE) -> 108522.5 | K9: =IF(G9=0,J9-G9,0) -> 0 | L9: =IF(G9>0,G9-J9,"Invoiced this Month") -> 0 | M9: =L9-K9 -> 0
A10: Alli Construction:Chaparral Janiga Residence | B10: 89424 | C10: CA-R | D10: 46090 | E10: Pre-Production | G10: 16906.51 | H10: =I10-G10 -> 16906.5 | I10: 33813.01 | K10: =IF(G10=0,J10-G10,0) -> 0 | L10: =IF(G10>0,G10-J10,"Invoiced this Month") -> 16906.51 | M10: =L10-K10 -> 16906.51
A11: American Glass - Livermore:Sunset Clubhouse-2 | B11: 85639 | C11: CA-C | D11: 45805 | E11: 46015 | F11: 46097 | J11: =VLOOKUP(A11,'Feb 26'!A:G,7,FALSE) -> 11673 | K11: =IF(G11=0,J11-G11,0) -> 11673 | L11: =IF(G11>0,G11-J11,"Invoiced this Month") -> Invoiced this Month | M11: =-K11 -> -11673
A12: American Glass & Mirror Company:1000 Nevillewood Drive | B12: 87836 | C12: VA-C | D12: 46098 | E12: Pre-Production | G12: 18709 | H12: =I12-G12 -> 18709 | I12: 37418 | K12: =IF(G12=0,J12-G12,0) -> 0 | L12: =IF(G12>0,G12-J12,"Invoiced this Month") -> 18709 | M12: =L12-K12 -> 18709
A13: American Products Inc (API):LuLulemon Boston Panel | B13: 89707 | C13: FL-C | D13: 46107 | E13: Pre-Production | G13: 3227 | H13: =I13-G13 -> 3227 | I13: 6454 | K13: =IF(G13=0,J13-G13,0) -> 0 | L13: =IF(G13>0,G13-J13,"Invoiced this Month") -> 3227 | M13: =L13-K13 -> 3227
A14: Angie Nyborg:Nyborg Residence | B14: 89450 | C14: NV-R | D14: 46097 | E14: Pre-Production | G14: 29728 | H14: =I14-G14 -> 31453 | I14: 61181 | K14: =IF(G14=0,J14-G14,0) -> 0 | L14: =IF(G14>0,G14-J14,"Invoiced this Month") -> 29728 | M14: =L14-K14 -> 29728
A15: Aragon Construction, Inc.:Penta (1) Interior | B15: 84044 | C15: CA-C | D15: 45811 | E15: 46002 | F15: Cutting | G15: 93528 | H15: =I15-G15 -> -28848 | I15: 64680 | J15: =VLOOKUP(A15,'Feb 26'!A:G,7,FALSE) -> 93528 | K15: =IF(G15=0,J15-G15,0) -> 0 | L15: =IF(G15>0,G15-J15,"Invoiced this Month") -> 0 | M15: =L15-K15 -> 0
A16: Aragon Construction, Inc.:Penta (2) Exterior | B16: 84046 | C16: CA-C | D16: 45811 | E16: 46002 | F16: Cutting | G16: 97035 | H16: =I16-G16 -> 38165 | I16: 135200 | J16: =VLOOKUP(A16,'Feb 26'!A:G,7,FALSE) -> 97035 | K16: =IF(G16=0,J16-G16,0) -> 0 | L16: =IF(G16>0,G16-J16,"Invoiced this Month") -> 0 | M16: =L16-K16 -> 0
A17: Aragon Construction, Inc.:Puente Hills | B17: 82690 | C17: CA-C | D17: 11/17/2025 | E17: Pre-Production | F17: Pre-Production | G17: 13744 | H17: =I17-G17 -> 12649 | I17: 26393 | J17: =VLOOKUP(A17,'Feb 26'!A:G,7,FALSE) -> 13744 | K17: =IF(G17=0,J17-G17,0) -> 0 | L17: =IF(G17>0,G17-J17,"Invoiced this Month") -> 0 | M17: =L17-K17 -> 0
A18: Aune Brothers Construction:2460 Cajon Lane | B18: 86022 | C18: AZ-R | D18: 46091 | E18: Pre-Production | G18: 4247 | H18: =I18-G18 -> 4247 | I18: 8494 | K18: =IF(G18=0,J18-G18,0) -> 0 | L18: =IF(G18>0,G18-J18,"Invoiced this Month") -> 4247 | M18: =L18-K18 -> 4247
A19: Barbara Bellio:Bellio Residence | B19: 87402 | C19: NV-R | D19: 45939 | E19: Pre-Production | F19: Pre-Production | G19: 20000 | H19: =I19-G19 -> 19516 | I19: 39516 | J19: =VLOOKUP(A19,'Feb 26'!A:G,7,FALSE) -> 20000 | K19: =IF(G19=0,J19-G19,0) -> 0 | L19: =IF(G19>0,G19-J19,"Invoiced this Month") -> 0 | M19: =L19-K19 -> 0
A20: Best Contracting LLC:UCSB San Benito Housing | B20: 87022 | C20: CA-C | D20: 11/20/2025 | E20: Pre-Production | F20: Pre-Production | G20: 60823 | H20: =I20-G20 -> 60822 | I20: 121645 | J20: =VLOOKUP(A20,'Feb 26'!A:G,7,FALSE) -> 60823 | K20: =IF(G20=0,J20-G20,0) -> 0 | L20: =IF(G20>0,G20-J20,"Invoiced this Month") -> 0 | M20: =L20-K20 -> 0
A21: Biery Cheese Company:Silo Radius | B21: 87104 | C21: OH-C | D21: 45939 | E21: 46072 | F21: 46106 | J21: =VLOOKUP(A21,'Feb 26'!A:G,7,FALSE) -> 24528.82 | K21: =IF(G21=0,J21-G21,0) -> 24528.82 | L21: =IF(G21>0,G21-J21,"Invoiced this Month") -> Invoiced this Month | M21: =-K21 -> -24528.82
A22: BMG Door & Glass:Rowley | B22: 88961 | C22: AZ-R | D22: 46062 | E22: Pre-Production | F22: Pre-Production | G22: 22865 | H22: =I22-G22 -> 22864 | I22: 45729 | J22: =VLOOKUP(A22,'Feb 26'!A:G,7,FALSE) -> 22865 | K22: =IF(G22=0,J22-G22,0) -> 0 | L22: =IF(G22>0,G22-J22,"Invoiced this Month") -> 0 | M22: =L22-K22 -> 0
A23: BMG Door & Glass:Zamora Residence | B23: 88921 | C23: NV-R | D23: 01/30/2026 | E23: Pre-Production | F23: 46112 | J23: =VLOOKUP(A23,'Feb 26'!A:G,7,FALSE) -> 18436 | K23: =IF(G23=0,J23-G23,0) -> 18436 | L23: =IF(G23>0,G23-J23,"Invoiced this Month") -> Invoiced this Month | M23: =-K23 -> -18436
A24: Brad Lager:Palmer | B24: 87591 | C24: MO-R | D24: 46058 | E24: Pre-Production | F24: Pre-Production | G24: 25317 | H24: =I24-G24 -> 25316 | I24: 50633 | J24: =VLOOKUP(A24,'Feb 26'!A:G,7,FALSE) -> 25317 | K24: =IF(G24=0,J24-G24,0) -> 0 | L24: =IF(G24>0,G24-J24,"Invoiced this Month") -> 0 | M24: =L24-K24 -> 0
A25: Brett Hill Construction, Inc:4895 Kalanianaole | B25: 88674 | C25: HI-R | D25: 46055 | E25: Pre-Production | F25: Pre-Production | G25: 238760 | H25: =I25-G25 -> 238759 | I25: 477519 | J25: =VLOOKUP(A25,'Feb 26'!A:G,7,FALSE) -> 238760 | K25: =IF(G25=0,J25-G25,0) -> 0 | L25: =IF(G25>0,G25-J25,"Invoiced this Month") -> 0 | M25: =L25-K25 -> 0
A26: Builders Direct Supply:4545 North-Studio | B26: 85791 | C26: CA-R | D26: 45959 | E26: Pre-Production | F26: Pre-Production | G26: 8977.7 | H26: =I26-G26 -> 80799.3 | I26: 89777 | J26: =VLOOKUP(A26,'Feb 26'!A:G,7,FALSE) -> 8977.7 | K26: =IF(G26=0,J26-G26,0) -> 0 | L26: =IF(G26>0,G26-J26,"Invoiced this Month") -> 0 | M26: =L26-K26 -> 0
A27: Builders Direct Supply:Larroque Door | B27: 88582 | C27: CA-R | D27: 02/16/2026 | E27: Pre-Production | F27: 46112 | J27: =VLOOKUP(A27,'Feb 26'!A:G,7,FALSE) -> 4551 | K27: =IF(G27=0,J27-G27,0) -> 4551 | L27: =IF(G27>0,G27-J27,"Invoiced this Month") -> Invoiced this Month | M27: =-K27 -> -4551
A28: Builders Direct Supply:Marriott | B28: 88115 | C28: CA-C | D28: 46059 | E28: Pre-Production | F28: Pre-Production | G28: 62150.5 | H28: =I28-G28 -> 62150.5 | I28: 124301 | J28: =VLOOKUP(A28,'Feb 26'!A:G,7,FALSE) -> 62150.5 | K28: =IF(G28=0,J28-G28,0) -> 0 | L28: =IF(G28>0,G28-J28,"Invoiced this Month") -> 0 | M28: =L28-K28 -> 0
A29: Builders Direct Supply:North 4545 | B29: 83690 | C29: CA-R | D29: 45959 | E29: Pre-Production | F29: Pre-Production | G29: 41681.4 | H29: =I29-G29 -> 375132.6 | I29: 416814 | J29: =VLOOKUP(A29,'Feb 26'!A:G,7,FALSE) -> 41681.4 | K29: =IF(G29=0,J29-G29,0) -> 0 | L29: =IF(G29>0,G29-J29,"Invoiced this Month") -> 0 | M29: =L29-K29 -> 0
A30: Builders Direct Supply:Snell and Wilmer | B30: 86318 | C30: CA-C | D30: 01/08/2026 | E30: Pre-Production | F30: Pre-Production | G30: 26483.5 | H30: =I30-G30 -> 26483.5 | I30: 52967 | J30: =VLOOKUP(A30,'Feb 26'!A:G,7,FALSE) -> 26483.5 | L30: =IF(G30>0,G30-J30,"Invoiced this Month") -> 0 | M30: =L30-K30 -> 0
A31: Builders FirstSource/Dixieline Lumber & Home Center:Bhill Orange County | B31: 89482 | C31: CA-R | D31: 46111 | E31: Pre-Production | G31: 4138 | H31: =I31-G31 -> 4138 | I31: 8276 | K31: =IF(G31=0,J31-G31,0) -> 0 | L31: =IF(G31>0,G31-J31,"Invoiced this Month") -> 4138 | M31: =L31-K31 -> 4138
A32: Builders FirstSource/Dixieline Lumber & Home Center:Dixieline Lumber & Home Center:Rick Moore | B32: 89242 | C32: CA-C | D32: 46083 | E32: Pre-Production | G32: 8432 | H32: =I32-G32 -> 8432 | I32: 16864 | K32: =IF(G32=0,J32-G32,0) -> 0 | L32: =IF(G32>0,G32-J32,"Invoiced this Month") -> 8432 | M32: =L32-K32 -> 8432
A33: Builders FirstSource/Dixieline Lumber & Home Center:Jody Doors | B33: 88100 | C33: CA-R | D33: 12/29/2025 | E33: 46062 | F33: 46094 | J33: =VLOOKUP(A33,'Feb 26'!A:G,7,FALSE) -> 8674 | K33: =IF(G33=0,J33-G33,0) -> 8674 | L33: =IF(G33>0,G33-J33,"Invoiced this Month") -> Invoiced this Month | M33: =-K33 -> -8674
A34: C Thru Glass:Caesars Republic Pool Club Lounge | B34: 87633 | C34: NV-C | D34: 01/08/2026 | E34: 46072 | F34: 46108 | J34: =VLOOKUP(A34,'Feb 26'!A:G,7,FALSE) -> 39028 | K34: =IF(G34=0,J34-G34,0) -> 39028 | L34: =IF(G34>0,G34-J34,"Invoiced this Month") -> Invoiced this Month | M34: =-K34 -> -39028
A35: CAC Aluminum & Glass Inc.:355 Deerfield Sliding Doors | B35: 89649 | C35: IL-C | D35: 46101 | E35: Pre-Production | G35: 17176 | H35: =I35-G35 -> 17175 | I35: 34351 | K35: =IF(G35=0,J35-G35,0) -> 0 | L35: =IF(G35>0,G35-J35,"Invoiced this Month") -> 17176 | M35: =L35-K35 -> 17176
A36: Capitol Glass & Aluminum Co.:Cypress Village | B36: 88240 | C36: FL-C | D36: 46062 | E36: Pre-Production | F36: Pre-Production | G36: 16435.5 | H36: =I36-G36 -> 16435.5 | I36: 32871 | J36: =VLOOKUP(A36,'Feb 26'!A:G,7,FALSE) -> 16435.5 | K36: =IF(G36=0,J36-G36,0) -> 0 | L36: =IF(G36>0,G36-J36,"Invoiced this Month") -> 0 | M36: =L36-K36 -> 0
A37: Capitol Glass Company:99 Rhode Island | B37: 85440 | C37: CA-C | D37: 11/19/2025 | E37: 46044 | F37: 46106 | J37: =VLOOKUP(A37,'Feb 26'!A:G,7,FALSE) -> 15439 | K37: =IF(G37=0,J37-G37,0) -> 15439 | L37: =IF(G37>0,G37-J37,"Invoiced this Month") -> Invoiced this Month | M37: =-K37 -> -15439
A38: Capitol Glass Company:Sunnydale Block 7 | B38: 88227 | C38: CA-C | D38: 12/29/2025 | E38: Pre-Production | F38: Pre-Production | G38: 32005 | H38: =I38-G38 -> 32005 | I38: 64010 | J38: =VLOOKUP(A38,'Feb 26'!A:G,7,FALSE) -> 32005 | K38: =IF(G38=0,J38-G38,0) -> 0 | L38: =IF(G38>0,G38-J38,"Invoiced this Month") -> 0 | M38: =L38-K38 -> 0
A39: Capitol Glass Company:The Eliza | B39: 84966 | C39: CA-C | D39: 46099 | E39: Pre-Production | G39: 39804 | H39: =I39-G39 -> 39803 | I39: 79607 | K39: =IF(G39=0,J39-G39,0) -> 0 | L39: =IF(G39>0,G39-J39,"Invoiced this Month") -> 39804 | M39: =L39-K39 -> 39804
A40: Catalyst Acoustics Group | B40: Unknown | D40: 05/31/2022 | E40: Pre-Production | F40: Pre-Production | G40: 4108 | H40: =I40-G40 -> 0 | I40: 4108 | J40: =VLOOKUP(A40,'Feb 26'!A:G,7,FALSE) -> 4108 | K40: =IF(G40=0,J40-G40,0) -> 0 | L40: =IF(G40>0,G40-J40,"Invoiced this Month") -> 0 | M40: =L40-K40 -> 0
A41: Chase Kloehn:Kloehn Remodel | B41: 88513 | C41: NV-R | D41: 46085 | E41: Pre-Production | G41: 11224 | H41: =I41-G41 -> 13423 | I41: 24647 | K41: =IF(G41=0,J41-G41,0) -> 0 | L41: =IF(G41>0,G41-J41,"Invoiced this Month") -> 11224 | M41: =L41-K41 -> 11224
A42: Chopper Dawson INC:Daniel Res | B42: 85396 | C42: VA-R | D42: 46090 | E42: Pre-Production | G42: 9792 | H42: =I42-G42 -> 9792 | I42: 19584 | K42: =IF(G42=0,J42-G42,0) -> 0 | L42: =IF(G42>0,G42-J42,"Invoiced this Month") -> 9792 | M42: =L42-K42 -> 9792
A43: Chris & Kareen Brown:By Woods Door | B43: 86825 | C43: MD-R | D43: 02/23/2026 | E43: Pre-Production | F43: Pre-Production | G43: 6409 | H43: =I43-G43 -> 6408 | I43: 12817 | J43: =VLOOKUP(A43,'Feb 26'!A:G,7,FALSE) -> 6409 | K43: =IF(G43=0,J43-G43,0) -> 0 | L43: =IF(G43>0,G43-J43,"Invoiced this Month") -> 0 | M43: =L43-K43 -> 0
A44: Chuck Hamilton Construction Inc.:Shueck Pool House | B44: 89296 | C44: AR-R | D44: 46100 | E44: Pre-Production | G44: 109253 | H44: =I44-G44 -> 109253 | I44: 218506 | K44: =IF(G44=0,J44-G44,0) -> 0 | L44: =IF(G44>0,G44-J44,"Invoiced this Month") -> 109253 | M44: =L44-K44 -> 109253
A45: CK2 Contracting:1221 W. Washington | B45: 88868 | C45: IL-R | D45: 46059 | E45: Pre-Production | F45: Pre-Production | G45: 17321 | H45: =I45-G45 -> 17321 | I45: 34642 | J45: =VLOOKUP(A45,'Feb 26'!A:G,7,FALSE) -> 17321 | K45: =IF(G45=0,J45-G45,0) -> 0 | L45: =IF(G45>0,G45-J45,"Invoiced this Month") -> 0 | M45: =L45-K45 -> 0
A46: Classic Carpentry Inc.:CC Project / 262 Mermaid's Bight | B46: 88131 | C46: FL-R | D46: 01/20/2026 | E46: 46076 | F46: Pre-Production | G46: 33237 | H46: =I46-G46 -> 33236 | I46: 66473 | J46: =VLOOKUP(A46,'Feb 26'!A:G,7,FALSE) -> 33237 | L46: =IF(G46>0,G46-J46,"Invoiced this Month") -> 0 | M46: =L46-K46 -> 0
A47: Coltin Craigo:Alphorn Road | B47: 87218 | C47: WI-R | D47: 12/19/2025 | E47: 46028 | F47: 46084 | J47: =VLOOKUP(A47,'Feb 26'!A:G,7,FALSE) -> 7433 | K47: =IF(G47=0,J47-G47,0) -> 7433 | L47: =IF(G47>0,G47-J47,"Invoiced this Month") -> Invoiced this Month | M47: =-K47 -> -7433
A48: Constructa:Nuevo Proyecto en Punta Mita | B48: 83937 | C48: MX-C | D48: 11/20/2025 | E48: 46071 | F48: 46112 | J48: =VLOOKUP(A48,'Feb 26'!A:G,7,FALSE) -> 59570.5 | K48: =IF(G48=0,J48-G48,0) -> 59570.5 | L48: =IF(G48>0,G48-J48,"Invoiced this Month") -> Invoiced this Month | M48: =-K48 -> -59570.5
A49: Crisci Builders:Lot 147 Addition | B49: 87426 | C49: NV-R | D49: 46084 | E49: Pre-Production | G49: 94654 | H49: =I49-G49 -> 94653 | I49: 189307 | K49: =IF(G49=0,J49-G49,0) -> 0 | L49: =IF(G49>0,G49-J49,"Invoiced this Month") -> 94654 | M49: =L49-K49 -> 94654
A50: Crystal Glass Inc.:New Logan Elementry | B50: 83108 | C50: MI-C | D50: 04/17/2025 | E50: Pre-Production | F50: Pre-Production | G50: 172204.5 | H50: =I50-G50 -> 172204.5 | I50: 344409 | J50: =VLOOKUP(A50,'Feb 26'!A:G,7,FALSE) -> 172204.5 | K50: =IF(G50=0,J50-G50,0) -> 0 | L50: =IF(G50>0,G50-J50,"Invoiced this Month") -> 0 | M50: =L50-K50 -> 0
A51: D & R Glass:Cedar and Sage | B51: 84134 | C51: CA-C | D51: 45945 | E51: Pre-Production | F51: Pre-Production | G51: 64205 | H51: =I51-G51 -> 61477 | I51: 125682 | J51: =VLOOKUP(A51,'Feb 26'!A:G,7,FALSE) -> 64205 | K51: =IF(G51=0,J51-G51,0) -> 0 | L51: =IF(G51>0,G51-J51,"Invoiced this Month") -> 0 | M51: =L51-K51 -> 0
A52: Dan and Molly Dirscherl:Dirscherl Cabana | B52: 85777 | C52: NJ-R | D52: 46093 | E52: Pre-Production | G52: 17769 | H52: =I52-G52 -> 168389 | I52: 186158 | K52: =IF(G52=0,J52-G52,0) -> 0 | L52: =IF(G52>0,G52-J52,"Invoiced this Month") -> 17769 | M52: =L52-K52 -> 17769
A53: David Ostrander:Ostrander Residence Remodel | B53: 88087 | C53: MN-R | D53: 02/11/2026 | E53: Pre-Production | F53: Pre-Production | G53: 123085 | H53: =I53-G53 -> 123084 | I53: 246169 | J53: =VLOOKUP(A53,'Feb 26'!A:G,7,FALSE) -> 123085 | K53: =IF(G53=0,J53-G53,0) -> 0 | L53: =IF(G53>0,G53-J53,"Invoiced this Month") -> 0 | M53: =L53-K53 -> 0
A54: David Shuldiner Inc:450 Lexington | B54: 83623 | C54: NY-C | D54: 45859 | E54: 46020 | F54: 46094 | J54: =VLOOKUP(A54,'Feb 26'!A:G,7,FALSE) -> 75227 | K54: =IF(G54=0,J54-G54,0) -> 75227 | L54: =IF(G54>0,G54-J54,"Invoiced this Month") -> Invoiced this Month | M54: =-K54 -> -75227
A55: Debbie Piliero:46 Upper Rd | B55: 87161 | C55: CA-R | D55: 45924 | E55: 45992 | F55: Pull Material | G55: 17417 | H55: =I55-G55 -> 17417 | I55: 34834 | J55: =VLOOKUP(A55,'Feb 26'!A:G,7,FALSE) -> 17417 | K55: =IF(G55=0,J55-G55,0) -> 0 | L55: =IF(G55>0,G55-J55,"Invoiced this Month") -> 0 | M55: =L55-K55 -> 0
A56: Desert Window Systems:Lennar | B56: 88180 | C56: NV-R | D56: 02/25/2026 | E56: Pre-Production | F56: Pre-Production | G56: 38957 | H56: =I56-G56 -> 38957 | I56: 77914 | J56: =VLOOKUP(A56,'Feb 26'!A:G,7,FALSE) -> 38957 | K56: =IF(G56=0,J56-G56,0) -> 0 | L56: =IF(G56>0,G56-J56,"Invoiced this Month") -> 0 | M56: =L56-K56 -> 0
A57: Devoe Custom Homes:Vanderveen | B57: 89554 | C57: FL-R | D57: 46100 | E57: Pre-Production | G57: 17304 | H57: =I57-G57 -> 17303 | I57: 34607 | K57: =IF(G57=0,J57-G57,0) -> 0 | L57: =IF(G57>0,G57-J57,"Invoiced this Month") -> 17304 | M57: =L57-K57 -> 17304
A58: DGB Glass Inc.:Hotel Grey | B58: 86965 | C58: TX-C | D58: 45924 | E58: 46048 | F58: Pull Material | G58: 49026 | H58: =I58-G58 -> 51328 | I58: 100354 | J58: =VLOOKUP(A58,'Feb 26'!A:G,7,FALSE) -> 49026 | K58: =IF(G58=0,J58-G58,0) -> 0 | L58: =IF(G58>0,G58-J58,"Invoiced this Month") -> 0 | M58: =L58-K58 -> 0
A59: Discount Glass & Mirror Inc.:Cardella | B59: 83204 | C59: CA-C | D59: 46108 | E59: Pre-Production | G59: 44368 | H59: =I59-G59 -> 44368 | I59: 88736 | K59: =IF(G59=0,J59-G59,0) -> 0 | L59: =IF(G59>0,G59-J59,"Invoiced this Month") -> 44368 | M59: =L59-K59 -> 44368
A60: Discount Glass & Mirror Inc.:Encinitas | B60: 85495 | C60: CA-C | D60: 46083 | E60: Pre-Production | G60: 29175 | H60: =I60-G60 -> 29175 | I60: 58350 | K60: =IF(G60=0,J60-G60,0) -> 0 | L60: =IF(G60>0,G60-J60,"Invoiced this Month") -> 29175 | M60: =L60-K60 -> 29175
A61: Donatello Bonasera Development, LLC:Casa Faten | B61: 88756 | C61: CA-R | D61: 46092 | E61: Pre-Production | G61: 160000 | H61: =I61-G61 -> 158239 | I61: 318239 | K61: =IF(G61=0,J61-G61,0) -> 0 | L61: =IF(G61>0,G61-J61,"Invoiced this Month") -> 160000 | M61: =L61-K61 -> 160000
A62: Donatello Bonasera Development, LLC:The F Penthouse | B62: 89698 | C62: CA-R | D62: 46091 | E62: Pre-Production | G62: 8935.32 | H62: =I62-G62 -> 8935.32 | I62: 17870.64 | K62: =IF(G62=0,J62-G62,0) -> 0 | L62: =IF(G62>0,G62-J62,"Invoiced this Month") -> 8935.32 | M62: =L62-K62 -> 8935.32
A63: Don's Mobile Glass:Grossi | B63: 88858 | C63: CA-R | D63: 46105 | E63: Pre-Production | G63: 16192 | H63: =I63-G63 -> 16192 | I63: 32384 | K63: =IF(G63=0,J63-G63,0) -> 0 | L63: =IF(G63>0,G63-J63,"Invoiced this Month") -> 16192 | M63: =L63-K63 -> 16192
A64: Doors, Etc.:Doors Etc HSW | B64: 88511 | C64: CA-R | D64: 02/19/2026 | E64: Pre-Production | F64: Pre-Production | G64: 19222 | H64: =I64-G64 -> 19222 | I64: 38444 | J64: =VLOOKUP(A64,'Feb 26'!A:G,7,FALSE) -> 19222 | K64: =IF(G64=0,J64-G64,0) -> 0 | L64: =IF(G64>0,G64-J64,"Invoiced this Month") -> 0 | M64: =L64-K64 -> 0
A65: Dugally Oberfeld, Inc.:Cox | B65: 83729 | C65: CA-R | D65: 01/06/2026 | E65: Pre-Production | F65: Pre-Production | G65: 31223 | H65: =I65-G65 -> 27501 | I65: 58724 | J65: =VLOOKUP(A65,'Feb 26'!A:G,7,FALSE) -> 31223 | L65: =IF(G65>0,G65-J65,"Invoiced this Month") -> 0 | M65: =L65-K65 -> 0
A66: Dynamic Glass:Antero Resources | B66: 85504 | C66: CO-C | D66: 46100 | E66: Pre-Production | G66: 151068 | H66: =I66-G66 -> 151068 | I66: 302136 | K66: =IF(G66=0,J66-G66,0) -> 0 | L66: =IF(G66>0,G66-J66,"Invoiced this Month") -> 151068 | M66: =L66-K66 -> 151068
A67: E & Z Glass & Window:Cotton On Dallas Galleria | B67: 89285 | C67: TX-R | D67: 46098 | E67: Pre-Production | G67: 23405 | H67: =I67-G67 -> 23404 | I67: 46809 | K67: =IF(G67=0,J67-G67,0) -> 0 | L67: =IF(G67>0,G67-J67,"Invoiced this Month") -> 23405 | M67: =L67-K67 -> 23405
A68: EAP Glass:4th Street North Apts | B68: 85454 | C68: CO-C | D68: 12/30/2025 | E68: 46044 | F68: Sanding | G68: 14438 | H68: =I68-G68 -> 14438 | I68: 28876 | J68: =VLOOKUP(A68,'Feb 26'!A:G,7,FALSE) -> 14438 | K68: =IF(G68=0,J68-G68,0) -> 0 | L68: =IF(G68>0,G68-J68,"Invoiced this Month") -> 0 | M68: =L68-K68 -> 0
A69: Edge Design and Construction INC:Brooks Project Add On | B69: 89984 | C69: NV-R | D69: 46112 | E69: Pre-Production | G69: 1897 | H69: =I69-G69 -> 0 | I69: 1897 | K69: =IF(G69=0,J69-G69,0) -> 0 | L69: =IF(G69>0,G69-J69,"Invoiced this Month") -> 1897 | M69: =L69-K69 -> 1897
A70: Elaine Fitzpatrick:Fitzpatrick Residence | B70: 85838 | C70: NV-R | D70: 01/23/2026 | E70: 46077 | F70: 46112 | J70: =VLOOKUP(A70,'Feb 26'!A:G,7,FALSE) -> 3386 | K70: =IF(G70=0,J70-G70,0) -> 3386 | L70: =IF(G70>0,G70-J70,"Invoiced this Month") -> Invoiced this Month | M70: =-K70 -> -3386
A71: Element Facades 13:299 MILWAUKEE | B71: 86960 | C71: CO-C | D71: 11/25/2025 | E71: Pre-Production | F71: Pre-Production | G71: 8962 | H71: =I71-G71 -> 26885 | I71: 35847 | J71: =VLOOKUP(A71,'Feb 26'!A:G,7,FALSE) -> 8962 | K71: =IF(G71=0,J71-G71,0) -> 0 | L71: =IF(G71>0,G71-J71,"Invoiced this Month") -> 0 | M71: =L71-K71 -> 0
A72: Emerald Glass:The Frank | B72: 84692 | C72: WA-C | D72: 02/23/2026 | E72: Pre-Production | F72: Pre-Production | G72: 5345 | H72: =I72-G72 -> 5344 | I72: 10689 | J72: =VLOOKUP(A72,'Feb 26'!A:G,7,FALSE) -> 5345 | K72: =IF(G72=0,J72-G72,0) -> 0 | L72: =IF(G72>0,G72-J72,"Invoiced this Month") -> 0 | M72: =L72-K72 -> 0
A73: Environmental Glass Inc:Ann Arbor Thurston | B73: 84161 | C73: MI-C | D73: 46013 | E73: Pre-Production | F73: Pre-Production | G73: 176687 | H73: =I73-G73 -> 176686 | I73: 353373 | J73: =VLOOKUP(A73,'Feb 26'!A:G,7,FALSE) -> 46821.92 | K73: =IF(G73=0,J73-G73,0) -> 0 | L73: =IF(G73>0,G73-J73,"Invoiced this Month") -> 129865.08 | M73: =L73-K73 -> 129865.08
A74: Environmental Glass Inc:Mitchell Elementary | B74: 81492-R1 | C74: MI-C | D74: 45868 | E74: Pre-Production | F74: Pre-Production | G74: 114974 | H74: =I74-G74 -> 114973 | I74: 229947 | J74: =VLOOKUP(A74,'Feb 26'!A:G,7,FALSE) -> 57487 | K74: =IF(G74=0,J74-G74,0) -> 0 | L74: =IF(G74>0,G74-J74,"Invoiced this Month") -> 57487 | M74: =L74-K74 -> 57487
A75: Fast Glass:Brockway | B75: 87121 | C75: NV-R | D75: 12/19/2025 | E75: 46079 | F75: 46106 | J75: =VLOOKUP(A75,'Feb 26'!A:G,7,FALSE) -> 8901 | K75: =IF(G75=0,J75-G75,0) -> 8901 | L75: =IF(G75>0,G75-J75,"Invoiced this Month") -> Invoiced this Month | M75: =-K75 -> -8901
A76: Ford Metro Inc:Chapter / Ann Arbor | B76: 87492 | C76: MN-R | D76: 02/10/2026 | E76: Pre-Production | F76: Pre-Production | G76: 22079 | H76: =I76-G76 -> 22079 | I76: 44158 | J76: =VLOOKUP(A76,'Feb 26'!A:G,7,FALSE) -> 22079 | K76: =IF(G76=0,J76-G76,0) -> 0 | L76: =IF(G76>0,G76-J76,"Invoiced this Month") -> 0 | M76: =L76-K76 -> 0
A77: Franklin Herbas:Herbas Folding | B77: 89313 | C77: CA-R | D77: 02/26/2026 | E77: Pre-Production | F77: Pre-Production | G77: 8773 | H77: =I77-G77 -> 8773 | I77: 17546 | J77: =VLOOKUP(A77,'Feb 26'!A:G,7,FALSE) -> 8773 | K77: =IF(G77=0,J77-G77,0) -> 0 | L77: =IF(G77>0,G77-J77,"Invoiced this Month") -> 0 | M77: =L77-K77 -> 0
A78: Gen 3 Hospitality:Richardson House | B78: 88603 | C78: NV-R | D78: 01/06/2026 | E78: Pre-Production | F78: Pre-Production | G78: 23396 | H78: =I78-G78 -> 23396 | I78: 46792 | J78: =VLOOKUP(A78,'Feb 26'!A:G,7,FALSE) -> 23396 | K78: =IF(G78=0,J78-G78,0) -> 0 | L78: =IF(G78>0,G78-J78,"Invoiced this Month") -> 0 | M78: =L78-K78 -> 0
A79: Giroux Glass:SoCalGas Loggia | B79: 88082 | C79: CA-C | D79: 02/23/2026 | E79: Pre-Production | F79: Pre-Production | G79: 35295 | H79: =I79-G79 -> 35294 | I79: 70589 | J79: =VLOOKUP(A79,'Feb 26'!A:G,7,FALSE) -> 35295 | K79: =IF(G79=0,J79-G79,0) -> 0 | L79: =IF(G79>0,G79-J79,"Invoiced this Month") -> 0 | M79: =L79-K79 -> 0
A80: Glass and Metals, Inc:2100 Crystal | B80: 88012 | C80: VA-C | D80: 46086 | E80: Pre-Production | G80: 25461 | H80: =I80-G80 -> 25461 | I80: 50922 | K80: =IF(G80=0,J80-G80,0) -> 0 | L80: =IF(G80>0,G80-J80,"Invoiced this Month") -> 25461 | M80: =L80-K80 -> 25461
A81: Golden Glass Inc.:Pepperdine University | B81: 76624 | C81: CA-C | D81: 04/19/2024 | E81: 46038 | F81: Coating | G81: 82176 | H81: =I81-G81 -> 82176 | I81: 164352 | J81: =VLOOKUP(A81,'Feb 26'!A:G,7,FALSE) -> 82176 | K81: =IF(G81=0,J81-G81,0) -> 0 | L81: =IF(G81>0,G81-J81,"Invoiced this Month") -> 0 | M81: =L81-K81 -> 0
A82: GP Glass & Mirror LLC:George_Additional Fixed Window | B82: 89773 | C82: NV-R | D82: 46106 | E82: Pre-Production | G82: 1142.27 | H82: =I82-G82 -> 0 | I82: 1142.27 | K82: =IF(G82=0,J82-G82,0) -> 0 | L82: =IF(G82>0,G82-J82,"Invoiced this Month") -> 1142.27 | M82: =L82-K82 -> 1142.27
A83: GP Glass & Mirror LLC:George_Additional Windows | B83: 89187 | C83: NV-R | D83: 02/26/2026 | E83: Pre-Production | F83: 46106 | J83: =VLOOKUP(A83,'Feb 26'!A:G,7,FALSE) -> 3000 | K83: =IF(G83=0,J83-G83,0) -> 3000 | L83: =IF(G83>0,G83-J83,"Invoiced this Month") -> Invoiced this Month | M83: =-K83 -> -3000
A84: Hardman Glazing Management LLC:Brown Shop | B84: 87128 | C84: ID-R | D84: 01/12/2026 | E84: Pre-Production | F84: Pre-Production | G84: 25470 | H84: =I84-G84 -> 25467 | I84: 50937 | J84: =VLOOKUP(A84,'Feb 26'!A:G,7,FALSE) -> 25470 | K84: =IF(G84=0,J84-G84,0) -> 0 | L84: =IF(G84>0,G84-J84,"Invoiced this Month") -> 0 | M84: =L84-K84 -> 0
A85: Hardman Glazing Management LLC:Hinged Door | B85: 89121 | C85: CA-R | D85: 46062 | E85: Pre-Production | F85: Pre-Production | G85: 2712 | H85: =I85-G85 -> 3336 | I85: 6048 | J85: =VLOOKUP(A85,'Feb 26'!A:G,7,FALSE) -> 2712 | K85: =IF(G85=0,J85-G85,0) -> 0 | L85: =IF(G85>0,G85-J85,"Invoiced this Month") -> 0 | M85: =L85-K85 -> 0
A86: Hasco Constrution:Sperryn Jones | B86: 82632 | C86: SN-R | D86: 04/11/2025 | E86: Pre-Production | F86: Pre-Production | G86: 109478 | H86: =I86-G86 -> 109478 | I86: 218956 | J86: =VLOOKUP(A86,'Feb 26'!A:G,7,FALSE) -> 99911 | K86: =IF(G86=0,J86-G86,0) -> 0 | L86: =IF(G86>0,G86-J86,"Invoiced this Month") -> 9567 | M86: =L86-K86 -> 9567
A87: Heart of America Aston LLC:592 Aston | B87: 84210 | C87: IL-C | D87: 45876 | E87: Pre-Production | F87: Pre-Production | G87: 31567 | H87: =I87-G87 -> 46437 | I87: 78004 | J87: =VLOOKUP(A87,'Feb 26'!A:G,7,FALSE) -> 31567 | K87: =IF(G87=0,J87-G87,0) -> 0 | L87: =IF(G87>0,G87-J87,"Invoiced this Month") -> 0 | M87: =L87-K87 -> 0
A88: Helou Construction:Rosebowl South Endzone Club | B88: 88433 | C88: CA-C | D88: 01/14/2026 | E88: Pre-Production | F88: Pre-Production | G88: 80538 | H88: =I88-G88 -> 80538 | I88: 161076 | J88: =VLOOKUP(A88,'Feb 26'!A:G,7,FALSE) -> 80538 | K88: =IF(G88=0,J88-G88,0) -> 0 | L88: =IF(G88>0,G88-J88,"Invoiced this Month") -> 0 | M88: =L88-K88 -> 0
A89: Henry Grause:Grause Residence | B89: 88896 | C89: FL-R | D89: 46058 | E89: Pre-Production | F89: Pre-Production | G89: 10238 | H89: =I89-G89 -> 10237 | I89: 20475 | J89: =VLOOKUP(A89,'Feb 26'!A:G,7,FALSE) -> 10238 | K89: =IF(G89=0,J89-G89,0) -> 0 | L89: =IF(G89>0,G89-J89,"Invoiced this Month") -> 0 | M89: =L89-K89 -> 0
A90: Heritage Glass:DCI Pittock | B90: 87577 | C90: OR-C | D90: 01/16/2026 | E90: 46072 | F90: 46094 | J90: =VLOOKUP(A90,'Feb 26'!A:G,7,FALSE) -> 11785 | K90: =IF(G90=0,J90-G90,0) -> 11785 | L90: =IF(G90>0,G90-J90,"Invoiced this Month") -> Invoiced this Month | M90: =-K90 -> -11785
A91: Ikirkpatrick Construction:Stewart Residence 3 | B91: 87792 | C91: HI-R | D91: 12/01/2025 | E91: 46045 | F91: Pull Material | G91: 49733 | H91: =I91-G91 -> 49713 | I91: 99446 | J91: =VLOOKUP(A91,'Feb 26'!A:G,7,FALSE) -> 49733 | K91: =IF(G91=0,J91-G91,0) -> 0 | L91: =IF(G91>0,G91-J91,"Invoiced this Month") -> 0 | M91: =L91-K91 -> 0
A92: Infinity Group:Wilson Residence 77 | B92: 85175 | C92: CT-R | D92: 46084 | E92: Pre-Production | G92: 22778 | H92: =I92-G92 -> 22779 | I92: 45557 | K92: =IF(G92=0,J92-G92,0) -> 0 | L92: =IF(G92>0,G92-J92,"Invoiced this Month") -> 22778 | M92: =L92-K92 -> 22778
A93: Integrated Glass Concepts, Inc:Diablo Valley College | B93: 87488 | C93: CA-C | D93: 12/16/2025 | E93: Pre-Production | F93: Pre-Production | G93: 17613 | H93: =I93-G93 -> 17612 | I93: 35225 | J93: =VLOOKUP(A93,'Feb 26'!A:G,7,FALSE) -> 17613 | K93: =IF(G93=0,J93-G93,0) -> 0 | L93: =IF(G93>0,G93-J93,"Invoiced this Month") -> 0 | M93: =L93-K93 -> 0
A94: Island Tiles:Hilton Ballroom Doors | B94: 89316 | C94: BB-C | D94: 46100 | E94: Pre-Production | G94: 56063 | H94: =I94-G94 -> 56063 | I94: 112126 | K94: =IF(G94=0,J94-G94,0) -> 0 | L94: =IF(G94>0,G94-J94,"Invoiced this Month") -> 56063 | M94: =L94-K94 -> 56063
A95: J Shuman Door Installation:Chacon Residence | B95: 87376 | C95: CA-R | D95: 46085 | E95: Pre-Production | G95: 20322 | H95: =I95-G95 -> 20321 | I95: 40643 | K95: =IF(G95=0,J95-G95,0) -> 0 | L95: =IF(G95>0,G95-J95,"Invoiced this Month") -> 20322 | M95: =L95-K95 -> 20322
A96: J Shuman Door Installation:Jared Lou | B96: 86904 | C96: CA-R | D96: 46105 | E96: Pre-Production | G96: 6516 | H96: =I96-G96 -> 6515 | I96: 13031 | K96: =IF(G96=0,J96-G96,0) -> 0 | L96: =IF(G96>0,G96-J96,"Invoiced this Month") -> 6516 | M96: =L96-K96 -> 6516
A97: J Shuman Door Installation:Rob Poynter | B97: 87512 | C97: CA-C | D97: 46092 | E97: Pre-Production | G97: 4742 | H97: =I97-G97 -> 4972 | I97: 9714 | K97: =IF(G97=0,J97-G97,0) -> 0 | L97: =IF(G97>0,G97-J97,"Invoiced this Month") -> 4742 | M97: =L97-K97 -> 4742
A98: Jackson Design Home Remodeling:Multi-Slide Corner | B98: 88258 | C98: CA-R | D98: 12/01/2025 | E98: 46064 | F98: 46097 | J98: =VLOOKUP(A98,'Feb 26'!A:G,7,FALSE) -> 9467 | K98: =IF(G98=0,J98-G98,0) -> 9467 | L98: =IF(G98>0,G98-J98,"Invoiced this Month") -> Invoiced this Month | M98: =-K98 -> -9467
A99: JDP Associates:Shohet Project | B99: 88931 | C99: NV-R | D99: 46099 | E99: Pre-Production | G99: 5000 | H99: =I99-G99 -> 2102 | I99: 7102 | K99: =IF(G99=0,J99-G99,0) -> 0 | L99: =IF(G99>0,G99-J99,"Invoiced this Month") -> 5000 | M99: =L99-K99 -> 5000
A100: Jonah Monroe:Monroe Residence | B100: 87636 | C100: MD-R | D100: 11/19/2025 | E100: 46010 | F100: Pull Material | G100: 45837 | H100: =I100-G100 -> 44121 | I100: 89958 | J100: =VLOOKUP(A100,'Feb 26'!A:G,7,FALSE) -> 45837 | K100: =IF(G100=0,J100-G100,0) -> 0 | L100: =IF(G100>0,G100-J100,"Invoiced this Month") -> 0 | M100: =L100-K100 -> 0
...

Sheet Apr 26
A1: Customer | B1: Q Number | C1: Region | D1: Payment Date | E1: Production Start Day | F1: Stage | G1: DEPOSIT | H1: FINAL | I1: TOTAL | J1: BOM Dep | K1: Dep to Rev | L1: New Dep this Month
A2: 1st Choice Glass:MUSC - Clemson | B2: 88562 | C2: NC-C | D2: 46091 | E2: Pre-Production | F2: Pre-Production | G2: 51110.14 | H2: 0 | I2: 51110.14 | J2: =IFERROR(VLOOKUP(B2,'Mar 26'!B:G,6,FALSE),0) -> 51110.14 | K2: 0 | L2: =G2-J2 -> 0 | M2: =L2-K2 -> 0
A3: A&A Window Products Inc:45 Littles Road | B3: 88556 | C3: MA-R | D3: 46086 | E3: Pre-Production | F3: Pre-Production | G3: 11662 | H3: 11662 | I3: 23324 | J3: =VLOOKUP(B3,'Mar 26'!B:G,6,FALSE) -> 11662 | K3: 0 | L3: =G3-J3 -> 0 | M3: =L3-K3 -> 0
A4: Advanced Windows:1990 K Street | B4: 87616 | C4: MD-C | D4: 46069 | E4: Pre-Production | F4: Pre-Production | G4: 35586 | H4: 9375 | I4: 44961 | J4: =VLOOKUP(B4,'Mar 26'!B:G,6,FALSE) -> 35586 | K4: 0 | L4: =G4-J4 -> 0 | M4: =L4-K4 -> 0
A5: Advanced Windows:Golden Hill | B5: 84541 | C5: MD-C | D5: 45943 | E5: 46083 | F5: Coating | G5: 10262 | H5: 10261 | I5: 20523 | J5: =VLOOKUP(B5,'Mar 26'!B:G,6,FALSE) -> 10262 | K5: 0 | L5: =G5-J5 -> 0 | M5: =L5-K5 -> 0
A6: AFR Construction:Boe Dekker | B6: 87676 | C6: NV-R | D6: 46125 | E6: Pre-Production | F6: Pre-Production | G6: 2400.25 | H6: =I6-G6 -> 2449.75 | I6: 4850 | J6: 0 | K6: 0 | L6: =G6-J6 -> 2400.25 | M6: =L6-K6 -> 2400.25
A7: Ajay Glass & Mirror Co., Inc.:Billitier | B7: 89718 | C7: NY-R | D7: 46105 | E7: Pre-Production | F7: Pre-Production | G7: 9796.19 | H7: 9796.18 | I7: 19592.37 | J7: =VLOOKUP(B7,'Mar 26'!B:G,6,FALSE) -> 9796.19 | K7: 0 | L7: =G7-J7 -> 0 | M7: =L7-K7 -> 0
A8: Akis Doganis:Doganis Residence | B8: 87185 | C8: NV-R | D8: 45995 | E8: Pre-Production | F8: Pre-Production | G8: 31515 | H8: 31514 | I8: 63029 | J8: =VLOOKUP(B8,'Mar 26'!B:G,6,FALSE) -> 31515 | K8: 0 | L8: =G8-J8 -> 0 | M8: =L8-K8 -> 0
A9: All New Glass:Chanel UTC | B9: 83846 | C9: WA-C | D9: 45880 | E9: 46076 | F9: Cutting | G9: =108522.5+77742 -> 186264.5 | H9: 108521.5 | I9: 217044 | J9: =VLOOKUP(B9,'Mar 26'!B:G,6,FALSE) -> 108522.5 | K9: 0 | L9: =G9-J9 -> 77742 | M9: =L9-K9 -> 77742
A10: Alli Construction:Chaparral Janiga Residence | B10: 89424 | C10: CA-R | D10: 46090 | E10: Pre-Production | F10: Pre-Production | G10: 16906.51 | H10: 16906.5 | I10: 33813.01 | J10: =VLOOKUP(B10,'Mar 26'!B:G,6,FALSE) -> 16906.51 | K10: 0 | L10: =G10-J10 -> 0 | M10: =L10-K10 -> 0
A11: American Glass & Mirror Company:1000 Nevillewood Drive | B11: 87836 | C11: VA-C | D11: 46098 | E11: Pre-Production | F11: Pre-Production | G11: 18709 | H11: 18709 | I11: 37418 | J11: =VLOOKUP(B11,'Mar 26'!B:G,6,FALSE) -> 18709 | K11: 0 | L11: =G11-J11 -> 0 | M11: =L11-K11 -> 0
A12: American Products Inc (API):LuLulemon Boston Panel | B12: 89707 | C12: FL-C | D12: 46107 | E12: Pre-Production | F12: Cancelled 4/21 | G12: 0 | J12: =VLOOKUP(B12,'Mar 26'!B:G,6,FALSE) -> 3227 | K12: =J12-G12 -> 3227 | L12: Invoiced This Month | M12: =0-K12 -> -3227
A13: Angie Nyborg:Nyborg Residence | B13: 89450 | C13: NV-R | D13: 46097 | E13: Pre-Production | F13: Pre-Production | G13: 29728 | H13: 31453 | I13: 61181 | J13: =VLOOKUP(B13,'Mar 26'!B:G,6,FALSE) -> 29728 | K13: 0 | L13: =G13-J13 -> 0 | M13: =L13-K13 -> 0
A14: Aragon Construction, Inc.:Penta (1) Interior | B14: 84044 | C14: CA-C | D14: 45811 | E14: 46002 | F14: 46129 | G14: 0 | J14: =VLOOKUP(B14,'Mar 26'!B:G,6,FALSE) -> 93528 | K14: =J14-G14 -> 93528 | L14: Invoiced This Month | M14: =-K14 -> -93528
A15: Aragon Construction, Inc.:Penta (2) Exterior | B15: 84046 | C15: CA-C | D15: 45811 | E15: 46002 | F15: 46129 | G15: 0 | J15: =VLOOKUP(B15,'Mar 26'!B:G,6,FALSE) -> 97035 | K15: =J15-G15 -> 97035 | L15: Invoiced This Month | M15: =-K15 -> -97035
A16: Aragon Construction, Inc.:Puente Hills | B16: 82690 | C16: CA-C | D16: 45978 | E16: 46083 | F16: Assembly | G16: 13744 | H16: 12649 | I16: 26393 | J16: =VLOOKUP(B16,'Mar 26'!B:G,6,FALSE) -> 13744 | K16: 0 | L16: =G16-J16 -> 0 | M16: =L16-K16 -> 0
A17: Aune Brothers Construction:2460 Cajon Lane | B17: 86022 | C17: AZ-R | D17: 46091 | E17: 46099 | F17: 46122 | G17: 0 | J17: =VLOOKUP(B17,'Mar 26'!B:G,6,FALSE) -> 4247 | K17: =J17-G17 -> 4247 | L17: Invoiced This Month | M17: =-K17 -> -4247
A18: Aune Brothers Construction:Lake Havasu Multi Slide | B18: 90057 | C18: AZ-R | D18: 46128 | E18: Pre-Production | F18: Pre-Production | G18: 9211 | H18: =I18-G18 -> 9211.77 | I18: 18422.77 | J18: 0 | K18: =IF(G18=0,J18-G18,0) -> 0 | L18: =G18-J18 -> 9211 | M18: =L18-K18 -> 9211
A19: Barbara Bellio:Bellio Residence | B19: 87402 | C19: NV-R | D19: 45939 | E19: 46106 | F19: 46141 | G19: 0 | J19: =VLOOKUP(B19,'Mar 26'!B:G,6,FALSE) -> 20000 | K19: =J19-G19 -> 20000 | L19: Invoiced This Month | M19: =-K19 -> -20000
A20: Best Contracting LLC:UCSB San Benito Housing | B20: 87022 | C20: CA-C | D20: 45981 | E20: Pre-Production | F20: Pre-Production | G20: 60823 | H20: 60822 | I20: 121645 | J20: =VLOOKUP(B20,'Mar 26'!B:G,6,FALSE) -> 60823 | K20: 0 | L20: =G20-J20 -> 0 | M20: =L20-K20 -> 0
A21: Bill Jaeger:Jaeger Sliders | B21: 90185 | C21: NV-R | D21: 46140 | E21: Pre-Production | F21: Pre-Production | G21: 7191 | H21: =I21-G21 -> 7301.27 | I21: 14492.27 | K21: =IF(G21=0,J21-G21,0) -> 0 | L21: =G21-J21 -> 7191 | M21: =L21-K21 -> 7191
A22: BMG Door & Glass:Rowley | B22: 88961 | C22: AZ-R | D22: 46062 | E22: 46091 | F22: 46128 | G22: 0 | J22: =VLOOKUP(B22,'Mar 26'!B:G,6,FALSE) -> 22865 | K22: =J22-G22 -> 22865 | L22: Invoiced This Month | M22: =-K22 -> -22865
A23: BMG Door & Glass:Unell Door | B23: 89636 | C23: AZ-R | D23: 46122 | E23: Pre-Production | F23: Pre-Production | G23: 4764 | H23: =I23-G23 -> 4764 | I23: 9528 | J23: 0 | K23: 0 | L23: =G23-J23 -> 4764 | M23: =L23-K23 -> 4764
A24: Brad Lager:Palmer | B24: 87591 | C24: MO-R | D24: 46058 | E24: Pre-Production | F24: Pre-Production | G24: 25317 | H24: 25316 | I24: 50633 | J24: =VLOOKUP(B24,'Mar 26'!B:G,6,FALSE) -> 25317 | K24: 0 | L24: =G24-J24 -> 0 | M24: =L24-K24 -> 0
A25: Brett Hill Construction, Inc:4895 Kalanianaole | B25: 88674 | C25: HI-R | D25: 46055 | E25: Pre-Production | F25: Pre-Production | G25: 238760 | H25: 238759 | I25: 477519 | J25: =VLOOKUP(B25,'Mar 26'!B:G,6,FALSE) -> 238760 | K25: 0 | L25: =G25-J25 -> 0 | M25: =L25-K25 -> 0
A26: Builders Direct Supply:4545 North-Studio | B26: 85791 | C26: CA-R | D26: 45959 | E26: Pre-Production | F26: Pre-Production | G26: 8977.7 | H26: 80799.3 | I26: 89777 | J26: =VLOOKUP(B26,'Mar 26'!B:G,6,FALSE) -> 8977.7 | K26: 0 | L26: =G26-J26 -> 0 | M26: =L26-K26 -> 0
A27: Builders Direct Supply:Christian Rooney | B27: 89792 | C27: CA-R | D27: 46140 | E27: Pre-Production | F27: Pre-Production | G27: 34278 | H27: =I27-G27 -> 34278 | I27: 68556 | K27: =IF(G27=0,J27-G27,0) -> 0 | L27: =G27-J27 -> 34278 | M27: =L27-K27 -> 34278
A28: Builders Direct Supply:Marriott | B28: 88115 | C28: CA-C | D28: 46059 | E28: 46084 | F28: 46129 | G28: 0 | J28: =VLOOKUP(B28,'Mar 26'!B:G,6,FALSE) -> 62150.5 | K28: =J28-G28 -> 62150.5 | L28: Invoiced This Month | M28: =-K28 -> -62150.5
A29: Builders Direct Supply:North 4545 | B29: 83690 | C29: CA-R | D29: 45959 | E29: Pre-Production | F29: Pre-Production | G29: 41681.4 | H29: 375132.6 | I29: 416814 | J29: =VLOOKUP(B29,'Mar 26'!B:G,6,FALSE) -> 41681.4 | K29: 0 | L29: =G29-J29 -> 0 | M29: =L29-K29 -> 0
A30: Builders Direct Supply:Snell and Wilmer | B30: 86318 | C30: CA-C | D30: 46030 | E30: Pre-Production | F30: Pre-Production | G30: =26483.5+4914.5 -> 31398 | H30: 26483.5 | I30: 52967 | J30: =VLOOKUP(B30,'Mar 26'!B:G,6,FALSE) -> 26483.5 | K30: 0 | L30: =G30-J30 -> 4914.5 | M30: =L30-K30 -> 4914.5
A31: Builders FirstSource/Dixieline Lumber & Home Center:Bhill Orange County | B31: 89482 | C31: CA-R | D31: 46111 | E31: Pre-Production | F31: Pre-Production | G31: 4138 | H31: 4138 | I31: 8276 | J31: =VLOOKUP(B31,'Mar 26'!B:G,6,FALSE) -> 4138 | K31: 0 | L31: =G31-J31 -> 0 | M31: =L31-K31 -> 0
A32: Builders FirstSource/Dixieline Lumber & Home Center:Dixieline Lumber & Home Center:Rick Moore | B32: 89242 | C32: CA-C | D32: 46083 | E32: 46111 | F32: 46135 | G32: 0 | J32: =VLOOKUP(B32,'Mar 26'!B:G,6,FALSE) -> 8432 | K32: =J32-G32 -> 8432 | L32: Invoiced This Month | M32: =-K32 -> -8432
A33: Buzick Construction, Inc.:Big Blue Bar | B33: 90093 | C33: KY-C | D33: 46127 | E33: Pre-Production | F33: Pre-Production | G33: 20789 | H33: =I33-G33 -> 20789.52 | I33: 41578.52 | J33: 0 | K33: 0 | L33: =G33-J33 -> 20789 | M33: =L33-K33 -> 20789
A34: C Thru Glass:Mt. Charleston Lodge | B34: 89607 | C34: NV-C | D34: 46126 | E34: Pre-Production | F34: Pre-Production | G34: 19335 | H34: =I34-G34 -> 19335 | I34: 38670 | J34: 0 | K34: 0 | L34: =G34-J34 -> 19335 | M34: =L34-K34 -> 19335
A35: CAC Aluminum & Glass Inc.:355 Deerfield Sliding Doors | B35: 89649 | C35: IL-C | D35: 46101 | E35: Pre-Production | F35: Pre-Production | G35: 17176 | H35: 17175 | I35: 34351 | J35: =VLOOKUP(B35,'Mar 26'!B:G,6,FALSE) -> 17176 | K35: 0 | L35: =G35-J35 -> 0 | M35: =L35-K35 -> 0
A36: Callender's House of Glass:750 Picacho Ln | B36: 90005 | C36: CA-R | D36: 46128 | E36: Pre-Production | F36: Pre-Production | G36: 9786 | H36: =I36-G36 -> 9785.44 | I36: 19571.44 | J36: 0 | K36: =IF(G36=0,J36-G36,0) -> 0 | L36: =G36-J36 -> 9786 | M36: =L36-K36 -> 9786
A37: Capitol Glass & Aluminum Co.:Cypress Village | B37: 88240 | C37: FL-C | D37: 46062 | E37: 46090 | F37: 46122 | G37: 0 | J37: =VLOOKUP(B37,'Mar 26'!B:G,6,FALSE) -> 16435.5 | K37: =J37-G37 -> 16435.5 | L37: Invoiced This Month | M37: =-K37 -> -16435.5
A38: Capitol Glass Company:Sunnydale Block 7 | B38: 88227 | C38: CA-C | D38: 46020 | E38: Pre-Production | F38: Pre-Production | G38: 32005 | H38: 32005 | I38: 64010 | J38: =VLOOKUP(B38,'Mar 26'!B:G,6,FALSE) -> 32005 | K38: 0 | L38: =G38-J38 -> 0 | M38: =L38-K38 -> 0
A39: Capitol Glass Company:The Eliza | B39: 84966 | C39: CA-C | D39: 46099 | E39: Pre-Production | F39: Pre-Production | G39: 39804 | H39: 39803 | I39: 79607 | J39: =VLOOKUP(B39,'Mar 26'!B:G,6,FALSE) -> 39804 | K39: 0 | L39: =G39-J39 -> 0 | M39: =L39-K39 -> 0
A40: Catalyst Acoustics Group | B40: Unknown | D40: 44712 | E40: Pre-Production | F40: Pre-Production | G40: 4108 | H40: 0 | I40: 4108 | J40: =VLOOKUP(B40,'Mar 26'!B:G,6,FALSE) -> 4108 | K40: 0 | L40: =G40-J40 -> 0 | M40: =L40-K40 -> 0
A41: Charles Chou:Chou Folding Window | B41: 90088 | C41: NV-R | D41: 46118 | E41: Pre-Production | F41: Pre-Production | G41: 2638 | H41: =I41-G41 -> 2637.58 | I41: 5275.58 | J41: 0 | K41: 0 | L41: =G41-J41 -> 2638 | M41: =L41-K41 -> 2638
A42: Chase Kloehn:Kloehn Remodel | B42: 88513 | C42: NV-R | D42: 46085 | E42: Pre-Production | F42: Pre-Production | G42: 11224 | H42: 13423 | I42: 24647 | J42: =VLOOKUP(B42,'Mar 26'!B:G,6,FALSE) -> 11224 | K42: 0 | L42: =G42-J42 -> 0 | M42: =L42-K42 -> 0
A43: Chopper Dawson INC:Daniel Res | B43: 85396 | C43: VA-R | D43: 46090 | E43: Pre-Production | F43: Pre-Production | G43: 9792 | H43: 9792 | I43: 19584 | J43: =VLOOKUP(B43,'Mar 26'!B:G,6,FALSE) -> 9792 | K43: 0 | L43: =G43-J43 -> 0 | M43: =L43-K43 -> 0
A44: Chris & Kareen Brown:By Woods Door | B44: 86825 | C44: MD-R | D44: 46076 | E44: 46101 | F44: 46142 | G44: 0 | J44: =VLOOKUP(B44,'Mar 26'!B:G,6,FALSE) -> 6409 | K44: =J44-G44 -> 6409 | L44: Invoiced This Month | M44: =-K44 -> -6409
A45: Chuck Hamilton Construction Inc.:Shueck Pool House | B45: 89296 | C45: AR-R | D45: 46100 | E45: Pre-Production | F45: Pre-Production | G45: 109253 | H45: 109253 | I45: 218506 | J45: =VLOOKUP(B45,'Mar 26'!B:G,6,FALSE) -> 109253 | K45: 0 | L45: =G45-J45 -> 0 | M45: =L45-K45 -> 0
A46: CK2 Contracting:1221 W. Washington | B46: 88868 | C46: IL-R | D46: 46059 | E46: Pre-Production | F46: Pre-Production | G46: 17321 | H46: 17321 | I46: 34642 | J46: =VLOOKUP(B46,'Mar 26'!B:G,6,FALSE) -> 17321 | K46: 0 | L46: =G46-J46 -> 0 | M46: =L46-K46 -> 0
A47: Classic Carpentry Inc.:CC Project / 262 Mermaid's Bight | B47: 88131 | C47: FL-R | D47: 46042 | E47: 46076 | F47: 46142 | G47: 0 | J47: =VLOOKUP(B47,'Mar 26'!B:G,6,FALSE) -> 33237 | K47: =J47-G47 -> 33237 | L47: Invoiced This Month | M47: =-K47 -> -33237
A48: Classic Glass:Hotel Mohi | B48: 88845 | C48: CA-C | D48: 46115 | E48: Pre-Production | F48: Pre-Production | G48: 51819 | H48: =I48-G48 -> 51818 | I48: 103637 | J48: 0 | K48: 0 | L48: =G48-J48 -> 51819 | M48: =L48-K48 -> 51819
A49: Clear Solutions Group:Xs Remodel | B49: 89829 | C49: NV-C | D49: 46134 | E49: Pre-Production | F49: Pre-Production | G49: 90746 | H49: =I49-G49 -> 90746 | I49: 181492 | K49: =IF(G49=0,J49-G49,0) -> 0 | L49: =G49-J49 -> 90746 | M49: =L49-K49 -> 90746
A50: Clerestory LLC:Malireddy Pivot Door | B50: 89254 | C50: GA-R | D50: 46142 | E50: Pre-Production | F50: Pre-Production | G50: 8136 | H50: =I50-G50 -> 8136 | I50: 16272 | K50: =IF(G50=0,J50-G50,0) -> 0 | L50: =G50-J50 -> 8136 | M50: =L50-K50 -> 8136
A51: Commercial Contractors, Inc.:Flabletics Tampa FL | B51: 90388 | C51: FL-C | D51: 46140 | E51: Pre-Production | F51: Pre-Production | G51: 25275 | H51: =I51-G51 -> 25275.26 | I51: 50550.26 | K51: =IF(G51=0,J51-G51,0) -> 0 | L51: =G51-J51 -> 25275 | M51: =L51-K51 -> 25275
A52: Crisci Builders:Lot 147 Addition | B52: 87426 | C52: NV-R | D52: 46084 | E52: Pre-Production | F52: Pre-Production | G52: 94654 | H52: 94653 | I52: 189307 | J52: =VLOOKUP(B52,'Mar 26'!B:G,6,FALSE) -> 94654 | K52: 0 | L52: =G52-J52 -> 0 | M52: =L52-K52 -> 0
A53: Crystal Glass Inc.:New Logan Elementry | B53: 83108 | C53: MI-C | D53: 45764 | E53: Pre-Production | F53: Pre-Production | G53: 172204.5 | H53: 172204.5 | I53: 344409 | J53: =VLOOKUP(B53,'Mar 26'!B:G,6,FALSE) -> 172204.5 | K53: 0 | L53: =G53-J53 -> 0 | M53: =L53-K53 -> 0
A54: D & R Glass:Cedar and Sage | B54: 84134 | C54: CA-C | D54: 45945 | E54: 46091 | F54: Coating | G54: 64205 | H54: 61477 | I54: 125682 | J54: =VLOOKUP(B54,'Mar 26'!B:G,6,FALSE) -> 64205 | K54: 0 | L54: =G54-J54 -> 0 | M54: =L54-K54 -> 0
A55: Dan and Molly Dirscherl:Dirscherl Cabana | B55: 85777 | C55: NJ-R | D55: 46093 | E55: Pre-Production | F55: Pre-Production | G55: 17769 | H55: 168389 | I55: 186158 | J55: =VLOOKUP(B55,'Mar 26'!B:G,6,FALSE) -> 17769 | K55: 0 | L55: =G55-J55 -> 0 | M55: =L55-K55 -> 0
A56: David Ostrander:Ostrander Residence Remodel | B56: 88087 | C56: MN-R | D56: 46064 | E56: Pre-Production | F56: Pre-Production | G56: 123085 | H56: 123084 | I56: 246169 | J56: =VLOOKUP(B56,'Mar 26'!B:G,6,FALSE) -> 123085 | K56: 0 | L56: =G56-J56 -> 0 | M56: =L56-K56 -> 0
A57: Debbie Piliero:46 Upper Rd | B57: 87161 | C57: CA-R | D57: 45924 | E57: 45992 | F57: Coating | G57: 17417 | H57: 17417 | I57: 34834 | J57: =VLOOKUP(B57,'Mar 26'!B:G,6,FALSE) -> 17417 | K57: 0 | L57: =G57-J57 -> 0 | M57: =L57-K57 -> 0
A58: Desert Window Systems:Lennar | B58: 88180 | C58: NV-R | D58: 46078 | E58: 46090 | F58: 46133 | G58: 0 | J58: =VLOOKUP(B58,'Mar 26'!B:G,6,FALSE) -> 38957 | K58: =J58-G58 -> 38957 | L58: Invoiced This Month | M58: =-K58 -> -38957
A59: Devoe Custom Homes:Bodnar | B59: 89338 | C59: FL-R | D59: 46134 | E59: Pre-Production | F59: Pre-Production | G59: 14498 | H59: =I59-G59 -> 14498 | I59: 28996 | K59: =IF(G59=0,J59-G59,0) -> 0 | L59: =G59-J59 -> 14498 | M59: =L59-K59 -> 14498
A60: Devoe Custom Homes:Vanderveen | B60: 89554 | C60: FL-R | D60: 46100 | E60: Pre-Production | F60: Pre-Production | G60: 17304 | H60: 17303 | I60: 34607 | J60: =VLOOKUP(B60,'Mar 26'!B:G,6,FALSE) -> 17304 | K60: 0 | L60: =G60-J60 -> 0 | M60: =L60-K60 -> 0
A61: DGB Glass Inc.:Hotel Grey | B61: 86965 | C61: TX-C | D61: 45924 | E61: 46048 | F61: 46120 | G61: 0 | J61: =VLOOKUP(B61,'Mar 26'!B:G,6,FALSE) -> 49026 | K61: =J61-G61 -> 49026 | L61: Invoiced This Month | M61: =-K61 -> -49026
A62: Discount Glass & Mirror Inc.:Cardella | B62: 83204 | C62: CA-C | D62: 46108 | E62: Pre-Production | F62: Pre-Production | G62: 44368 | H62: 44368 | I62: 88736 | J62: =VLOOKUP(B62,'Mar 26'!B:G,6,FALSE) -> 44368 | K62: 0 | L62: =G62-J62 -> 0 | M62: =L62-K62 -> 0
A63: Discount Glass & Mirror Inc.:Encinitas | B63: 85495 | C63: CA-C | D63: 46083 | E63: 46106 | F63: Cutting | G63: 29175 | H63: 29175 | I63: 58350 | J63: =VLOOKUP(B63,'Mar 26'!B:G,6,FALSE) -> 29175 | K63: 0 | L63: =G63-J63 -> 0 | M63: =L63-K63 -> 0
A64: Donatello Bonasera Development, LLC:Casa Faten | B64: 88756 | C64: CA-R | D64: 46092 | E64: Pre-Production | F64: Pre-Production | G64: 160000 | H64: 158239 | I64: 318239 | J64: =VLOOKUP(B64,'Mar 26'!B:G,6,FALSE) -> 160000 | K64: 0 | L64: =G64-J64 -> 0 | M64: =L64-K64 -> 0
A65: Donatello Bonasera Development, LLC:The F Penthouse | B65: 89698 | C65: CA-R | D65: 46091 | E65: Pre-Production | F65: Pre-Production | G65: 8935.32 | H65: 8935.32 | I65: 17870.64 | J65: =VLOOKUP(B65,'Mar 26'!B:G,6,FALSE) -> 8935.32 | K65: 0 | L65: =G65-J65 -> 0 | M65: =L65-K65 -> 0
A66: Don's Mobile Glass:Grossi | B66: 88858 | C66: CA-R | D66: 46105 | E66: Pre-Production | F66: Pre-Production | G66: 16192 | H66: 16192 | I66: 32384 | J66: =VLOOKUP(B66,'Mar 26'!B:G,6,FALSE) -> 16192 | K66: 0 | L66: =G66-J66 -> 0 | M66: =L66-K66 -> 0
A67: Doors, Etc.:Doors Etc HSW | B67: 88511 | C67: CA-R | D67: 46072 | E67: Pre-Production | F67: Pre-Production | G67: 19222 | H67: 19222 | I67: 38444 | J67: =VLOOKUP(B67,'Mar 26'!B:G,6,FALSE) -> 19222 | K67: 0 | L67: =G67-J67 -> 0 | M67: =L67-K67 -> 0
A68: Dugally Oberfeld, Inc.:Cox | B68: 83729 | C68: CA-R | D68: 46028 | E68: Pre-Production | F68: Pre-Production | G68: 31223 | H68: 27501 | I68: 58724 | J68: =VLOOKUP(B68,'Mar 26'!B:G,6,FALSE) -> 31223 | K68: 0 | L68: =G68-J68 -> 0 | M68: =L68-K68 -> 0
A69: Dynamic Glass:Antero Resources | B69: 85504 | C69: CO-C | D69: 46100 | E69: Pre-Production | F69: Pre-Production | G69: 151068 | H69: 151068 | I69: 302136 | J69: =VLOOKUP(B69,'Mar 26'!B:G,6,FALSE) -> 151068 | K69: 0 | L69: =G69-J69 -> 0 | M69: =L69-K69 -> 0
A70: E & Z Glass & Window:Cotton On Dallas Galleria | B70: 89285 | C70: TX-R | D70: 46098 | E70: Pre-Production | F70: Pre-Production | G70: 23405 | H70: 23404 | I70: 46809 | J70: =VLOOKUP(B70,'Mar 26'!B:G,6,FALSE) -> 23405 | K70: 0 | L70: =G70-J70 -> 0 | M70: =L70-K70 -> 0
A71: EAP Glass:4th Street North Apts | B71: 85454 | C71: CO-C | D71: 12/30/2025 | E71: 46044 | F71: 46139 | G71: 0 | J71: =VLOOKUP(B71,'Mar 26'!B:G,6,FALSE) -> 14438 | K71: =J71-G71 -> 14438 | L71: Invoiced This Month | M71: =-K71 -> -14438
A72: Echelon Builders LLC:Residential | B72: 89324 | C72: HI-R | D72: 46141 | E72: Pre-Production | F72: Pre-Production | G72: 15963 | H72: =I72-G72 -> 15962 | I72: 31925 | K72: =IF(G72=0,J72-G72,0) -> 0 | L72: =G72-J72 -> 15963 | M72: =L72-K72 -> 15963
A73: Edge Design and Construction INC:Brooks Project Add On | B73: 89984 | C73: NV-R | D73: 46112 | E73: Pre-Production | F73: Pre-Production | G73: 1897 | H73: 0 | I73: 1897 | J73: =VLOOKUP(B73,'Mar 26'!B:G,6,FALSE) -> 1897 | K73: 0 | L73: =G73-J73 -> 0 | M73: =L73-K73 -> 0
A74: Element Facades 13:299 MILWAUKEE | B74: 86960 | C74: CO-C | D74: 45986 | E74: Pre-Production | F74: Pre-Production | G74: 8962 | H74: 26885 | I74: 35847 | J74: =VLOOKUP(B74,'Mar 26'!B:G,6,FALSE) -> 8962 | K74: 0 | L74: =G74-J74 -> 0 | M74: =L74-K74 -> 0
A75: Elham Taherian:2180 Havensight Add On | B75: 89760 | C75: NV-R | D75: 46139 | E75: Pre-Production | F75: Pre-Production | G75: 5641 | H75: =I75-G75 -> 5640 | I75: 11281 | K75: =IF(G75=0,J75-G75,0) -> 0 | L75: =G75-J75 -> 5641 | M75: =L75-K75 -> 5641
A76: Elite Glazing Inc.:RSF Clubhouse | B76: 85987 | C76: CA-C | D76: 46115 | E76: Pre-Production | F76: Pre-Production | G76: 68043 | H76: =I76-G76 -> 68042 | I76: 136085 | J76: 0 | K76: 0 | L76: =G76-J76 -> 68043 | M76: =L76-K76 -> 68043
A77: Emerald Glass:The Frank | B77: 84692 | C77: WA-C | D77: 46076 | E77: 46100 | F77: Pull Material | G77: 5345 | H77: 5344 | I77: 10689 | J77: =VLOOKUP(B77,'Mar 26'!B:G,6,FALSE) -> 5345 | K77: 0 | L77: =G77-J77 -> 0 | M77: =L77-K77 -> 0
A78: Environmental Glass Inc:Ann Arbor Thurston | B78: 84161 | C78: MI-C | D78: 46013 | E78: Pre-Production | F78: Pre-Production | G78: 176687 | H78: 176686 | I78: 353373 | J78: =VLOOKUP(B78,'Mar 26'!B:G,6,FALSE) -> 176687 | K78: 0 | L78: =G78-J78 -> 0 | M78: =L78-K78 -> 0
A79: Environmental Glass Inc:Mitchell Elementary | B79: 81492-R1 | C79: MI-C | D79: 45868 | E79: Pre-Production | F79: Pre-Production | G79: 114974 | H79: 114973 | I79: 229947 | J79: =VLOOKUP(B79,'Mar 26'!B:G,6,FALSE) -> 114974 | K79: 0 | L79: =G79-J79 -> 0 | M79: =L79-K79 -> 0
A80: Flat Iron Development Co:Brandon Baca Voyage | B80: 89675 | C80: CO-R | D80: 46114 | E80: Pre-Production | F80: Pre-Production | G80: 6002 | H80: =I80-G80 -> 6002 | I80: 12004 | J80: 0 | K80: 0 | L80: =G80-J80 -> 6002 | M80: =L80-K80 -> 6002
A81: Ford Metro Inc:Chapter / Ann Arbor | B81: 87492 | C81: MN-R | D81: 46063 | E81: Pre-Production | F81: Pre-Production | G81: 22079 | H81: 22079 | I81: 44158 | J81: =VLOOKUP(B81,'Mar 26'!B:G,6,FALSE) -> 22079 | K81: 0 | L81: =G81-J81 -> 0 | M81: =L81-K81 -> 0
A82: Franklin Herbas:Herbas Folding | B82: 89313 | C82: CA-R | D82: 46079 | E82: 46111 | F82: Pull Material | G82: 8773 | H82: 8773 | I82: 17546 | J82: =VLOOKUP(B82,'Mar 26'!B:G,6,FALSE) -> 8773 | K82: 0 | L82: =G82-J82 -> 0 | M82: =L82-K82 -> 0
A83: Gallatin Glass Works Inc:5026 Iron Ridge Patio | B83: 88818 | C83: MT-R | D83: 46121 | E83: Pre-Production | F83: Pre-Production | G83: 15127 | H83: =I83-G83 -> 15126 | I83: 30253 | J83: 0 | K83: 0 | L83: =G83-J83 -> 15127 | M83: =L83-K83 -> 15127
A84: Gen 3 Hospitality:Richardson House | B84: 88603 | C84: NV-R | D84: 46028 | E84: 46085 | F84: 46127 | G84: 0 | J84: =VLOOKUP(B84,'Mar 26'!B:G,6,FALSE) -> 23396 | K84: =J84-G84 -> 23396 | L84: Invoiced This Month | M84: =-K84 -> -23396
A85: Giroux Glass:SoCalGas Loggia | B85: 88082 | C85: CA-C | D85: 46076 | E85: Pre-Production | F85: Pre-Production | G85: 35295 | H85: 35294 | I85: 70589 | J85: =VLOOKUP(B85,'Mar 26'!B:G,6,FALSE) -> 35295 | K85: 0 | L85: =G85-J85 -> 0 | M85: =L85-K85 -> 0
A86: Glass and Metals, Inc:2100 Crystal | B86: 88012 | C86: VA-C | D86: 46086 | E86: Pre-Production | F86: Pre-Production | G86: 25461 | H86: 25461 | I86: 50922 | J86: =VLOOKUP(B86,'Mar 26'!B:G,6,FALSE) -> 25461 | K86: 0 | L86: =G86-J86 -> 0 | M86: =L86-K86 -> 0
A87: Golden Glass Inc.:Pepperdine University | B87: 76624 | C87: CA-C | D87: 4/19/2024 | E87: 46038 | F87: Cutting | G87: 82176 | H87: 82176 | I87: 164352 | J87: =VLOOKUP(B87,'Mar 26'!B:G,6,FALSE) -> 82176 | K87: 0 | L87: =G87-J87 -> 0 | M87: =L87-K87 -> 0
A88: Goldfinch Brothers:Stoel Rives L48 | B88: 89287 | C88: WA-C | D88: 46113 | E88: Pre-Production | F88: Pre-Production | G88: 89586 | H88: =I88-G88 -> 89585 | I88: 179171 | J88: 0 | K88: 0 | L88: =G88-J88 -> 89586 | M88: =L88-K88 -> 89586
A89: GP Glass & Mirror LLC:George_Additional Fixed Window | B89: 89773 | C89: NV-R | D89: 46106 | E89: Pre-Production | F89: 46142 | G89: 0 | J89: =VLOOKUP(B89,'Mar 26'!B:G,6,FALSE) -> 1142.27 | K89: =J89-G89 -> 1142.27 | L89: Invoiced This Month | M89: =-K89 -> -1142.27
A90: Green Glass:Overland | B90: 89055 | C90: CA-C | D90: 46120 | E90: Pre-Production | F90: Pre-Production | G90: 8582 | H90: =I90-G90 -> 8582 | I90: 17164 | J90: 0 | K90: 0 | L90: =G90-J90 -> 8582 | M90: =L90-K90 -> 8582
A91: Hall Aluminum Products:TT Union Building D | B91: 87359 | C91: IN-C | D91: 46125 | E91: Pre-Production | F91: Pre-Production | G91: 19467 | H91: =I91-G91 -> 19466 | I91: 38933 | J91: 0 | K91: 0 | L91: =G91-J91 -> 19467 | M91: =L91-K91 -> 19467
A92: Hardman Glazing Management LLC:800 Corte Madera | B92: 89412 | C92: CA-R | D92: 46126 | E92: Pre-Production | F92: Pre-Production | G92: 20897 | H92: =I92-G92 -> 0 | I92: 20897 | J92: 0 | K92: 0 | L92: =G92-J92 -> 20897 | M92: =L92-K92 -> 20897
A93: Hardman Glazing Management LLC:Brown Shop | B93: 87128 | C93: ID-R | D93: 46034 | E93: 46099 | F93: 46121 | G93: 0 | J93: =VLOOKUP(B93,'Mar 26'!B:G,6,FALSE) -> 25470 | K93: =J93-G93 -> 25470 | L93: Invoiced This Month | M93: =-K93 -> -25470
A94: Hardman Glazing Management LLC:Hinged Door | B94: 89121 | C94: CA-R | D94: 46062 | E94: 46098 | F94: 46128 | G94: 0 | J94: =VLOOKUP(B94,'Mar 26'!B:G,6,FALSE) -> 2712 | K94: =J94-G94 -> 2712 | L94: Invoiced This Month | M94: =-K94 -> -2712
A95: Hardman Glazing Management LLC:Utility building - 800 Corte Madera | B95: 89867 | C95: CA-R | D95: 46126 | E95: Pre-Production | F95: Pre-Production | G95: 14271.62 | H95: =I95-G95 -> 0 | I95: 14271.62 | J95: 0 | K95: 0 | L95: =G95-J95 -> 14271.62 | M95: =L95-K95 -> 14271.62
A96: Hasco Constrution:Sperryn Jones | B96: 82632 | C96: SN-R | D96: 45758 | E96: Pre-Production | F96: Pre-Production | G96: 109478 | H96: 109478 | I96: 218956 | J96: =VLOOKUP(B96,'Mar 26'!B:G,6,FALSE) -> 109478 | K96: 0 | L96: =G96-J96 -> 0 | M96: =L96-K96 -> 0
A97: Heart of America Aston LLC:592 Aston | B97: 84210 | C97: IL-C | D97: 45876 | E97: Pre-Production | F97: Pre-Production | G97: 31567 | H97: 46437 | I97: 78004 | J97: =VLOOKUP(B97,'Mar 26'!B:G,6,FALSE) -> 31567 | K97: 0 | L97: =G97-J97 -> 0 | M97: =L97-K97 -> 0
A98: Helou Construction:Rosebowl South Endzone Club | B98: 88433 | C98: CA-C | D98: 46036 | E98: Pre-Production | F98: Pre-Production | G98: 80538 | H98: 80538 | I98: 161076 | J98: =VLOOKUP(B98,'Mar 26'!B:G,6,FALSE) -> 80538 | K98: 0 | L98: =G98-J98 -> 0 | M98: =L98-K98 -> 0
A99: Henry Grause:Grause Residence | B99: 88896 | C99: FL-R | D99: 46058 | E99: 46099 | F99: 46129 | G99: 0 | J99: =VLOOKUP(B99,'Mar 26'!B:G,6,FALSE) -> 10238 | K99: =J99-G99 -> 10238 | L99: Invoiced This Month | M99: =-K99 -> -10238
A100: Ikirkpatrick Construction:Stewart Residence 3 | B100: 87792 | C100: HI-R | D100: 45992 | E100: 46045 | F100: Cutting | G100: 49733 | H100: 49713 | I100: 99446 | J100: =VLOOKUP(B100,'Mar 26'!B:G,6,FALSE) -> 49733 | K100: 0 | L100: =G100-J100 -> 0 | M100: =L100-K100 -> 0
...

Sheet May 26
A1: Customer | B1: Q Number | C1: Region | D1: Payment Date | E1: Production Start Day | F1: Stage | G1: DEPOSIT | H1: FINAL | I1: TOTAL | J1: BOM Dep | K1: Dep to Rev | L1: New Dep this Month
A2: 1st Choice Glass:MUSC - Clemson | B2: 88562 | C2: NC-C | D2: 46091 | E2: Pre-Production | F2: Pre-Production | G2: 51110.14 | H2: 0 | I2: 51110.14 | J2: =IFERROR(VLOOKUP(B2,'Apr 26'!B:G,6,FALSE),0) -> 51110.14 | K2: 0 | L2: =G2-J2 -> 0
A3: A&A Window Products Inc:45 Littles Road | B3: 88556 | C3: MA-R | D3: 46086 | E3: Pre-Production | F3: Pre-Production | G3: 11662 | H3: 11662 | I3: 23324 | J3: =IFERROR(VLOOKUP(B3,'Apr 26'!B:G,6,FALSE),0) -> 11662 | K3: 0 | L3: =G3-J3 -> 0
A4: Advanced Windows:1990 K Street | B4: 87616 | C4: MD-C | D4: 46069 | E4: Pre-Production | F4: Pre-Production | G4: 35586 | H4: 9375 | I4: 44961 | J4: =IFERROR(VLOOKUP(B4,'Apr 26'!B:G,6,FALSE),0) -> 35586 | K4: 0 | L4: =G4-J4 -> 0
A5: Advanced Windows:Golden Hill | B5: 84541 | C5: MD-C | D5: 45943 | E5: 46083 | F5: 46153 | G5: 0 | J5: =IFERROR(VLOOKUP(B5,'Apr 26'!B:G,6,FALSE),0) -> 10262 | K5: =J5-G5 -> 10262 | L5: Invoiced This Month
A6: AFR Construction:Boe Dekker | B6: 87676 | C6: NV-R | D6: 46125 | E6: Pre-Production | F6: Pre-Production | G6: 2400.25 | H6: =I6-G6 -> 2449.75 | I6: 4850 | J6: =IFERROR(VLOOKUP(B6,'Apr 26'!B:G,6,FALSE),0) -> 2400.25 | K6: 0 | L6: =G6-J6 -> 0
A7: Ajay Glass & Mirror Co., Inc.:Billitier | B7: 89718 | C7: NY-R | D7: 46105 | E7: 46119 | F7: 46153 | G7: 0 | J7: =IFERROR(VLOOKUP(B7,'Apr 26'!B:G,6,FALSE),0) -> 9796.19 | K7: =J7-G7 -> 9796.19 | L7: Invoiced This Month
A8: Akis Doganis:Doganis Residence | B8: 87185 | C8: NV-R | D8: 45995 | E8: Pre-Production | F8: Pre-Production | G8: 31515 | H8: 31514 | I8: 63029 | J8: =IFERROR(VLOOKUP(B8,'Apr 26'!B:G,6,FALSE),0) -> 31515 | K8: 0 | L8: =G8-J8 -> 0
A9: All New Glass:Chanel UTC | B9: 83846 | C9: WA-C | D9: 45880 | E9: 46076 | F9: 46163 | G9: 0 | J9: =IFERROR(VLOOKUP(B9,'Apr 26'!B:G,6,FALSE),0) -> 186264.5 | K9: =J9-G9 -> 186264.5 | L9: Invoiced This Month
A10: Alli Construction:Chaparral Janiga Residence | B10: 89424 | C10: CA-R | D10: 46090 | E10: 46141 | F10: Pull Material | G10: 16906.51 | H10: 16906.5 | I10: 33813.01 | J10: =IFERROR(VLOOKUP(B10,'Apr 26'!B:G,6,FALSE),0) -> 16906.51 | K10: 0 | L10: =G10-J10 -> 0
A11: American Glass & Mirror Company:1000 Nevillewood Drive | B11: 87836 | C11: VA-C | D11: 46098 | E11: Pre-Production | F11: Pre-Production | G11: 18709 | H11: 18709 | I11: 37418 | J11: =IFERROR(VLOOKUP(B11,'Apr 26'!B:G,6,FALSE),0) -> 18709 | K11: 0 | L11: =G11-J11 -> 0
A12: Angie Nyborg:Nyborg Residence | B12: 89450 | C12: NV-R | D12: 46097 | E12: 46122 | F12: 46171 | G12: 0 | J12: =IFERROR(VLOOKUP(B12,'Apr 26'!B:G,6,FALSE),0) -> 29728 | K12: =IF(G12=0,J12-G12,0) -> 29728 | L12: Invoiced This Month
A13: Aragon Construction, Inc.:Puente Hills | B13: 82690 | C13: CA-C | D13: 45978 | E13: 46083 | F13: 46171 | G13: 0 | J13: =IFERROR(VLOOKUP(B13,'Apr 26'!B:G,6,FALSE),0) -> 13744 | K13: =IF(G13=0,J13-G13,0) -> 13744 | L13: Invoiced This Month
A14: Architectural Glass & Design:9825 Stonecrest | B14: 88159 | C14: CA-C | D14: 46148 | E14: Pre-Production | F14: Pre-Production | G14: 8819 | H14: =I14-G14 -> 8818 | I14: 17637 | J14: =IFERROR(VLOOKUP(B14,'Apr 26'!B:G,6,FALSE),0) -> 0 | K14: 0 | L14: =G14-J14 -> 8819
A15: Aune Brothers Construction:Lake Havasu Multi Slide | B15: 90057 | C15: AZ-R | D15: 46128 | E15: Pre-Production | F15: Pre-Production | G15: 9211 | H15: =I15-G15 -> 9211.77 | I15: 18422.77 | J15: =IFERROR(VLOOKUP(B15,'Apr 26'!B:G,6,FALSE),0) -> 9211 | K15: =IF(G15=0,J15-G15,0) -> 0 | L15: =G15-J15 -> 0
A16: Best Contracting LLC:UCSB San Benito Housing | B16: 87022 | C16: CA-C | D16: 45981 | E16: Pre-Production | F16: Pre-Production | G16: 60823 | H16: 60822 | I16: 121645 | J16: =IFERROR(VLOOKUP(B16,'Apr 26'!B:G,6,FALSE),0) -> 60823 | K16: 0 | L16: =G16-J16 -> 0
A17: Bill Jaeger:Jaeger Sliders | B17: 90185 | C17: NV-R | D17: 46140 | E17: Pre-Production | F17: Pre-Production | G17: 7191 | H17: =I17-G17 -> 7301.27 | I17: 14492.27 | J17: =IFERROR(VLOOKUP(B17,'Apr 26'!B:G,6,FALSE),0) -> 7191 | K17: =IF(G17=0,J17-G17,0) -> 0 | L17: =G17-J17 -> 0
A18: BMG Door & Glass:Unell Door | B18: 89636 | C18: AZ-R | D18: 46122 | E18: 46127 | F18: 46170 | G18: 0 | J18: =IFERROR(VLOOKUP(B18,'Apr 26'!B:G,6,FALSE),0) -> 4764 | K18: =IF(G18=0,J18-G18,0) -> 4764 | L18: Invoiced This Month
A19: Boulder Ridge Sash & Door:129 Tahoe Tavern | B19: 89731 | C19: CA-R | D19: 46147 | E19: Pre-Production | F19: Pre-Production | G19: 13338.01 | H19: =I19-G19 -> 13336.99 | I19: 26675 | J19: =IFERROR(VLOOKUP(B19,'Apr 26'!B:G,6,FALSE),0) -> 0 | K19: 0 | L19: =G19-J19 -> 13338.01
A20: Boyett Construction Inc:Ian | B20: 90450 | C20: CA-R | D20: 46146 | E20: Pre-Production | F20: Pre-Production | G20: 7699 | H20: =I20-G20 -> 7699.29 | I20: 15398.29 | J20: =IFERROR(VLOOKUP(B20,'Apr 26'!B:G,6,FALSE),0) -> 0 | K20: 0 | L20: =G20-J20 -> 7699
A21: Brad Lager:Palmer | B21: 87591 | C21: MO-R | D21: 46058 | E21: 46125 | F21: Pull Material | G21: 25317 | H21: 25316 | I21: 50633 | J21: =IFERROR(VLOOKUP(B21,'Apr 26'!B:G,6,FALSE),0) -> 25317 | K21: 0 | L21: =G21-J21 -> 0
A22: Brett Hill Construction, Inc:4895 Kalanianaole | B22: 88674 | C22: HI-R | D22: 46055 | E22: 46132 | F22: Pull Material | G22: 238760 | H22: 238759 | I22: 477519 | J22: =IFERROR(VLOOKUP(B22,'Apr 26'!B:G,6,FALSE),0) -> 238760 | K22: 0 | L22: =G22-J22 -> 0
A23: Builders Direct Supply:4545 North-Studio | B23: 85791 | C23: CA-R | D23: 45959 | E23: Pre-Production | F23: Pre-Production | G23: 8977.7 | H23: 80799.3 | I23: 89777 | J23: =IFERROR(VLOOKUP(B23,'Apr 26'!B:G,6,FALSE),0) -> 8977.7 | K23: 0 | L23: =G23-J23 -> 0
A24: Builders Direct Supply:Christian Rooney | B24: 89792 | C24: CA-R | D24: 46140 | E24: Pre-Production | F24: Pre-Production | G24: 34278 | H24: =I24-G24 -> 34278 | I24: 68556 | J24: =IFERROR(VLOOKUP(B24,'Apr 26'!B:G,6,FALSE),0) -> 34278 | K24: =IF(G24=0,J24-G24,0) -> 0 | L24: =G24-J24 -> 0
A25: Builders Direct Supply:Keel Residence | B25: 90329 | C25: CA-R | D25: 05/14/2026 | E25: Pre-Production | F25: Pre-Production | G25: 8966.25 | H25: =I25-G25 -> 8966.3 | I25: 17932.55 | J25: =IFERROR(VLOOKUP(B25,'Apr 26'!B:G,6,FALSE),0) -> 0 | K25: 0 | L25: =G25-J25 -> 8966.25
A26: Builders Direct Supply:North 4545 | B26: 83690 | C26: CA-R | D26: 45959 | E26: Pre-Production | F26: Pre-Production | G26: 41681.4 | H26: 375132.6 | I26: 416814 | J26: =IFERROR(VLOOKUP(B26,'Apr 26'!B:G,6,FALSE),0) -> 41681.4 | K26: 0 | L26: =G26-J26 -> 0
A27: Builders Direct Supply:Snell and Wilmer | B27: 86318 | C27: CA-C | D27: 46030 | E27: 46140 | F27: Pull Material | G27: =26483.5+4914.5 -> 31398 | H27: 26483.5 | I27: 52967 | J27: =IFERROR(VLOOKUP(B27,'Apr 26'!B:G,6,FALSE),0) -> 31398 | K27: 0 | L27: =G27-J27 -> 0
A28: Builders FirstSource/Dixieline Lumber & Home Center:1416 Stone Canyon Rd | B28: 89873 | C28: CA-R | D28: 46168 | E28: Pre-Production | F28: Pre-Production | G28: 165000 | H28: =I28-G28 -> 165000 | I28: 330000 | L28: =G28-J28 -> 165000
A29: Builders FirstSource/Dixieline Lumber & Home Center:Bhill Orange County | B29: 89482 | C29: CA-R | D29: 46111 | E29: 46119 | F29: 46143 | G29: 0 | J29: =IFERROR(VLOOKUP(B29,'Apr 26'!B:G,6,FALSE),0) -> 4138 | K29: =J29-G29 -> 4138 | L29: Invoiced This Month
A30: Builders FirstSource/Dixieline Lumber & Home Center:Kyle Newport | B30: 90207 | C30: CA-R | D30: 46168 | E30: Pre-Production | F30: Pre-Production | G30: 4969 | H30: =I30-G30 -> 4970 | I30: 9939 | L30: =G30-J30 -> 4969
A31: Buzick Construction, Inc.:Big Blue Bar | B31: 90093 | C31: KY-C | D31: 46127 | E31: Pre-Production | F31: Pre-Production | G31: 20789 | H31: =I31-G31 -> 20789.52 | I31: 41578.52 | J31: =IFERROR(VLOOKUP(B31,'Apr 26'!B:G,6,FALSE),0) -> 20789 | K31: 0 | L31: =G31-J31 -> 0
A32: C Thru Glass:Mt. Charleston Lodge | B32: 89607 | C32: NV-C | D32: 46126 | E32: Pre-Production | F32: Pre-Production | G32: 19335 | H32: =I32-G32 -> 19335 | I32: 38670 | J32: =IFERROR(VLOOKUP(B32,'Apr 26'!B:G,6,FALSE),0) -> 19335 | K32: 0 | L32: =G32-J32 -> 0
A33: CAC Aluminum & Glass Inc.:355 Deerfield Sliding Doors | B33: 89649 | C33: IL-C | D33: 46101 | E33: 46126 | F33: Pull Material | G33: 17176 | H33: 17175 | I33: 34351 | J33: =IFERROR(VLOOKUP(B33,'Apr 26'!B:G,6,FALSE),0) -> 17176 | K33: 0 | L33: =G33-J33 -> 0
A34: Callender's House of Glass:750 Picacho Ln | B34: 90005 | C34: CA-R | D34: 46128 | E34: Pre-Production | F34: Pre-Production | G34: 9786 | H34: =I34-G34 -> 9785.44 | I34: 19571.44 | J34: =IFERROR(VLOOKUP(B34,'Apr 26'!B:G,6,FALSE),0) -> 9786 | K34: =IF(G34=0,J34-G34,0) -> 0 | L34: =G34-J34 -> 0
A35: Capitol Glass Company:Sunnydale Block 7 | B35: 88227 | C35: CA-C | D35: 46020 | E35: 46133 | F35: Pull Material | G35: 32005 | H35: 32005 | I35: 64010 | J35: =IFERROR(VLOOKUP(B35,'Apr 26'!B:G,6,FALSE),0) -> 32005 | K35: 0 | L35: =G35-J35 -> 0
A36: Capitol Glass Company:The Eliza | B36: 84966 | C36: CA-C | D36: 46099 | E36: Pre-Production | F36: Pre-Production | G36: 39804 | H36: 39803 | I36: 79607 | J36: =IFERROR(VLOOKUP(B36,'Apr 26'!B:G,6,FALSE),0) -> 39804 | K36: 0 | L36: =G36-J36 -> 0
A37: Catalyst Acoustics Group | B37: Unknown | D37: 44712 | E37: Pre-Production | F37: Pre-Production | G37: 4108 | H37: 0 | I37: 4108 | J37: =IFERROR(VLOOKUP(B37,'Apr 26'!B:G,6,FALSE),0) -> 4108 | K37: 0 | L37: =G37-J37 -> 0
A38: Charles Chou:Chou Folding Window | B38: 90088 | C38: NV-R | D38: 46118 | E38: 46134 | F38: 46155 | G38: 0 | J38: =IFERROR(VLOOKUP(B38,'Apr 26'!B:G,6,FALSE),0) -> 2638 | K38: =J38-G38 -> 2638 | L38: Invoiced This Month
A39: Charlotte Rosiak:1805 Villa De Conde Way Entry | B39: 90923 | C39: NV-R | D39: 46160 | E39: Pre-Production | F39: Pre-Production | G39: 7275.85 | H39: =I39-G39 -> 7275.84 | I39: 14551.69 | L39: =G39-J39 -> 7275.85
A40: Chase Kloehn:Kloehn Remodel | B40: 88513 | C40: NV-R | D40: 46085 | E40: Pre-Production | F40: Pre-Production | G40: 11224 | H40: 13423 | I40: 24647 | J40: =IFERROR(VLOOKUP(B40,'Apr 26'!B:G,6,FALSE),0) -> 11224 | K40: 0 | L40: =G40-J40 -> 0
A41: Chopper Dawson INC:Daniel Res | B41: 85396 | C41: VA-R | D41: 46090 | E41: Pre-Production | F41: 46163 | G41: 0 | J41: =IFERROR(VLOOKUP(B41,'Apr 26'!B:G,6,FALSE),0) -> 9792 | K41: =J41-G41 -> 9792 | L41: Invoiced This Month
A42: Chuck Hamilton Construction Inc.:Shueck Pool House | B42: 89296 | C42: AR-R | D42: 46100 | E42: Pre-Production | F42: Pre-Production | G42: 109253 | H42: 109253 | I42: 218506 | J42: =IFERROR(VLOOKUP(B42,'Apr 26'!B:G,6,FALSE),0) -> 109253 | K42: 0 | L42: =G42-J42 -> 0
A43: CK2 Contracting:1221 W. Washington | B43: 88868 | C43: IL-R | D43: 46059 | E43: Pre-Production | F43: Pre-Production | G43: 17321 | H43: 17321 | I43: 34642 | J43: =IFERROR(VLOOKUP(B43,'Apr 26'!B:G,6,FALSE),0) -> 17321 | K43: 0 | L43: =G43-J43 -> 0
A44: Classic Glass:Hotel Mohi | B44: 88845 | C44: CA-C | D44: 46115 | E44: Pre-Production | F44: Pre-Production | G44: 51819 | H44: =I44-G44 -> 51818 | I44: 103637 | J44: =IFERROR(VLOOKUP(B44,'Apr 26'!B:G,6,FALSE),0) -> 51819 | K44: 0 | L44: =G44-J44 -> 0
A45: Clear Solutions Group:Xs Remodel | B45: 89829 | C45: NV-C | D45: 46134 | E45: Pre-Production | F45: Pre-Production | G45: 90746 | H45: =I45-G45 -> 90746 | I45: 181492 | J45: =IFERROR(VLOOKUP(B45,'Apr 26'!B:G,6,FALSE),0) -> 90746 | K45: =IF(G45=0,J45-G45,0) -> 0 | L45: =G45-J45 -> 0
A46: Clerestory LLC:Malireddy Pivot Door | B46: 89254 | C46: GA-R | D46: 46142 | E46: Pre-Production | F46: Pre-Production | G46: 8136 | H46: =I46-G46 -> 8136 | I46: 16272 | J46: =IFERROR(VLOOKUP(B46,'Apr 26'!B:G,6,FALSE),0) -> 8136 | K46: =IF(G46=0,J46-G46,0) -> 0 | L46: =G46-J46 -> 0
A47: Colindres and Associates:2528 Union St | B47: 91035 | C47: CA-C | D47: 46169 | E47: Pre-Production | F47: Pre-Production | G47: 19766.41 | H47: =I47-G47 -> 19766.4 | I47: 39532.81 | L47: =G47-J47 -> 19766.41
A48: Commercial Contractors, Inc.:Flabletics Tampa FL | B48: 90388 | C48: FL-C | D48: 46140 | E48: Pre-Production | F48: Pre-Production | G48: 25275 | H48: =I48-G48 -> 25275.26 | I48: 50550.26 | J48: =IFERROR(VLOOKUP(B48,'Apr 26'!B:G,6,FALSE),0) -> 25275 | K48: =IF(G48=0,J48-G48,0) -> 0 | L48: =G48-J48 -> 0
A49: Crisci Builders:Lot 147 Addition | B49: 87426 | C49: NV-R | D49: 46084 | E49: 46125 | F49: Cutting | G49: =94654+110507.46 -> 205161.46 | H49: =I49-G49 -> 0 | I49: 205161.46 | J49: =IFERROR(VLOOKUP(B49,'Apr 26'!B:G,6,FALSE),0) -> 94654 | K49: 0 | L49: =G49-J49 -> 110507.46
A50: Crystal Glass Inc.:New Logan Elementry | B50: 83108 | C50: MI-C | D50: 45764 | E50: Pre-Production | F50: Pre-Production | G50: 172204.5 | H50: 172204.5 | I50: 344409 | J50: =IFERROR(VLOOKUP(B50,'Apr 26'!B:G,6,FALSE),0) -> 172204.5 | K50: 0 | L50: =G50-J50 -> 0
A51: D & R Glass:Cedar and Sage | B51: 84134 | C51: CA-C | D51: 45945 | E51: 46091 | F51: Coating | G51: 64205 | H51: 61477 | I51: 125682 | J51: =IFERROR(VLOOKUP(B51,'Apr 26'!B:G,6,FALSE),0) -> 64205 | K51: 0 | L51: =G51-J51 -> 0
A52: Dan and Molly Dirscherl:Dirscherl Cabana | B52: 85777 | C52: NJ-R | D52: 46093 | E52: Pre-Production | F52: Pre-Production | G52: 17769 | H52: 168389 | I52: 186158 | J52: =IFERROR(VLOOKUP(B52,'Apr 26'!B:G,6,FALSE),0) -> 17769 | K52: 0 | L52: =G52-J52 -> 0
A53: David Ostrander:Ostrander Residence Remodel | B53: 88087 | C53: MN-R | D53: 46064 | E53: 46128 | F53: Powder Coat | G53: 123085 | H53: 123084 | I53: 246169 | J53: =IFERROR(VLOOKUP(B53,'Apr 26'!B:G,6,FALSE),0) -> 123085 | K53: 0 | L53: =G53-J53 -> 0
A54: Debbie Piliero:46 Upper Rd | B54: 87161 | C54: CA-R | D54: 45924 | E54: 45992 | F54: 46170 | G54: 0 | J54: =IFERROR(VLOOKUP(B54,'Apr 26'!B:G,6,FALSE),0) -> 17417 | K54: =IF(G54=0,J54-G54,0) -> 17417 | L54: Invoiced This Month
A55: Desert Window Systems:Lennar 2 | B55: 90600 | C55: NV-R | D55: 05/15/2026 | E55: Pre-Production | F55: Pre-Production | G55: 84439.3 | H55: =I55-G55 -> 0 | I55: 84439.3 | J55: =IFERROR(VLOOKUP(B55,'Apr 26'!B:G,6,FALSE),0) -> 0 | K55: 0 | L55: =G55-J55 -> 84439.3
A56: Devoe Custom Homes:Bodnar | B56: 89338 | C56: FL-R | D56: 46134 | E56: Pre-Production | F56: Pre-Production | G56: 14498 | H56: =I56-G56 -> 14498 | I56: 28996 | J56: =IFERROR(VLOOKUP(B56,'Apr 26'!B:G,6,FALSE),0) -> 14498 | K56: =IF(G56=0,J56-G56,0) -> 0 | L56: =G56-J56 -> 0
A57: Devoe Custom Homes:Vanderveen | B57: 89554 | C57: FL-R | D57: 46100 | E57: 46127 | F57: 46156 | G57: 0 | J57: =IFERROR(VLOOKUP(B57,'Apr 26'!B:G,6,FALSE),0) -> 17304 | K57: =J57-G57 -> 17304 | L57: Invoiced This Month
A58: Discount Glass & Mirror Inc.:Cardella | B58: 83204 | C58: CA-C | D58: 46108 | E58: Pre-Production | F58: Pre-Production | G58: 44368 | H58: 44368 | I58: 88736 | J58: =IFERROR(VLOOKUP(B58,'Apr 26'!B:G,6,FALSE),0) -> 44368 | K58: 0 | L58: =G58-J58 -> 0
A59: Discount Glass & Mirror Inc.:Encinitas | B59: 85495 | C59: CA-C | D59: 46083 | E59: 46106 | F59: 46156 | G59: 0 | J59: =IFERROR(VLOOKUP(B59,'Apr 26'!B:G,6,FALSE),0) -> 29175 | K59: =J59-G59 -> 29175 | L59: Invoiced This Month
A60: Donatello Bonasera Development, LLC:Casa Faten | B60: 88756 | C60: CA-R | D60: 46092 | E60: Pre-Production | F60: Pre-Production | G60: 160000 | H60: 158239 | I60: 318239 | J60: =IFERROR(VLOOKUP(B60,'Apr 26'!B:G,6,FALSE),0) -> 160000 | K60: 0 | L60: =G60-J60 -> 0
A61: Donatello Bonasera Development, LLC:The F Penthouse | B61: 89698 | C61: CA-R | D61: 46091 | E61: 46122 | F61: 46163 | G61: 0 | J61: =IFERROR(VLOOKUP(B61,'Apr 26'!B:G,6,FALSE),0) -> 8935.32 | K61: =J61-G61 -> 8935.32 | L61: Invoiced This Month
A62: Don's Mobile Glass:Grossi | B62: 88858 | C62: CA-R | D62: 46105 | E62: 46134 | F62: 46170 | G62: 0 | J62: =IFERROR(VLOOKUP(B62,'Apr 26'!B:G,6,FALSE),0) -> 16192 | K62: =IF(G62=0,J62-G62,0) -> 16192 | L62: Invoiced This Month
A63: Doors, Etc.:Doors Etc HSW | B63: 88511 | C63: CA-R | D63: 46072 | E63: Pre-Production | F63: Pre-Production | G63: 19222 | H63: 19222 | I63: 38444 | J63: =IFERROR(VLOOKUP(B63,'Apr 26'!B:G,6,FALSE),0) -> 19222 | K63: 0 | L63: =G63-J63 -> 0
A64: Dugally Oberfeld, Inc.:Cox | B64: 83729 | C64: CA-R | D64: 46028 | E64: Pre-Production | F64: Pre-Production | G64: 31223 | H64: 27501 | I64: 58724 | J64: =IFERROR(VLOOKUP(B64,'Apr 26'!B:G,6,FALSE),0) -> 31223 | K64: 0 | L64: =G64-J64 -> 0
A65: Dynamic Builders LHC:1821 Pinion Tree Dr Flex Counter | B65: 90688 | C65: AZ-R | D65: 46163 | E65: Pre-Production | F65: Pre-Production | G65: 11700 | H65: =I65-G65 -> 11755.11 | I65: 23455.11 | L65: =G65-J65 -> 11700
A66: Dynamic Glass:Antero Resources | B66: 85504 | C66: CO-C | D66: 46100 | E66: Pre-Production | F66: Pre-Production | G66: 151068 | H66: 151068 | I66: 302136 | J66: =IFERROR(VLOOKUP(B66,'Apr 26'!B:G,6,FALSE),0) -> 151068 | K66: 0 | L66: =G66-J66 -> 0
A67: E & Z Glass & Window:Cotton On Dallas Galleria | B67: 89285 | C67: TX-R | D67: 46098 | E67: Pre-Production | F67: Pre-Production | G67: 23405 | H67: 23404 | I67: 46809 | J67: =IFERROR(VLOOKUP(B67,'Apr 26'!B:G,6,FALSE),0) -> 23405 | K67: 0 | L67: =G67-J67 -> 0
A68: Echelon Builders LLC:Residential | B68: 89324 | C68: HI-R | D68: 46141 | E68: Pre-Production | F68: Pre-Production | G68: 15963 | H68: =I68-G68 -> 15962 | I68: 31925 | J68: =IFERROR(VLOOKUP(B68,'Apr 26'!B:G,6,FALSE),0) -> 15963 | K68: =IF(G68=0,J68-G68,0) -> 0 | L68: =G68-J68 -> 0
A69: Edge Design and Construction INC:Brooks Project Add On | B69: 89984 | C69: NV-R | D69: 46112 | E69: 46134 | F69: 46161 | G69: 0 | J69: =IFERROR(VLOOKUP(B69,'Apr 26'!B:G,6,FALSE),0) -> 1897 | K69: =J69-G69 -> 1897 | L69: Invoiced This Month
A70: Element Facades 13:299 MILWAUKEE | B70: 86960 | C70: CO-C | D70: 45986 | E70: Pre-Production | F70: Pre-Production | G70: 8962 | H70: 26885 | I70: 35847 | J70: =IFERROR(VLOOKUP(B70,'Apr 26'!B:G,6,FALSE),0) -> 8962 | K70: 0 | L70: =G70-J70 -> 0
A71: Elham Taherian:2180 Havensight Add On | B71: 89760 | C71: NV-R | D71: 46139 | E71: Pre-Production | F71: Pre-Production | G71: 5641 | H71: =I71-G71 -> 5640 | I71: 11281 | J71: =IFERROR(VLOOKUP(B71,'Apr 26'!B:G,6,FALSE),0) -> 5641 | K71: =IF(G71=0,J71-G71,0) -> 0 | L71: =G71-J71 -> 0
A72: Elite Glazing Inc.:RSF Clubhouse | B72: 85987 | C72: CA-C | D72: 46115 | E72: Pre-Production | F72: Pre-Production | G72: 68043 | H72: =I72-G72 -> 68042 | I72: 136085 | J72: =IFERROR(VLOOKUP(B72,'Apr 26'!B:G,6,FALSE),0) -> 68043 | K72: 0 | L72: =G72-J72 -> 0
A73: Emerald Glass:The Frank | B73: 84692 | C73: WA-C | D73: 46076 | E73: 46100 | F73: 46171 | G73: 0 | J73: =IFERROR(VLOOKUP(B73,'Apr 26'!B:G,6,FALSE),0) -> 5345 | K73: =IF(G73=0,J73-G73,0) -> 5345 | L73: Invoiced This Month
A74: Environmental Glass Inc:Ann Arbor Thurston | B74: 84161 | C74: MI-C | D74: 46013 | E74: Pre-Production | F74: Pre-Production | G74: 176687 | H74: 176686 | I74: 353373 | J74: =IFERROR(VLOOKUP(B74,'Apr 26'!B:G,6,FALSE),0) -> 176687 | K74: 0 | L74: =G74-J74 -> 0
A75: Environmental Glass Inc:Mitchell Elementary | B75: 81492-R1 | C75: MI-C | D75: 45868 | E75: Pre-Production | F75: Pre-Production | G75: 114974 | H75: 114973 | I75: 229947 | J75: =IFERROR(VLOOKUP(B75,'Apr 26'!B:G,6,FALSE),0) -> 114974 | K75: 0 | L75: =G75-J75 -> 0
A76: Flat Iron Development Co:Brandon Baca Voyage | B76: 89675 | C76: CO-R | D76: 46114 | E76: 46139 | F76: 46171 | G76: 0 | J76: =IFERROR(VLOOKUP(B76,'Apr 26'!B:G,6,FALSE),0) -> 6002 | K76: =IF(G76=0,J76-G76,0) -> 6002 | L76: Invoiced This Month
A77: Ford Metro Inc:Chapter / Ann Arbor | B77: 87492 | C77: MN-R | D77: 46063 | E77: Pre-Production | F77: Pre-Production | G77: 22079 | H77: 22079 | I77: 44158 | J77: =IFERROR(VLOOKUP(B77,'Apr 26'!B:G,6,FALSE),0) -> 22079 | K77: 0 | L77: =G77-J77 -> 0
A78: Franklin Herbas:Herbas Folding | B78: 89313 | C78: CA-R | D78: 46079 | E78: 46111 | F78: 46146 | G78: 0 | J78: =IFERROR(VLOOKUP(B78,'Apr 26'!B:G,6,FALSE),0) -> 8773 | K78: =J78-G78 -> 8773 | L78: Invoiced This Month
A79: Gallatin Glass Works Inc:5026 Iron Ridge Patio | B79: 88818 | C79: MT-R | D79: 46121 | E79: Pre-Production | F79: Pre-Production | G79: 15127 | H79: =I79-G79 -> 15126 | I79: 30253 | J79: =IFERROR(VLOOKUP(B79,'Apr 26'!B:G,6,FALSE),0) -> 15127 | K79: 0 | L79: =G79-J79 -> 0
A80: Giroux Glass:SoCalGas Loggia | B80: 88082 | C80: CA-C | D80: 46076 | E80: Pre-Production | F80: Pre-Production | G80: 35295 | H80: 35294 | I80: 70589 | J80: =IFERROR(VLOOKUP(B80,'Apr 26'!B:G,6,FALSE),0) -> 35295 | K80: 0 | L80: =G80-J80 -> 0
A81: Giroux Glass:Sparks Training Facility | B81: 89539 | C81: CA-C | D81: 46170 | E81: Pre-Production | F81: Pre-Production | G81: 32606 | H81: =I81-G81 -> 32606 | I81: 65212 | L81: =G81-J81 -> 32606
A82: Glass and Metals, Inc:2100 Crystal | B82: 88012 | C82: VA-C | D82: 46086 | E82: Pre-Production | F82: Pre-Production | G82: 25461 | H82: 25461 | I82: 50922 | J82: =IFERROR(VLOOKUP(B82,'Apr 26'!B:G,6,FALSE),0) -> 25461 | K82: 0 | L82: =G82-J82 -> 0
A83: Glass Concepts:WIC | B83: 90365 | C83: CO-C | D83: 05/11/2026 | E83: Pre-Production | F83: Pre-Production | G83: 12373 | H83: =I83-G83 -> 12372.53 | I83: 24745.53 | J83: =IFERROR(VLOOKUP(B83,'Apr 26'!B:G,6,FALSE),0) -> 0 | K83: 0 | L83: =G83-J83 -> 12373
A84: Glass House LLC:Red Arrow | B84: 88675 | C84: NV-R | D84: 46149 | E84: Pre-Production | F84: Pre-Production | G84: 51194.18 | H84: =I84-G84 -> 0 | I84: 51194.18 | J84: =IFERROR(VLOOKUP(B84,'Apr 26'!B:G,6,FALSE),0) -> 0 | K84: 0 | L84: =G84-J84 -> 51194.18
A85: Glass House Products:Lawther Remodel | B85: 90930 | C85: TX-R | D85: 46163 | E85: Pre-Production | F85: Pre-Production | G85: 28888.91 | H85: =I85-G85 -> 28888.91 | I85: 57777.82 | L85: =G85-J85 -> 28888.91
A86: Golden Glass Inc.:Pepperdine University | B86: 76624 | C86: CA-C | D86: 4/19/2024 | E86: 46038 | F86: 46146 | G86: 0 | J86: =IFERROR(VLOOKUP(B86,'Apr 26'!B:G,6,FALSE),0) -> 82176 | K86: =J86-G86 -> 82176 | L86: Invoiced This Month
A87: Goldfinch Brothers:Stoel Rives L48 | B87: 89287 | C87: WA-C | D87: 46113 | E87: Pre-Production | F87: Pre-Production | G87: 89586 | H87: =I87-G87 -> 89585 | I87: 179171 | J87: =IFERROR(VLOOKUP(B87,'Apr 26'!B:G,6,FALSE),0) -> 89586 | K87: 0 | L87: =G87-J87 -> 0
A88: GP Glass & Mirror LLC:George_Pivot Door and Trapezoids | B88: 90716 | C88: NV-R | D88: 05/15/2026 | E88: Pre-Production | F88: Pre-Production | G88: 11932 | H88: =I88-G88 -> 11931 | I88: 23863 | J88: =IFERROR(VLOOKUP(B88,'Apr 26'!B:G,6,FALSE),0) -> 0 | K88: 0 | L88: =G88-J88 -> 11932
A89: Green Glass:Overland | B89: 89055 | C89: CA-C | D89: 46120 | E89: Pre-Production | F89: Pre-Production | G89: 8582 | H89: =I89-G89 -> 8582 | I89: 17164 | J89: =IFERROR(VLOOKUP(B89,'Apr 26'!B:G,6,FALSE),0) -> 8582 | K89: 0 | L89: =G89-J89 -> 0
A90: Hall Aluminum Products:TT Union Building D | B90: 87359 | C90: IN-C | D90: 46125 | E90: Pre-Production | F90: Pre-Production | G90: 19467 | H90: =I90-G90 -> 19466 | I90: 38933 | J90: =IFERROR(VLOOKUP(B90,'Apr 26'!B:G,6,FALSE),0) -> 19467 | K90: 0 | L90: =G90-J90 -> 0
A91: Hardman Glazing Management LLC:800 Corte Madera | B91: 89412 | C91: CA-R | D91: 46126 | E91: Pre-Production | F91: Pre-Production | G91: 20897 | H91: =I91-G91 -> 0 | I91: 20897 | J91: =IFERROR(VLOOKUP(B91,'Apr 26'!B:G,6,FALSE),0) -> 20897 | K91: 0 | L91: =G91-J91 -> 0
A92: Hardman Glazing Management LLC:Utility building - 800 Corte Madera | B92: 89867 | C92: CA-R | D92: 46126 | E92: Pre-Production | F92: Pre-Production | G92: 14271.62 | H92: =I92-G92 -> 0 | I92: 14271.62 | J92: =IFERROR(VLOOKUP(B92,'Apr 26'!B:G,6,FALSE),0) -> 14271.62 | K92: 0 | L92: =G92-J92 -> 0
A93: Hasco Constrution:Sperryn Jones | B93: 82632 | C93: SN-R | D93: 45758 | E93: Pre-Production | F93: Pre-Production | G93: 109478 | H93: 109478 | I93: 218956 | J93: =IFERROR(VLOOKUP(B93,'Apr 26'!B:G,6,FALSE),0) -> 109478 | K93: 0 | L93: =G93-J93 -> 0
A94: HBS Inc.:Burns | B94: 87391 | C94: FL-R | D94: 46168 | E94: Pre-Production | F94: Pre-Production | G94: 60000 | H94: =I94-G94 -> 42519 | I94: 102519 | L94: =G94-J94 -> 60000
A95: HBS Inc.:Holloway | B95: 90134 | C95: FL-R | D95: 05/15/2026 | E95: Pre-Production | F95: Pre-Production | G95: 19000 | H95: =I95-G95 -> 0 | I95: 19000 | J95: =IFERROR(VLOOKUP(B95,'Apr 26'!B:G,6,FALSE),0) -> 0 | K95: 0 | L95: =G95-J95 -> 19000
A96: Heart of America Aston LLC:592 Aston | B96: 84210 | C96: IL-C | D96: 45876 | E96: Pre-Production | F96: Pre-Production | G96: 31567 | H96: 46437 | I96: 78004 | J96: =IFERROR(VLOOKUP(B96,'Apr 26'!B:G,6,FALSE),0) -> 31567 | K96: 0 | L96: =G96-J96 -> 0
A97: Helou Construction:Rosebowl South Endzone Club | B97: 88433 | C97: CA-C | D97: 46036 | E97: Pre-Production | F97: Pre-Production | G97: =80538+4404.5 -> 84942.5 | H97: 80538 | I97: 161076 | J97: =IFERROR(VLOOKUP(B97,'Apr 26'!B:G,6,FALSE),0) -> 80538 | K97: 0 | L97: =G97-J97 -> 4404.5
A98: Ikirkpatrick Construction:Stewart Residence 3 | B98: 87792 | C98: HI-R | D98: 45992 | E98: 46045 | F98: 46164 | G98: 0 | J98: =IFERROR(VLOOKUP(B98,'Apr 26'!B:G,6,FALSE),0) -> 49733 | K98: =J98-G98 -> 49733 | L98: Invoiced This Month
A99: Infinity Group:Wilson Residence 77 | B99: 85175 | C99: CT-R | D99: 46084 | E99: Pre-Production | F99: Pre-Production | G99: 22778 | H99: 22779 | I99: 45557 | J99: =IFERROR(VLOOKUP(B99,'Apr 26'!B:G,6,FALSE),0) -> 22778 | K99: 0 | L99: =G99-J99 -> 0
A100: Integrated Door & Window Systems:102 McKnight Dr- Phase 2 | B100: 88155 | C100: CA-R | D100: 46135 | E100: Pre-Production | F100: Pre-Production | G100: 26625 | H100: =I100-G100 -> 26625 | I100: 53250 | J100: =IFERROR(VLOOKUP(B100,'Apr 26'!B:G,6,FALSE),0) -> 26625 | K100: =IF(G100=0,J100-G100,0) -> 0 | L100: =G100-J100 -> 0
...

Sheet Jun 26
A1: Customer | B1: Q Number | C1: Region | D1: Payment Date | E1: Production Start Day | F1: Stage | G1: DEPOSIT | H1: FINAL | I1: TOTAL | J1: BOM Dep | K1: Dep to Rev | L1: New Dep this Month
A2: 1st Choice Glass:MUSC - Clemson | B2: 88562 | C2: NC-C | D2: 46091 | E2: Pre-Production | F2: Pre-Production | G2: 51110.14 | H2: 0 | I2: 51110.14 | J2: =IFERROR(VLOOKUP(B2,'May 26'!B:G,6,FALSE),0) -> 51110.14 | K2: 0 | L2: =G2-J2 -> 0 | N2: =VLOOKUP(B2,[3]invoicing!$C:$AI,33,FALSE)
A3: A&A Window Products Inc:45 Littles Road | B3: 88556 | C3: MA-R | D3: 46086 | E3: 46150 | F3: 46202 | G3: 0 | J3: =IFERROR(VLOOKUP(B3,'May 26'!B:G,6,FALSE),0) -> 11662 | K3: =J3-G3 -> 11662 | L3: Invoiced This Month
A4: AAC Glass Inc.:PUSD Folding Door | B4: 88164 | C4: CA-C | D4: 46195 | E4: Pre-Production | F4: Pre-Production | G4: 22283 | H4: =I4-G4 -> 22282 | I4: 44565 | J4: =IFERROR(VLOOKUP(B4,'May 26'!B:G,6,FALSE),0) -> 0 | K4: 0 | L4: =G4-J4 -> 22283
A5: Advanced Windows:1990 K Street | B5: 87616 | C5: MD-C | D5: 46069 | E5: Pre-Production | F5: Pre-Production | G5: 35586 | H5: 9375 | I5: 44961 | J5: =IFERROR(VLOOKUP(B5,'May 26'!B:G,6,FALSE),0) -> 35586 | K5: 0 | L5: =G5-J5 -> 0
A6: AFR Construction:Boe Dekker | B6: 87676 | C6: NV-R | D6: 46125 | E6: 46153 | F6: 46185 | G6: 0 | J6: =IFERROR(VLOOKUP(B6,'May 26'!B:G,6,FALSE),0) -> 2400.25 | K6: =J6-G6 -> 2400.25 | L6: Invoiced This Month | N6: =VLOOKUP(B6,[3]invoicing!$C:$AI,33,FALSE)
A7: Akis Doganis:Doganis Residence | B7: 87185 | C7: NV-R | D7: 45995 | E7: Pre-Production | F7: Pre-Production | G7: 31515 | H7: 31514 | I7: 63029 | J7: =IFERROR(VLOOKUP(B7,'May 26'!B:G,6,FALSE),0) -> 31515 | K7: 0 | L7: =G7-J7 -> 0 | N7: =VLOOKUP(B7,[3]invoicing!$C:$AI,33,FALSE)
A8: Alli Construction:Chaparral Janiga Residence | B8: 89424 | C8: CA-R | D8: 46090 | E8: 46141 | F8: 46185 | G8: 0 | J8: =IFERROR(VLOOKUP(B8,'May 26'!B:G,6,FALSE),0) -> 16906.51 | K8: =J8-G8 -> 16906.51 | L8: Invoiced This Month | N8: =VLOOKUP(B8,[3]invoicing!$C:$AI,33,FALSE)
A9: American Glass & Mirror Company:1000 Nevillewood Drive | B9: 87836 | C9: VA-C | D9: 46098 | E9: 46191 | F9: Powder Coat | G9: 18709 | H9: 18709 | I9: 37418 | J9: =IFERROR(VLOOKUP(B9,'May 26'!B:G,6,FALSE),0) -> 18709 | K9: 0 | L9: =G9-J9 -> 0 | N9: =VLOOKUP(B9,[3]invoicing!$C:$AI,33,FALSE)
A10: Architectural Glass & Design:9825 Stonecrest | B10: 88159 | C10: CA-C | D10: 46148 | E10: Pre-Production | F10: Pre-Production | G10: 8819 | H10: =I10-G10 -> 8818 | I10: 17637 | J10: =IFERROR(VLOOKUP(B10,'May 26'!B:G,6,FALSE),0) -> 8819 | K10: 0 | L10: =G10-J10 -> 0 | N10: =VLOOKUP(B10,[3]invoicing!$C:$AI,33,FALSE)
A11: Aune Brothers Construction:Lake Havasu Multi Slide | B11: 90057 | C11: AZ-R | D11: 46128 | E11: 46160 | F11: 46202 | G11: 0 | J11: =IFERROR(VLOOKUP(B11,'May 26'!B:G,6,FALSE),0) -> 9211 | K11: =J11-G11 -> 9211 | L11: Invoiced This Month | N11: =VLOOKUP(B11,[3]invoicing!$C:$AI,33,FALSE)
A12: Automatic Door & Glass:633 St. Croix Add On | B12: 89869 | C12: NV-R | D12: 46181 | E12: Pre-Production | F12: Pre-Production | G12: 6204 | H12: =I12-G12 -> 6204.62 | I12: 12408.62 | J12: =IFERROR(VLOOKUP(B12,'May 26'!B:G,6,FALSE),0) -> 0 | K12: 0 | L12: =G12-J12 -> 6204 | N12: =VLOOKUP(B12,[3]invoicing!$C:$AI,33,FALSE)
A13: Best Contracting LLC:UCSB San Benito Housing | B13: 87022 | C13: CA-C | D13: 45981 | E13: Pre-Production | F13: Pre-Production | G13: 60823 | H13: 60822 | I13: 121645 | J13: =IFERROR(VLOOKUP(B13,'May 26'!B:G,6,FALSE),0) -> 60823 | K13: 0 | L13: =G13-J13 -> 0 | N13: =VLOOKUP(B13,[3]invoicing!$C:$AI,33,FALSE)
A14: Best Window Co.:Simms Residence | B14: 89319 | C14: OK-R | D14: 46182 | E14: Pre-Production | F14: Pre-Production | G14: 35841 | H14: =I14-G14 -> 28303 | I14: 64144 | J14: =IFERROR(VLOOKUP(B14,'May 26'!B:G,6,FALSE),0) -> 0 | K14: 0 | L14: =G14-J14 -> 35841 | N14: =VLOOKUP(B14,[3]invoicing!$C:$AI,33,FALSE)
A15: Bill Jaeger:Jaeger Sliders | B15: 90185 | C15: NV-R | D15: 46140 | E15: 46188 | F15: Pull Material | G15: 7191 | H15: =I15-G15 -> 7301.27 | I15: 14492.27 | J15: =IFERROR(VLOOKUP(B15,'May 26'!B:G,6,FALSE),0) -> 7191 | K15: =IF(G15=0,J15-G15,0) -> 0 | L15: =G15-J15 -> 0 | N15: =VLOOKUP(B15,[3]invoicing!$C:$AI,33,FALSE)
A16: BMG Door & Glass:Halise Diamond | B16: 89197 | C16: AZ-R | D16: 46198 | E16: Pre-Production | F16: Pre-Production | G16: 19024 | H16: =I16-G16 -> 19022.13 | I16: 38046.13 | J16: =IFERROR(VLOOKUP(B16,'May 26'!B:G,6,FALSE),0) -> 0 | K16: 0 | L16: =G16-J16 -> 19024
A17: Boulder Ridge Sash & Door:129 Tahoe Tavern | B17: 89731 | C17: CA-R | D17: 46147 | E17: Pre-Production | F17: Pre-Production | G17: 13338.01 | H17: =I17-G17 -> 13336.99 | I17: 26675 | J17: =IFERROR(VLOOKUP(B17,'May 26'!B:G,6,FALSE),0) -> 13338.01 | K17: 0 | L17: =G17-J17 -> 0 | N17: =VLOOKUP(B17,[3]invoicing!$C:$AI,33,FALSE)
A18: Boyett Construction Inc:Ian | B18: 90450 | C18: CA-R | D18: 46146 | E18: 46168 | F18: 46199 | G18: 0 | J18: =IFERROR(VLOOKUP(B18,'May 26'!B:G,6,FALSE),0) -> 7699 | K18: =J18-G18 -> 7699 | L18: Invoiced This Month | N18: =VLOOKUP(B18,[3]invoicing!$C:$AI,33,FALSE)
A19: Brad Lager:Palmer | B19: 87591 | C19: MO-R | D19: 46058 | E19: 46125 | F19: 46177 | G19: 0 | J19: =IFERROR(VLOOKUP(B19,'Apr 26'!B:G,6,FALSE),0) -> 25317 | K19: =J19-G19 -> 25317 | L19: Invoiced This Month
A20: Brett Hill Construction, Inc:4895 Kalanianaole | B20: 88674 | C20: HI-R | D20: 46055 | E20: 46132 | F20: Assembly | G20: 238760 | H20: 238759 | I20: 477519 | J20: =IFERROR(VLOOKUP(B20,'May 26'!B:G,6,FALSE),0) -> 238760 | K20: 0 | L20: =G20-J20 -> 0 | N20: =VLOOKUP(B20,[3]invoicing!$C:$AI,33,FALSE)
A21: Builders Direct Supply:4545 North-Studio | B21: 85791 | C21: CA-R | D21: 45959 | E21: Pre-Production | F21: Pre-Production | G21: 50992 | H21: =I21-G21 -> 50992 | I21: 101984 | J21: =IFERROR(VLOOKUP(B21,'May 26'!B:G,6,FALSE),0) -> 8977.7 | K21: 0 | L21: =G21-J21 -> 42014.3
A22: Builders Direct Supply:Christian Rooney | B22: 89792 | C22: CA-R | D22: 46140 | E22: Pre-Production | F22: Pre-Production | G22: 34278 | H22: =I22-G22 -> 34278 | I22: 68556 | J22: =IFERROR(VLOOKUP(B22,'May 26'!B:G,6,FALSE),0) -> 34278 | K22: =IF(G22=0,J22-G22,0) -> 0 | L22: =G22-J22 -> 0 | N22: =VLOOKUP(B22,[3]invoicing!$C:$AI,33,FALSE)
A23: Builders Direct Supply:Keel Residence | B23: 90329 | C23: CA-R | D23: 05/14/2026 | E23: 46191 | F23: Powder Coat | G23: 8966.25 | H23: =I23-G23 -> 8966.3 | I23: 17932.55 | J23: =IFERROR(VLOOKUP(B23,'May 26'!B:G,6,FALSE),0) -> 8966.25 | K23: 0 | L23: =G23-J23 -> 0 | N23: =VLOOKUP(B23,[3]invoicing!$C:$AI,33,FALSE)
A24: Builders Direct Supply:North 4545 | B24: 83690 | C24: CA-R | D24: 45959 | E24: Pre-Production | F24: Pre-Production | G24: 200341.5 | H24: =I24-G24 -> 205952.5 | I24: 406294 | J24: =IFERROR(VLOOKUP(B24,'May 26'!B:G,6,FALSE),0) -> 41681.4 | K24: 0 | L24: =G24-J24 -> 158660.1
A25: Builders Direct Supply:Snell and Wilmer | B25: 86318 | C25: CA-C | D25: 46030 | E25: 46140 | F25: Assembly | G25: 31398 | H25: 26483.5 | I25: 62796 | J25: =IFERROR(VLOOKUP(B25,'May 26'!B:G,6,FALSE),0) -> 31398 | K25: 0 | L25: =G25-J25 -> 0
A26: Builders FirstSource/Dixieline Lumber & Home Center:107 Via Toluca | B26: 88510 | C26: CA-R | D26: 46181 | E26: Pre-Production | F26: Pre-Production | G26: 15005 | H26: =I26-G26 -> 15004 | I26: 30009 | J26: =IFERROR(VLOOKUP(B26,'May 26'!B:G,6,FALSE),0) -> 0 | K26: 0 | L26: =G26-J26 -> 15005 | N26: =VLOOKUP(B26,[3]invoicing!$C:$AI,33,FALSE)
A27: Builders FirstSource/Dixieline Lumber & Home Center:1416 Stone Canyon Rd | B27: 89873 | C27: CA-R | D27: 46168 | E27: Pre-Production | F27: Pre-Production | G27: 165000 | H27: =I27-G27 -> 165000 | I27: 330000 | J27: =IFERROR(VLOOKUP(B27,'May 26'!B:G,6,FALSE),0) -> 165000 | L27: =G27-J27 -> 0 | N27: =VLOOKUP(B27,[3]invoicing!$C:$AI,33,FALSE)
A28: Builders FirstSource/Dixieline Lumber & Home Center:Kyle Newport | B28: 90207 | C28: CA-R | D28: 46168 | E28: Pre-Production | F28: Pre-Production | G28: 7754 | H28: =I28-G28 -> 2185 | I28: 9939 | J28: =IFERROR(VLOOKUP(B28,'May 26'!B:G,6,FALSE),0) -> 4969 | L28: =G28-J28 -> 2785 | N28: =VLOOKUP(B28,[3]invoicing!$C:$AI,33,FALSE)
A29: Buzick Construction, Inc.:Big Blue Bar | B29: 90093 | C29: KY-C | D29: 46127 | E29: 46155 | F29: 46195 | G29: 0 | J29: =IFERROR(VLOOKUP(B29,'May 26'!B:G,6,FALSE),0) -> 20789 | K29: =J29-G29 -> 20789 | L29: Invoiced This Month
A30: C Thru Glass:Mt. Charleston Lodge | B30: 89607 | C30: NV-C | D30: 46126 | E30: Pre-Production | F30: Pre-Production | G30: 19335 | H30: =I30-G30 -> 19335 | I30: 38670 | J30: =IFERROR(VLOOKUP(B30,'May 26'!B:G,6,FALSE),0) -> 19335 | K30: 0 | L30: =G30-J30 -> 0 | N30: =VLOOKUP(B30,[3]invoicing!$C:$AI,33,FALSE)
A31: CAC Aluminum & Glass Inc.:355 Deerfield Sliding Doors | B31: 89649 | C31: IL-C | D31: 46101 | E31: 46126 | F31: 46175 | G31: 0 | J31: =IFERROR(VLOOKUP(B31,'Apr 26'!B:G,6,FALSE),0) -> 17176 | K31: =J31-G31 -> 17176 | L31: Invoiced This Month | N31: =VLOOKUP(B31,[3]invoicing!$C:$AI,33,FALSE)
A32: Callender's House of Glass:750 Picacho Ln | B32: 90005 | C32: CA-R | D32: 46128 | E32: 46168 | F32: Assembly | G32: 9786 | H32: =I32-G32 -> 9785.44 | I32: 19571.44 | J32: =IFERROR(VLOOKUP(B32,'May 26'!B:G,6,FALSE),0) -> 9786 | K32: =IF(G32=0,J32-G32,0) -> 0 | L32: =G32-J32 -> 0 | N32: =VLOOKUP(B32,[3]invoicing!$C:$AI,33,FALSE)
A33: Capitol Glass Company:Sunnydale Block 7 | B33: 88227 | C33: CA-C | D33: 46020 | E33: 46133 | F33: Powder Coat | G33: 32005 | H33: 32005 | I33: 64010 | J33: =IFERROR(VLOOKUP(B33,'May 26'!B:G,6,FALSE),0) -> 32005 | K33: 0 | L33: =G33-J33 -> 0 | N33: =VLOOKUP(B33,[3]invoicing!$C:$AI,33,FALSE)
A34: Capitol Glass Company:The Eliza | B34: 84966 | C34: CA-C | D34: 46099 | E34: Pre-Production | F34: Pre-Production | G34: 39804 | H34: 39803 | I34: 79607 | J34: =IFERROR(VLOOKUP(B34,'May 26'!B:G,6,FALSE),0) -> 39804 | K34: 0 | L34: =G34-J34 -> 0 | N34: =VLOOKUP(B34,[3]invoicing!$C:$AI,33,FALSE)
A35: Carmen Creek Homes:Hoskins LTS.30 & French Door | B35: 91001 | C35: UT-R | D35: 46175 | E35: 46198 | F35: Pull Material | G35: 14017.3 | H35: =I35-G35 -> 14017.29 | I35: 28034.59 | J35: =IFERROR(VLOOKUP(B35,'May 26'!B:G,6,FALSE),0) -> 0 | K35: 0 | L35: =G35-J35 -> 14017.3 | N35: =VLOOKUP(B35,[3]invoicing!$C:$AI,33,FALSE)
A36: Catalyst Acoustics Group | B36: Unknown | D36: 44712 | E36: Pre-Production | F36: Pre-Production | G36: 4108 | H36: 0 | I36: 4108 | J36: =IFERROR(VLOOKUP(B36,'Apr 26'!B:G,6,FALSE),0) -> 4108 | K36: 0 | L36: =G36-J36 -> 0
A37: Charlotte Rosiak:1805 Villa De Conde Way Entry | B37: 90923 | C37: NV-R | D37: 46160 | E37: Pre-Production | F37: Pre-Production | G37: 7275.85 | H37: =I37-G37 -> 7275.84 | I37: 14551.69 | J37: =IFERROR(VLOOKUP(B37,'May 26'!B:G,6,FALSE),0) -> 7275.85 | L37: =G37-J37 -> 0 | N37: =VLOOKUP(B37,[3]invoicing!$C:$AI,33,FALSE)
A38: Chase Kloehn:Kloehn Remodel | B38: 88513 | C38: NV-R | D38: 46085 | E38: 46147 | F38: 46191 | G38: 0 | H38: 0 | I38: 0 | J38: =IFERROR(VLOOKUP(B38,'May 26'!B:G,6,FALSE),0) -> 11224 | K38: =J38-G38 -> 11224 | L38: Invoiced This Month | N38: =VLOOKUP(B38,[3]invoicing!$C:$AI,33,FALSE)
A39: Chuck Hamilton Construction Inc.:Shueck Pool House | B39: 89296 | C39: AR-R | D39: 46100 | E39: 46162 | F39: Pull Material | G39: 109253 | H39: 109253 | I39: 224986 | J39: =IFERROR(VLOOKUP(B39,'May 26'!B:G,6,FALSE),0) -> 109253 | K39: 0 | L39: =G39-J39 -> 0
A40: CK2 Contracting:1221 W. Washington | B40: 88868 | C40: IL-R | D40: 46059 | E40: 46181 | F40: Powder Coat | G40: 17321 | H40: 17321 | I40: 35424 | J40: =IFERROR(VLOOKUP(B40,'May 26'!B:G,6,FALSE),0) -> 17321 | K40: 0 | L40: =G40-J40 -> 0
A41: Classic Glass:Hotel Mohi | B41: 88845 | C41: CA-C | D41: 46115 | E41: Pre-Production | F41: Pre-Production | G41: 51819 | H41: =I41-G41 -> 51818 | I41: 103637 | J41: =IFERROR(VLOOKUP(B41,'May 26'!B:G,6,FALSE),0) -> 51819 | K41: 0 | L41: =G41-J41 -> 0 | N41: =VLOOKUP(B41,[3]invoicing!$C:$AI,33,FALSE)
A42: Clear Solutions Group:Xs Remodel | B42: 89829 | C42: NV-C | D42: 46134 | E42: 46183 | F42: Coating | G42: 90746 | H42: =I42-G42 -> 90746 | I42: 181492 | J42: =IFERROR(VLOOKUP(B42,'May 26'!B:G,6,FALSE),0) -> 90746 | K42: =IF(G42=0,J42-G42,0) -> 0 | L42: =G42-J42 -> 0 | N42: =VLOOKUP(B42,[3]invoicing!$C:$AI,33,FALSE)
A43: Clerestory LLC:Malireddy Pivot Door | B43: 89254 | C43: GA-R | D43: 46142 | E43: Pre-Production | F43: Pre-Production | G43: 8136 | H43: =I43-G43 -> 8136 | I43: 16272 | J43: =IFERROR(VLOOKUP(B43,'May 26'!B:G,6,FALSE),0) -> 8136 | K43: =IF(G43=0,J43-G43,0) -> 0 | L43: =G43-J43 -> 0 | N43: =VLOOKUP(B43,[3]invoicing!$C:$AI,33,FALSE)
A44: Colindres and Associates:2528 Union St | B44: 91035 | C44: CA-C | D44: 46169 | E44: Pre-Production | F44: Pre-Production | G44: 19766.41 | H44: =I44-G44 -> 19766.4 | I44: 39532.81 | J44: =IFERROR(VLOOKUP(B44,'May 26'!B:G,6,FALSE),0) -> 19766.41 | L44: =G44-J44 -> 0 | N44: =VLOOKUP(B44,[3]invoicing!$C:$AI,33,FALSE)
A45: Commercial Contractors, Inc.:Flabletics Tampa FL | B45: 90388 | C45: FL-C | D45: 46140 | E45: Pre-Production | F45: Pre-Production | G45: 25275 | H45: =I45-G45 -> 25275.26 | I45: 50550.26 | J45: =IFERROR(VLOOKUP(B45,'May 26'!B:G,6,FALSE),0) -> 25275 | K45: =IF(G45=0,J45-G45,0) -> 0 | L45: =G45-J45 -> 0 | N45: =VLOOKUP(B45,[3]invoicing!$C:$AI,33,FALSE)
A46: Crisci Builders:Lot 147 Add On | B46: 90595 | C46: NV-R | D46: 46195 | E46: 46175 | F46: Test-Wall | G46: 5569.3 | H46: =I46-G46 -> 0 | I46: 5569.3 | J46: =IFERROR(VLOOKUP(B46,'May 26'!B:G,6,FALSE),0) -> 0 | K46: 0 | L46: =G46-J46 -> 5569.3
A47: Crisci Builders:Lot 147 Addition | B47: 87426 | C47: NV-R | D47: 46084 | E47: 46125 | F47: 46176 | G47: 0 | J47: =IFERROR(VLOOKUP(B47,'May 26'!B:G,6,FALSE),0) -> 205161.46 | K47: =J47-G47 -> 205161.46 | L47: Invoiced This Month | N47: =VLOOKUP(B47,[3]invoicing!$C:$AI,33,FALSE)
A48: Crystal Glass Inc.:New Logan Elementry | B48: 83108 | C48: MI-C | D48: 45764 | E48: Pre-Production | F48: Pre-Production | G48: 172204.5 | H48: 172204.5 | I48: 344409 | J48: =IFERROR(VLOOKUP(B48,'May 26'!B:G,6,FALSE),0) -> 172204.5 | K48: 0 | L48: =G48-J48 -> 0 | N48: =VLOOKUP(B48,[3]invoicing!$C:$AI,33,FALSE)
A49: D & R Glass:Cedar and Sage | B49: 84134 | C49: CA-C | D49: 45945 | E49: 46091 | F49: Assembly | G49: 64205 | H49: 61477 | I49: 125682 | J49: =IFERROR(VLOOKUP(B49,'May 26'!B:G,6,FALSE),0) -> 64205 | K49: 0 | L49: =G49-J49 -> 0
A50: Dan and Molly Dirscherl:Dirscherl Cabana | B50: 85777 | C50: NJ-R | D50: 46093 | E50: Pre-Production | F50: Pre-Production | G50: 17769 | H50: 168389 | I50: 186158 | J50: =IFERROR(VLOOKUP(B50,'May 26'!B:G,6,FALSE),0) -> 17769 | K50: 0 | L50: =G50-J50 -> 0 | N50: =VLOOKUP(B50,[3]invoicing!$C:$AI,33,FALSE)
A51: David Ostrander:Ostrander Residence Remodel | B51: 88087 | C51: MN-R | D51: 46064 | E51: 46128 | F51: 46183 | G51: 0 | J51: =IFERROR(VLOOKUP(B51,'May 26'!B:G,6,FALSE),0) -> 123085 | K51: =J51-G51 -> 123085 | L51: Invoiced This Month
A52: Desert Window Systems:Lennar 2 | B52: 90600 | C52: NV-R | D52: 05/15/2026 | E52: 46189 | F52: Cutting | G52: 84439.3 | H52: =I52-G52 -> 0 | I52: 84439.3 | J52: =IFERROR(VLOOKUP(B52,'May 26'!B:G,6,FALSE),0) -> 84439.3 | K52: 0 | L52: =G52-J52 -> 0 | N52: =VLOOKUP(B52,[3]invoicing!$C:$AI,33,FALSE)
A53: Devoe Custom Homes:Bodnar | B53: 89338 | C53: FL-R | D53: 46134 | E53: Pre-Production | F53: Pre-Production | G53: 14498 | H53: =I53-G53 -> 15866 | I53: 30364 | J53: =IFERROR(VLOOKUP(B53,'May 26'!B:G,6,FALSE),0) -> 14498 | K53: =IF(G53=0,J53-G53,0) -> 0 | L53: =G53-J53 -> 0 | N53: =VLOOKUP(B53,[3]invoicing!$C:$AI,33,FALSE)
A54: Discount Glass & Mirror Inc.:Cardella | B54: 83204 | C54: CA-C | D54: 46108 | E54: 46148 | F54: Powder Coat | G54: 44368 | H54: 44368 | I54: 88736 | J54: =IFERROR(VLOOKUP(B54,'May 26'!B:G,6,FALSE),0) -> 44368 | K54: 0 | L54: =G54-J54 -> 0 | N54: =VLOOKUP(B54,[3]invoicing!$C:$AI,33,FALSE)
A55: Donatello Bonasera Development, LLC:Casa Faten | B55: 88756 | C55: CA-R | D55: 46092 | E55: Pre-Production | F55: Pre-Production | G55: 160000 | H55: 158239 | I55: 318239 | J55: =IFERROR(VLOOKUP(B55,'May 26'!B:G,6,FALSE),0) -> 160000 | K55: 0 | L55: =G55-J55 -> 0 | N55: =VLOOKUP(B55,[3]invoicing!$C:$AI,33,FALSE)
A56: Don's Mobile Glass:Grossi Add On | B56: 90858 | C56: CA-R | D56: 46185 | E56: Pre-Production | F56: Pre-Production | G56: 6717 | H56: =I56-G56 -> 6717 | I56: 13434 | J56: =IFERROR(VLOOKUP(B56,'May 26'!B:G,6,FALSE),0) -> 0 | K56: 0 | L56: =G56-J56 -> 6717 | N56: =VLOOKUP(B56,[3]invoicing!$C:$AI,33,FALSE)
A57: Don's Mobile Glass:Michael Raimondo | B57: 90442 | C57: CA-R | D57: 46181 | E57: Pre-Production | F57: Pre-Production | G57: 40000 | H57: =I57-G57 -> 32316 | I57: 72316 | J57: =IFERROR(VLOOKUP(B57,'May 26'!B:G,6,FALSE),0) -> 0 | K57: 0 | L57: =G57-J57 -> 40000 | N57: =VLOOKUP(B57,[3]invoicing!$C:$AI,33,FALSE)
A58: Doors, Etc.:Doors Etc HSW | B58: 88511 | C58: CA-R | D58: 46072 | E58: 46162 | F58: Assembly | G58: 19222 | H58: 19222 | I58: 38444 | J58: =IFERROR(VLOOKUP(B58,'May 26'!B:G,6,FALSE),0) -> 19222 | K58: 0 | L58: =G58-J58 -> 0 | N58: =VLOOKUP(B58,[3]invoicing!$C:$AI,33,FALSE)
A59: Dugally Oberfeld, Inc.:Cox | B59: 83729 | C59: CA-R | D59: 46028 | E59: 46155 | F59: Pull Material | G59: 31223 | H59: 27501 | I59: 58724 | J59: =IFERROR(VLOOKUP(B59,'May 26'!B:G,6,FALSE),0) -> 31223 | K59: 0 | L59: =G59-J59 -> 0 | N59: =VLOOKUP(B59,[3]invoicing!$C:$AI,33,FALSE)
A60: Dynamic Builders LHC:1821 Pinion Tree Dr Flex Counter | B60: 90688 | C60: AZ-R | D60: 46163 | E60: 46184 | F60: Assembly | G60: 11700 | H60: =I60-G60 -> 11755.11 | I60: 23455.11 | J60: =IFERROR(VLOOKUP(B60,'May 26'!B:G,6,FALSE),0) -> 11700 | L60: =G60-J60 -> 0 | N60: =VLOOKUP(B60,[3]invoicing!$C:$AI,33,FALSE)
A61: Dynamic Glass:Antero Resources | B61: 85504 | C61: CO-C | D61: 46100 | E61: Pre-Production | F61: Pre-Production | G61: 151068 | H61: 151068 | I61: 302136 | J61: =IFERROR(VLOOKUP(B61,'May 26'!B:G,6,FALSE),0) -> 151068 | K61: 0 | L61: =G61-J61 -> 0 | N61: =VLOOKUP(B61,[3]invoicing!$C:$AI,33,FALSE)
A62: E & Z Glass & Window:Cotton On Dallas Galleria | B62: 89285 | C62: TX-R | D62: 46098 | E62: 46155 | F62: 46190 | G62: 0 | J62: =IFERROR(VLOOKUP(B62,'May 26'!B:G,6,FALSE),0) -> 23405 | K62: =J62-G62 -> 23405 | L62: Invoiced This Month
A63: E & Z Glass & Window:Tollway Office Building | B63: 90853 | C63: TX-R | D63: 46177 | E63: 46202 | F63: Pull Material | G63: 48347 | H63: =I63-G63 -> 48346 | I63: 96693 | J63: =IFERROR(VLOOKUP(B63,'May 26'!B:G,6,FALSE),0) -> 0 | K63: 0 | L63: =G63-J63 -> 48347 | N63: =VLOOKUP(B63,[3]invoicing!$C:$AI,33,FALSE)
A64: Echelon Builders LLC:Residential | B64: 89324 | C64: HI-R | D64: 46141 | E64: 46197 | F64: Powder Coat | G64: 15963 | H64: =I64-G64 -> 15962 | I64: 31925 | J64: =IFERROR(VLOOKUP(B64,'May 26'!B:G,6,FALSE),0) -> 15963 | K64: =IF(G64=0,J64-G64,0) -> 0 | L64: =G64-J64 -> 0 | N64: =VLOOKUP(B64,[3]invoicing!$C:$AI,33,FALSE)
A65: Element Facades 13:299 MILWAUKEE | B65: 86960 | C65: CO-C | D65: 45986 | E65: Pre-Production | F65: Pre-Production | G65: 8962 | H65: 26885 | I65: 39102 | J65: =IFERROR(VLOOKUP(B65,'May 26'!B:G,6,FALSE),0) -> 8962 | K65: 0 | L65: =G65-J65 -> 0
A66: Elham Taherian:2180 Havensight Add On | B66: 89760 | C66: NV-R | D66: 46139 | E66: 46174 | F66: 46202 | G66: 0 | J66: =IFERROR(VLOOKUP(B66,'May 26'!B:G,6,FALSE),0) -> 5641 | K66: =J66-G66 -> 5641 | L66: Invoiced This Month
A67: Elite Glazing Group:LA Basketball | B67: 90706 | C67: CA-C | D67: 46181 | E67: Pre-Production | F67: Pre-Production | G67: 30536 | H67: =I67-G67 -> 30536 | I67: 61072 | J67: =IFERROR(VLOOKUP(B67,'May 26'!B:G,6,FALSE),0) -> 0 | K67: 0 | L67: =G67-J67 -> 30536 | N67: =VLOOKUP(B67,[3]invoicing!$C:$AI,33,FALSE)
A68: Elite Glazing Inc.:RSF Clubhouse | B68: 85987 | C68: CA-C | D68: 46115 | E68: 46177 | F68: Powder Coat | G68: 68043 | H68: =I68-G68 -> 68042 | I68: 136085 | J68: =IFERROR(VLOOKUP(B68,'May 26'!B:G,6,FALSE),0) -> 68043 | K68: 0 | L68: =G68-J68 -> 0 | N68: =VLOOKUP(B68,[3]invoicing!$C:$AI,33,FALSE)
A69: Environmental Glass Inc:Ann Arbor Thurston | B69: 84161 | C69: MI-C | D69: 46013 | E69: Pre-Production | F69: Pre-Production | G69: 176687 | H69: 176686 | I69: 353373 | J69: =IFERROR(VLOOKUP(B69,'May 26'!B:G,6,FALSE),0) -> 176687 | K69: 0 | L69: =G69-J69 -> 0 | N69: =VLOOKUP(B69,[3]invoicing!$C:$AI,33,FALSE)
A70: Environmental Glass Inc:Mitchell Elementary | B70: 81492-R1 | C70: MI-C | D70: 45868 | E70: Pre-Production | F70: Pre-Production | G70: 114974 | H70: 114973 | I70: 229947 | J70: =IFERROR(VLOOKUP(B70,'May 26'!B:G,6,FALSE),0) -> 114974 | K70: 0 | L70: =G70-J70 -> 0
A71: Ford Metro Inc:Chapter / Ann Arbor | B71: 87492 | C71: MN-R | D71: 46063 | E71: Pre-Production | F71: Pre-Production | G71: 22079 | H71: 22079 | I71: 44158 | J71: =IFERROR(VLOOKUP(B71,'May 26'!B:G,6,FALSE),0) -> 22079 | K71: 0 | L71: =G71-J71 -> 0 | N71: =VLOOKUP(B71,[3]invoicing!$C:$AI,33,FALSE)
A72: Gallatin Glass Works Inc:5026 Iron Ridge Patio | B72: 88818 | C72: MT-R | D72: 46121 | E72: 46181 | F72: Assembly | G72: 15127 | H72: =I72-G72 -> 15126 | I72: 30253 | J72: =IFERROR(VLOOKUP(B72,'May 26'!B:G,6,FALSE),0) -> 15127 | K72: 0 | L72: =G72-J72 -> 0 | N72: =VLOOKUP(B72,[3]invoicing!$C:$AI,33,FALSE)
A73: Giroux Glass:SoCalGas Loggia | B73: 88082 | C73: CA-C | D73: 46076 | E73: Pre-Production | F73: Pre-Production | G73: 35295 | H73: 35294 | I73: 70589 | J73: =IFERROR(VLOOKUP(B73,'May 26'!B:G,6,FALSE),0) -> 35295 | K73: 0 | L73: =G73-J73 -> 0 | N73: =VLOOKUP(B73,[3]invoicing!$C:$AI,33,FALSE)
A74: Giroux Glass:Sparks Training Facility | B74: 89539 | C74: CA-C | D74: 46170 | E74: Pre-Production | F74: Pre-Production | G74: 32606 | H74: =I74-G74 -> 32606 | I74: 65212 | J74: =IFERROR(VLOOKUP(B74,'May 26'!B:G,6,FALSE),0) -> 32606 | L74: =G74-J74 -> 0 | N74: =VLOOKUP(B74,[3]invoicing!$C:$AI,33,FALSE)
A75: Glass and Metals, Inc:2100 Crystal | B75: 88012 | C75: VA-C | D75: 46086 | E75: Pre-Production | F75: Pre-Production | G75: 25461 | H75: 25461 | I75: 51937 | J75: =IFERROR(VLOOKUP(B75,'May 26'!B:G,6,FALSE),0) -> 25461 | K75: 0 | L75: =G75-J75 -> 0
A76: Glass Concepts:WIC | B76: 90365 | C76: CO-C | D76: 05/11/2026 | E76: Pre-Production | F76: Pre-Production | G76: 12373 | H76: =I76-G76 -> 12372.53 | I76: 24745.53 | J76: =IFERROR(VLOOKUP(B76,'May 26'!B:G,6,FALSE),0) -> 12373 | K76: 0 | L76: =G76-J76 -> 0 | N76: =VLOOKUP(B76,[3]invoicing!$C:$AI,33,FALSE)
A77: Glass House LLC:Red Arrow | B77: 88675 | C77: NV-R | D77: 46149 | E77: Pre-Production | F77: Pre-Production | G77: 51194.18 | H77: =I77-G77 -> 0 | I77: 51194.18 | J77: =IFERROR(VLOOKUP(B77,'May 26'!B:G,6,FALSE),0) -> 51194.18 | K77: 0 | L77: =G77-J77 -> 0 | N77: =VLOOKUP(B77,[3]invoicing!$C:$AI,33,FALSE)
A78: Glass House Products:Lawther Remodel | B78: 90930 | C78: TX-R | D78: 46163 | E78: Pre-Production | F78: Pre-Production | G78: 28888.91 | H78: =I78-G78 -> 28888.91 | I78: 57777.82 | J78: =IFERROR(VLOOKUP(B78,'May 26'!B:G,6,FALSE),0) -> 28888.91 | L78: =G78-J78 -> 0 | N78: =VLOOKUP(B78,[3]invoicing!$C:$AI,33,FALSE)
A79: Goldfinch Brothers:Stoel Rives L48 | B79: 89287 | C79: WA-C | D79: 46113 | E79: Pre-Production | F79: Pre-Production | G79: 89586 | H79: =I79-G79 -> 89585 | I79: 179171 | J79: =IFERROR(VLOOKUP(B79,'May 26'!B:G,6,FALSE),0) -> 89586 | K79: 0 | L79: =G79-J79 -> 0 | N79: =VLOOKUP(B79,[3]invoicing!$C:$AI,33,FALSE)
A80: GP Glass & Mirror LLC:George_Pivot Door and Trapezoids | B80: 90716 | C80: NV-R | D80: 05/15/2026 | E80: 46188 | F80: Pull Material | G80: 11932 | H80: =I80-G80 -> 11931 | I80: 23863 | J80: =IFERROR(VLOOKUP(B80,'May 26'!B:G,6,FALSE),0) -> 11932 | K80: 0 | L80: =G80-J80 -> 0 | N80: =VLOOKUP(B80,[3]invoicing!$C:$AI,33,FALSE)
A81: Grand View Glass:LMAC Operable Glass Wall | B81: 89541 | C81: CO-C | D81: 46185 | E81: Pre-Production | F81: Pre-Production | G81: 9278.28 | H81: =I81-G81 -> 7903.72 | I81: 17182 | J81: =IFERROR(VLOOKUP(B81,'May 26'!B:G,6,FALSE),0) -> 0 | K81: 0 | L81: =G81-J81 -> 9278.28 | N81: =VLOOKUP(B81,[3]invoicing!$C:$AI,33,FALSE)
A82: Green Glass:Overland | B82: 89055 | C82: CA-C | D82: 46120 | E82: 46163 | F82: Assembly | G82: 8582 | H82: =I82-G82 -> 8582 | I82: 17164 | J82: =IFERROR(VLOOKUP(B82,'May 26'!B:G,6,FALSE),0) -> 8582 | K82: 0 | L82: =G82-J82 -> 0 | N82: =VLOOKUP(B82,[3]invoicing!$C:$AI,33,FALSE)
A83: Hall Aluminum Products:TT Union Building D | B83: 87359 | C83: IN-C | D83: 46125 | E83: Pre-Production | F83: Pre-Production | G83: 19467 | H83: =I83-G83 -> 19466 | I83: 38933 | J83: =IFERROR(VLOOKUP(B83,'May 26'!B:G,6,FALSE),0) -> 19467 | K83: 0 | L83: =G83-J83 -> 0 | N83: =VLOOKUP(B83,[3]invoicing!$C:$AI,33,FALSE)
A84: Hardman Glazing Management LLC:800 Corte Madera | B84: 89412 | C84: CA-R | D84: 46126 | E84: 46191 | F84: Powder Coat | G84: 20897 | H84: =I84-G84 -> 9706 | I84: 30603 | J84: =IFERROR(VLOOKUP(B84,'May 26'!B:G,6,FALSE),0) -> 20897 | K84: 0 | L84: =G84-J84 -> 0
A85: Hardman Glazing Management LLC:Utility building - 800 Corte Madera | B85: 89867 | C85: CA-R | D85: 46126 | E85: 46192 | F85: Powder Coat | G85: 14271.62 | H85: =I85-G85 -> 7648.63 | I85: 21920.25 | J85: =IFERROR(VLOOKUP(B85,'May 26'!B:G,6,FALSE),0) -> 14271.62 | K85: 0 | L85: =G85-J85 -> 0
A86: Hasco Constrution:Sperryn Jones | B86: 82632 | C86: SN-R | D86: 45758 | E86: 46146 | F86: Assembly | G86: 109478 | H86: 109478 | I86: 218956 | J86: =IFERROR(VLOOKUP(B86,'May 26'!B:G,6,FALSE),0) -> 109478 | K86: 0 | L86: =G86-J86 -> 0
A87: HBS Inc.:Burns | B87: 87391 | C87: FL-R | D87: 46168 | E87: Pre-Production | F87: Pre-Production | G87: 60000 | H87: =I87-G87 -> 42519 | I87: 102519 | J87: =IFERROR(VLOOKUP(B87,'May 26'!B:G,6,FALSE),0) -> 60000 | L87: =G87-J87 -> 0 | N87: =VLOOKUP(B87,[3]invoicing!$C:$AI,33,FALSE)
A88: HBS Inc.:Holloway | B88: 90134 | C88: FL-R | D88: 05/15/2026 | E88: 46169 | F88: Assembly | G88: 19000 | H88: =I88-G88 -> 0 | I88: 19000 | J88: =IFERROR(VLOOKUP(B88,'May 26'!B:G,6,FALSE),0) -> 19000 | K88: 0 | L88: =G88-J88 -> 0 | N88: =VLOOKUP(B88,[3]invoicing!$C:$AI,33,FALSE)
A89: Heart of America Aston LLC:592 Aston | B89: 84210 | C89: IL-C | D89: 45876 | E89: 46164 | F89: Pull Material | G89: 31567 | H89: 46437 | I89: 78004 | J89: =IFERROR(VLOOKUP(B89,'May 26'!B:G,6,FALSE),0) -> 31567 | K89: 0 | L89: =G89-J89 -> 0
A90: Helou Construction:Rosebowl South Endzone Club | B90: 88433 | C90: CA-C | D90: 46036 | E90: 46155 | F90: Powder Coat | G90: 84942.5 | H90: 80538 | I90: 169885 | J90: =IFERROR(VLOOKUP(B90,'May 26'!B:G,6,FALSE),0) -> 84942.5 | K90: 0 | L90: =G90-J90 -> 0
A91: Infinity Group:Wilson Residence 77 | B91: 85175 | C91: CT-R | D91: 46084 | E91: 45992 | F91: 46191 | G91: 0 | J91: =IFERROR(VLOOKUP(B91,'May 26'!B:G,6,FALSE),0) -> 22778 | K91: =J91-G91 -> 22778 | L91: Invoiced This Month | N91: =VLOOKUP(B91,[3]invoicing!$C:$AI,33,FALSE)
A92: Integrated Door & Window Systems:102 McKnight Dr- Phase 2 | B92: 88155 | C92: CA-R | D92: 46135 | E92: 46163 | F92: Powder Coat | G92: 26625 | H92: =I92-G92 -> 26625 | I92: 53250 | J92: =IFERROR(VLOOKUP(B92,'May 26'!B:G,6,FALSE),0) -> 26625 | K92: =IF(G92=0,J92-G92,0) -> 0 | L92: =G92-J92 -> 0 | N92: =VLOOKUP(B92,[3]invoicing!$C:$AI,33,FALSE)
A93: Integrated Glass Concepts, Inc:Diablo Valley College | B93: 87488 | C93: CA-C | D93: 46007 | E93: 46195 | F93: Powder Coat | G93: 17613 | H93: 17612 | I93: 35225 | J93: =IFERROR(VLOOKUP(B93,'May 26'!B:G,6,FALSE),0) -> 17613 | K93: 0 | L93: =G93-J93 -> 0 | N93: =VLOOKUP(B93,[3]invoicing!$C:$AI,33,FALSE)
A94: Island Tiles:Hilton Ballroom Doors | B94: 89316 | C94: BB-C | D94: 46100 | E94: 46174 | F94: Cutting | G94: 56063 | H94: 56063 | I94: 112126 | J94: =IFERROR(VLOOKUP(B94,'May 26'!B:G,6,FALSE),0) -> 56063 | K94: 0 | L94: =G94-J94 -> 0 | N94: =VLOOKUP(B94,[3]invoicing!$C:$AI,33,FALSE)
A95: J Shuman Door Installation:Arnaud Slider | B95: 90536 | C95: CA-R | D95: 46160 | E95: Pre-Production | F95: Pre-Production | G95: 9055.57 | H95: =I95-G95 -> 9055.57 | I95: 18111.14 | J95: =IFERROR(VLOOKUP(B95,'May 26'!B:G,6,FALSE),0) -> 9055.57 | L95: =G95-J95 -> 0 | N95: =VLOOKUP(B95,[3]invoicing!$C:$AI,33,FALSE)
A96: J Shuman Door Installation:Cord Project | B96: 90305 | C96: CA-R | D96: 46188 | E96: Pre-Production | F96: Pre-Production | G96: 6823.18 | H96: =I96-G96 -> 6823.18 | I96: 13646.36 | J96: =IFERROR(VLOOKUP(B96,'May 26'!B:G,6,FALSE),0) -> 0 | K96: 0 | L96: =G96-J96 -> 6823.18
A97: J Shuman Door Installation:Hospitality Building | B97: 86579 | C97: CA-R | D97: 46188 | E97: Pre-Production | F97: Pre-Production | G97: 69123 | H97: =I97-G97 -> 66195 | I97: 135318 | J97: =IFERROR(VLOOKUP(B97,'May 26'!B:G,6,FALSE),0) -> 0 | K97: 0 | L97: =G97-J97 -> 69123
A98: J Shuman Door Installation:Jared Lou | B98: 86904 | C98: CA-R | D98: 46105 | E98: 46163 | F98: Assembly | G98: 6516 | H98: 6515 | I98: 13031 | J98: =IFERROR(VLOOKUP(B98,'May 26'!B:G,6,FALSE),0) -> 6516 | K98: 0 | L98: =G98-J98 -> 0 | N98: =VLOOKUP(B98,[3]invoicing!$C:$AI,33,FALSE)
A99: J Shuman Door Installation:Marzalek Folding Door | B99: 87965 | C99: CA-R | D99: 05/13/2026 | E99: 46181 | F99: Cutting | G99: 8755 | H99: =I99-G99 -> 8755 | I99: 17510 | J99: =IFERROR(VLOOKUP(B99,'May 26'!B:G,6,FALSE),0) -> 8755 | K99: 0 | L99: =G99-J99 -> 0 | N99: =VLOOKUP(B99,[3]invoicing!$C:$AI,33,FALSE)
A100: J Shuman Door Installation:Nandini Saraiya | B100: 89168 | C100: CA-R | D100: 46136 | E100: Pre-Production | F100: Pre-Production | G100: 30691 | H100: =I100-G100 -> 30691 | I100: 61382 | J100: =IFERROR(VLOOKUP(B100,'May 26'!B:G,6,FALSE),0) -> 30691 | K100: =IF(G100=0,J100-G100,0) -> 0 | L100: =G100-J100 -> 0 | N100: =VLOOKUP(B100,[3]invoicing!$C:$AI,33,FALSE)
...

Sheet Jul 26
A1: Customer | B1: Q Number | C1: Region | D1: Payment Date | E1: Production Start Day | F1: Stage | G1: DEPOSIT | H1: FINAL | I1: TOTAL | J1: BOM Dep | K1: Dep to Rev | L1: New Dep this Month
A2: 1st Choice Glass:MUSC - Clemson | B2: 88562 | C2: NC-C | D2: 46091 | E2: Pre-Production | F2: Pre-Production | G2: 51110.14 | H2: 0 | I2: 51110.14 | J2: =IFERROR(VLOOKUP(B2,'Jun 26'!B:G,6,FALSE),0) -> 51110.14 | K2: 0 | L2: =G2-J2 -> 0 | N2: =L2-K2 -> 0
A3: AAC Glass Inc.:PUSD Folding Door | B3: 88164 | C3: CA-C | D3: 46195 | E3: Pre-Production | F3: Pre-Production | G3: 22283 | H3: =I3-G3 -> 22282 | I3: 44565 | J3: =IFERROR(VLOOKUP(B3,'Jun 26'!B:G,6,FALSE),0) -> 22283 | K3: 0 | L3: =G3-J3 -> 0 | N3: =L3-K3 -> 0
A4: Advanced Windows:1990 K Street | B4: 87616 | C4: MD-C | D4: 46069 | E4: Pre-Production | F4: Pre-Production | G4: 35586 | H4: 9375 | I4: 44961 | J4: =IFERROR(VLOOKUP(B4,'Jun 26'!B:G,6,FALSE),0) -> 35586 | K4: 0 | L4: =G4-J4 -> 0 | N4: =L4-K4 -> 0
A5: Akis Doganis:Doganis Residence | B5: 87185 | C5: NV-R | D5: 45995 | E5: Pre-Production | F5: Pre-Production | G5: 31515 | H5: 31514 | I5: 63029 | J5: =IFERROR(VLOOKUP(B5,'Jun 26'!B:G,6,FALSE),0) -> 31515 | K5: 0 | L5: =G5-J5 -> 0 | N5: =L5-K5 -> 0
A6: American Glass & Mirror Company:1000 Nevillewood Drive | B6: 87836 | C6: VA-C | D6: 46098 | E6: 46191 | F6: 46226 | G6: 0 | H6: 0 | I6: 0 | J6: =IFERROR(VLOOKUP(B6,'Jun 26'!B:G,6,FALSE),0) -> 18709 | K6: =IF(G6=0,J6-G6,0) -> 18709 | L6: Invoiced This Month | N6: -18709
A7: Architectural Glass & Design:9825 Stonecrest | B7: 88159 | C7: CA-C | D7: 46148 | E7: Pre-Production | F7: Pre-Production | G7: 8819 | H7: =I7-G7 -> 8818 | I7: 17637 | J7: =IFERROR(VLOOKUP(B7,'Jun 26'!B:G,6,FALSE),0) -> 8819 | K7: 0 | L7: =G7-J7 -> 0 | N7: =L7-K7 -> 0
A8: Automatic Door & Glass:633 St. Croix Add On | B8: 89869 | C8: NV-R | D8: 46181 | E8: Pre-Production | F8: Pre-Production | G8: 6204 | H8: =I8-G8 -> 7888.22 | I8: 14092.22 | J8: =IFERROR(VLOOKUP(B8,'Jun 26'!B:G,6,FALSE),0) -> 6204 | K8: 0 | L8: =G8-J8 -> 0 | N8: =L8-K8 -> 0
A9: Best Contracting LLC:UCSB San Benito Housing | B9: 87022 | C9: CA-C | D9: 45981 | E9: Pre-Production | F9: Pre-Production | G9: 60823 | H9: 60822 | I9: 121645 | J9: =IFERROR(VLOOKUP(B9,'Jun 26'!B:G,6,FALSE),0) -> 60823 | K9: 0 | L9: =G9-J9 -> 0 | N9: =L9-K9 -> 0
A10: Best Window Co.:Simms Residence | B10: 89319 | C10: OK-R | D10: 46182 | E10: Pre-Production | F10: Pre-Production | G10: =35841+10000+31298.86 -> 77139.86 | H10: =I10-G10 -> 0 | I10: 77139.86 | J10: =IFERROR(VLOOKUP(B10,'Jun 26'!B:G,6,FALSE),0) -> 35841 | K10: 0 | L10: =G10-J10 -> 41298.86 | N10: =L10-K10 -> 41298.86
A11: Bill Jaeger:Jaeger Sliders | B11: 90185 | C11: NV-R | D11: 46140 | E11: 46188 | F11: 46223 | G11: 0 | H11: 0 | I11: 0 | J11: =IFERROR(VLOOKUP(B11,'Jun 26'!B:G,6,FALSE),0) -> 7191 | K11: =IF(G11=0,J11-G11,0) -> 7191 | L11: Invoiced This Month | N11: -7191
A12: BMG Door & Glass:Halise Diamond | B12: 89197 | C12: AZ-R | D12: 46198 | E12: Pre-Production | F12: Pre-Production | G12: 19024 | H12: =I12-G12 -> 19022.13 | I12: 38046.13 | J12: =IFERROR(VLOOKUP(B12,'Jun 26'!B:G,6,FALSE),0) -> 19024 | K12: 0 | L12: =G12-J12 -> 0 | N12: =L12-K12 -> 0
A13: Boulder Ridge Sash & Door:129 Tahoe Tavern | B13: 89731 | C13: CA-R | D13: 46147 | E13: Pre-Production | F13: Pre-Production | G13: 13338.01 | H13: =I13-G13 -> 13336.99 | I13: 26675 | J13: =IFERROR(VLOOKUP(B13,'Jun 26'!B:G,6,FALSE),0) -> 13338.01 | K13: 0 | L13: =G13-J13 -> 0 | N13: =L13-K13 -> 0
A14: Brett Hill Construction, Inc:4895 Kalanianaole | B14: 88674 | C14: HI-R | D14: 46055 | E14: 46132 | F14: 46227 | G14: 488171 | H14: 0 | I14: 0 | J14: =IFERROR(VLOOKUP(B14,'Jun 26'!B:G,6,FALSE),0) -> 238760 | K14: =IF(G14=0,J14-G14,0) -> 0 | L14: =G14-J14 -> 249411 | N14: -238760
A15: Builders Direct Supply:4545 North-Studio | B15: 85791 | C15: CA-R | D15: 45959 | E15: Pre-Production | F15: Pre-Production | G15: 50992 | H15: =I15-G15 -> 50992 | I15: 101984 | J15: =IFERROR(VLOOKUP(B15,'Jun 26'!B:G,6,FALSE),0) -> 50992 | K15: 0 | L15: =G15-J15 -> 0 | N15: =L15-K15 -> 0
A16: Builders Direct Supply:Christian Rooney | B16: 89792 | C16: CA-R | D16: 46140 | E16: Pre-Production | F16: Pre-Production | G16: 34278 | H16: =I16-G16 -> 34278 | I16: 68556 | J16: =IFERROR(VLOOKUP(B16,'Jun 26'!B:G,6,FALSE),0) -> 34278 | K16: =IF(G16=0,J16-G16,0) -> 0 | L16: =G16-J16 -> 0 | N16: =L16-K16 -> 0
A17: Builders Direct Supply:Keel Residence | B17: 90329 | C17: CA-R | D17: 05/14/2026 | E17: 46191 | F17: Powder Coat | G17: 8966.25 | H17: =I17-G17 -> 8966.3 | I17: 17932.55 | J17: =IFERROR(VLOOKUP(B17,'Jun 26'!B:G,6,FALSE),0) -> 8966.25 | K17: 0 | L17: =G17-J17 -> 0 | N17: =L17-K17 -> 0
A18: Builders Direct Supply:North 4545 | B18: 83690 | C18: CA-R | D18: 45959 | E18: Pre-Production | F18: Pre-Production | G18: 200341.5 | H18: =I18-G18 -> 205952.5 | I18: 406294 | J18: =IFERROR(VLOOKUP(B18,'Jun 26'!B:G,6,FALSE),0) -> 200341.5 | K18: 0 | L18: =G18-J18 -> 0 | N18: =L18-K18 -> 0
A19: Builders Direct Supply:Snell and Wilmer | B19: 86318 | C19: CA-C | D19: 46030 | E19: 46140 | F19: Assembly | G19: 0 | H19: 0 | I19: 0 | J19: =IFERROR(VLOOKUP(B19,'Jun 26'!B:G,6,FALSE),0) -> 31398 | K19: =IF(G19=0,J19-G19,0) -> 31398 | L19: Invoiced This Month | N19: =L19-K19 -> #VALUE!
A20: Builders FirstSource/Dixieline Lumber & Home Center:107 Via Toluca | B20: 88510 | C20: CA-R | D20: 46181 | E20: Pre-Production | F20: Pre-Production | G20: 15005 | H20: =I20-G20 -> 15004 | I20: 30009 | J20: =IFERROR(VLOOKUP(B20,'Jun 26'!B:G,6,FALSE),0) -> 15005 | K20: 0 | L20: =G20-J20 -> 0 | N20: =L20-K20 -> 0
A21: Builders FirstSource/Dixieline Lumber & Home Center:1416 Stone Canyon Rd | B21: 89873 | C21: CA-R | D21: 46168 | E21: Pre-Production | F21: Pre-Production | G21: 165000 | H21: =I21-G21 -> 165000 | I21: 330000 | J21: =IFERROR(VLOOKUP(B21,'Jun 26'!B:G,6,FALSE),0) -> 165000 | L21: =G21-J21 -> 0 | N21: =L21-K21 -> 0
A22: Builders FirstSource/Dixieline Lumber & Home Center:Kyle Newport | B22: 90207 | C22: CA-R | D22: 46168 | E22: Pre-Production | F22: Pre-Production | G22: 7754 | H22: =I22-G22 -> 2185 | I22: 9939 | J22: =IFERROR(VLOOKUP(B22,'Jun 26'!B:G,6,FALSE),0) -> 7754 | L22: =G22-J22 -> 0 | N22: =L22-K22 -> 0
A23: C Thru Glass:Mt. Charleston Lodge | B23: 89607 | C23: NV-C | D23: 46126 | E23: Pre-Production | F23: Pre-Production | G23: 19335 | H23: =I23-G23 -> 19335 | I23: 38670 | J23: =IFERROR(VLOOKUP(B23,'Jun 26'!B:G,6,FALSE),0) -> 19335 | K23: 0 | L23: =G23-J23 -> 0 | N23: =L23-K23 -> 0
A24: Callender's House of Glass:750 Picacho Ln | B24: 90005 | C24: CA-R | D24: 46128 | E24: 46168 | F24: 46217 | G24: 0 | H24: 0 | I24: 0 | J24: =IFERROR(VLOOKUP(B24,'Jun 26'!B:G,6,FALSE),0) -> 9786 | K24: =IF(G24=0,J24-G24,0) -> 9786 | L24: Invoiced This Month | N24: -9786
A25: Capitol Glass Company:Sunnydale Block 7 | B25: 88227 | C25: CA-C | D25: 46020 | E25: 46133 | F25: Powder Coat | G25: 0 | H25: 0 | I25: 0 | J25: =IFERROR(VLOOKUP(B25,'Jun 26'!B:G,6,FALSE),0) -> 32005 | K25: =IF(G25=0,J25-G25,0) -> 32005 | L25: Invoiced This Month | N25: =L25-K25 -> #VALUE!
A26: Capitol Glass Company:The Eliza | B26: 84966 | C26: CA-C | D26: 46099 | E26: Pre-Production | F26: Pre-Production | G26: 39804 | H26: 39803 | I26: 79607 | J26: =IFERROR(VLOOKUP(B26,'Jun 26'!B:G,6,FALSE),0) -> 39804 | K26: 0 | L26: =G26-J26 -> 0 | N26: =L26-K26 -> 0
A27: Carmen Creek Homes:Hoskins LTS.30 & French Door | B27: 91001 | C27: UT-R | D27: 46175 | E27: 46198 | F27: Pull Material | G27: 14017.3 | H27: =I27-G27 -> 14017.29 | I27: 28034.59 | J27: =IFERROR(VLOOKUP(B27,'Jun 26'!B:G,6,FALSE),0) -> 14017.3 | K27: 0 | L27: =G27-J27 -> 0 | N27: =L27-K27 -> 0
A28: Catalyst Acoustics Group | B28: Unknown | D28: 44712 | E28: Pre-Production | F28: Pre-Production | G28: 4108 | H28: 0 | I28: 4108 | J28: =IFERROR(VLOOKUP(B28,'Jun 26'!B:G,6,FALSE),0) -> 4108 | K28: 0 | L28: =G28-J28 -> 0 | N28: =L28-K28 -> 0
A29: Charlotte Rosiak:1805 Villa De Conde Way Entry | B29: 90923 | C29: NV-R | D29: 46160 | E29: Pre-Production | F29: Pre-Production | G29: 7275.85 | H29: =I29-G29 -> 7275.84 | I29: 14551.69 | J29: =IFERROR(VLOOKUP(B29,'Jun 26'!B:G,6,FALSE),0) -> 7275.85 | L29: =G29-J29 -> 0 | N29: =L29-K29 -> 0
A30: Chuck Hamilton Construction Inc.:Shueck Pool House | B30: 89296 | C30: AR-R | D30: 46100 | E30: 46162 | F30: Pull Material | G30: 109253 | H30: 109253 | I30: 224986 | J30: =IFERROR(VLOOKUP(B30,'Jun 26'!B:G,6,FALSE),0) -> 109253 | K30: 0 | L30: =G30-J30 -> 0 | N30: =L30-K30 -> 0
A31: CK2 Contracting:1221 W. Washington | B31: 88868 | C31: IL-R | D31: 46059 | E31: 46181 | F31: Powder Coat | G31: 17321 | H31: 17321 | I31: 35424 | J31: =IFERROR(VLOOKUP(B31,'Jun 26'!B:G,6,FALSE),0) -> 17321 | K31: 0 | L31: =G31-J31 -> 0 | N31: =L31-K31 -> 0
A32: Classic Glass:Hotel Mohi | B32: 88845 | C32: CA-C | D32: 46115 | E32: Pre-Production | F32: Pre-Production | G32: 51819 | H32: =I32-G32 -> 51818 | I32: 103637 | J32: =IFERROR(VLOOKUP(B32,'Jun 26'!B:G,6,FALSE),0) -> 51819 | K32: 0 | L32: =G32-J32 -> 0 | N32: =L32-K32 -> 0
A33: Clear Solutions Group:Xs Remodel | B33: 89829 | C33: NV-C | D33: 46134 | E33: 46183 | F33: Coating | G33: 90746 | H33: =I33-G33 -> 90746 | I33: 181492 | J33: =IFERROR(VLOOKUP(B33,'Jun 26'!B:G,6,FALSE),0) -> 90746 | K33: =IF(G33=0,J33-G33,0) -> 0 | L33: =G33-J33 -> 0 | N33: =L33-K33 -> 0
A34: Clerestory LLC:Malireddy Pivot Door | B34: 89254 | C34: GA-R | D34: 46142 | E34: Pre-Production | F34: Pre-Production | G34: 8136 | H34: =I34-G34 -> 8136 | I34: 16272 | J34: =IFERROR(VLOOKUP(B34,'Jun 26'!B:G,6,FALSE),0) -> 8136 | K34: =IF(G34=0,J34-G34,0) -> 0 | L34: =G34-J34 -> 0 | N34: =L34-K34 -> 0
A35: Colindres and Associates:2528 Union St | B35: 91035 | C35: CA-C | D35: 46169 | E35: Pre-Production | F35: Pre-Production | G35: =19766.41+14755.42 -> 34521.83 | H35: =I35-G35 -> 19768.24 | I35: 54290.07 | J35: =IFERROR(VLOOKUP(B35,'Jun 26'!B:G,6,FALSE),0) -> 19766.41 | L35: =G35-J35 -> 14755.42 | N35: =L35-K35 -> 14755.42
A36: Commercial Contractors, Inc.:Flabletics Tampa FL | B36: 90388 | C36: FL-C | D36: 46140 | E36: Pre-Production | F36: Pre-Production | G36: 25275 | H36: =I36-G36 -> 25275.26 | I36: 50550.26 | J36: =IFERROR(VLOOKUP(B36,'Jun 26'!B:G,6,FALSE),0) -> 25275 | K36: =IF(G36=0,J36-G36,0) -> 0 | L36: =G36-J36 -> 0 | N36: =L36-K36 -> 0
A37: Crisci Builders:Lot 147 Add On | B37: 90595 | C37: NV-R | D37: 46195 | E37: 46175 | F37: Test-Wall | G37: 5569.3 | H37: =I37-G37 -> 0 | I37: 5569.3 | J37: =IFERROR(VLOOKUP(B37,'Jun 26'!B:G,6,FALSE),0) -> 5569.3 | K37: 0 | L37: =G37-J37 -> 0 | N37: =L37-K37 -> 0
A38: Crystal Glass Inc.:New Logan Elementry | B38: 83108 | C38: MI-C | D38: 45764 | E38: Pre-Production | F38: Pre-Production | G38: 172204.5 | H38: 172204.5 | I38: 344409 | J38: =IFERROR(VLOOKUP(B38,'Jun 26'!B:G,6,FALSE),0) -> 172204.5 | K38: 0 | L38: =G38-J38 -> 0 | N38: =L38-K38 -> 0
A39: D & R Glass:Cedar and Sage | B39: 84134 | C39: CA-C | D39: 45945 | E39: 46091 | F39: 46227 | G39: 0 | H39: 0 | I39: 0 | J39: =IFERROR(VLOOKUP(B39,'Jun 26'!B:G,6,FALSE),0) -> 64205 | K39: =IF(G39=0,J39-G39,0) -> 64205 | L39: Invoiced This Month | N39: -64205
A40: Dan and Molly Dirscherl:Dirscherl Cabana | B40: 85777 | C40: NJ-R | D40: 46093 | E40: Pre-Production | F40: Pre-Production | G40: 17769 | H40: 168389 | I40: 168779 | J40: =IFERROR(VLOOKUP(B40,'Jun 26'!B:G,6,FALSE),0) -> 17769 | K40: 0 | L40: =G40-J40 -> 0 | N40: =L40-K40 -> 0
A41: Desert Window Systems:Lennar 2 | B41: 90600 | C41: NV-R | D41: 05/15/2026 | E41: 46189 | F41: Cutting | G41: 84439.3 | H41: =I41-G41 -> 0 | I41: 84439.3 | J41: =IFERROR(VLOOKUP(B41,'Jun 26'!B:G,6,FALSE),0) -> 84439.3 | K41: 0 | L41: =G41-J41 -> 0 | N41: =L41-K41 -> 0
A42: Devoe Custom Homes:Bodnar | B42: 89338 | C42: FL-R | D42: 46134 | E42: Pre-Production | F42: Pre-Production | G42: 0 | H42: 0 | I42: 0 | J42: =IFERROR(VLOOKUP(B42,'Jun 26'!B:G,6,FALSE),0) -> 14498 | K42: =IF(G42=0,J42-G42,0) -> 14498 | L42: Invoiced This Month | N42: =L42-K42 -> #VALUE!
A43: Discount Glass & Mirror Inc.:Cardella | B43: 83204 | C43: CA-C | D43: 46108 | E43: 46148 | F43: 46217 | G43: 0 | H43: 0 | I43: 0 | J43: =IFERROR(VLOOKUP(B43,'Jun 26'!B:G,6,FALSE),0) -> 44368 | K43: =IF(G43=0,J43-G43,0) -> 44368 | L43: Invoiced This Month | N43: -44368
A44: Donatello Bonasera Development, LLC:Casa Faten | B44: 88756 | C44: CA-R | D44: 46092 | E44: Pre-Production | F44: Pre-Production | G44: 160000 | H44: 158239 | I44: 318239 | J44: =IFERROR(VLOOKUP(B44,'Jun 26'!B:G,6,FALSE),0) -> 160000 | K44: 0 | L44: =G44-J44 -> 0 | N44: =L44-K44 -> 0
A45: Don's Mobile Glass:Grossi Add On | B45: 90858 | C45: CA-R | D45: 46185 | E45: Pre-Production | F45: Pre-Production | G45: 6717 | H45: =I45-G45 -> 6717 | I45: 13434 | J45: =IFERROR(VLOOKUP(B45,'Jun 26'!B:G,6,FALSE),0) -> 6717 | K45: 0 | L45: =G45-J45 -> 0 | N45: =L45-K45 -> 0
A46: Don's Mobile Glass:Michael Raimondo | B46: 90442 | C46: CA-R | D46: 46181 | E46: Pre-Production | F46: Pre-Production | G46: 40000 | H46: =I46-G46 -> 32316 | I46: 72316 | J46: =IFERROR(VLOOKUP(B46,'Jun 26'!B:G,6,FALSE),0) -> 40000 | K46: 0 | L46: =G46-J46 -> 0 | N46: =L46-K46 -> 0
A47: Doors, Etc.:Doors Etc HSW | B47: 88511 | C47: CA-R | D47: 46072 | E47: 46162 | F47: Assembly | G47: 0 | H47: 0 | I47: 0 | J47: =IFERROR(VLOOKUP(B47,'Jun 26'!B:G,6,FALSE),0) -> 19222 | K47: =IF(G47=0,J47-G47,0) -> 19222 | L47: Invoiced This Month | N47: =L47-K47 -> #VALUE!
A48: Dugally Oberfeld, Inc.:Cox | B48: 83729 | C48: CA-R | D48: 46028 | E48: 46155 | F48: Pull Material | G48: 31223 | H48: 27501 | I48: 58724 | J48: =IFERROR(VLOOKUP(B48,'Jun 26'!B:G,6,FALSE),0) -> 31223 | K48: 0 | L48: =G48-J48 -> 0 | N48: =L48-K48 -> 0
A49: Dynamic Builders LHC:1821 Pinion Tree Dr Flex Counter | B49: 90688 | C49: AZ-R | D49: 46163 | E49: 46184 | F49: 46213 | G49: 0 | H49: =I49-G49 -> 23455.11 | I49: 23455.11 | J49: =IFERROR(VLOOKUP(B49,'Jun 26'!B:G,6,FALSE),0) -> 11700 | K49: =J49-G49 -> 11700 | L49: Invoiced This Month | N49: -11700
A50: Dynamic Glass:Antero Resources | B50: 85504 | C50: CO-C | D50: 46100 | E50: Pre-Production | F50: Pre-Production | G50: 151068 | H50: 151068 | I50: 302136 | J50: =IFERROR(VLOOKUP(B50,'Jun 26'!B:G,6,FALSE),0) -> 151068 | K50: 0 | L50: =G50-J50 -> 0 | N50: =L50-K50 -> 0
A51: E & Z Glass & Window:Tollway Office Building | B51: 90853 | C51: TX-R | D51: 46177 | E51: 46202 | F51: Pull Material | G51: 48347 | H51: =I51-G51 -> 48346 | I51: 96693 | J51: =IFERROR(VLOOKUP(B51,'Jun 26'!B:G,6,FALSE),0) -> 48347 | K51: 0 | L51: =G51-J51 -> 0 | N51: =L51-K51 -> 0
A52: Echelon Builders LLC:Residential | B52: 89324 | C52: HI-R | D52: 46141 | E52: 46197 | F52: Powder Coat | G52: 15963 | H52: =I52-G52 -> 15962 | I52: 31925 | J52: =IFERROR(VLOOKUP(B52,'Jun 26'!B:G,6,FALSE),0) -> 15963 | K52: =IF(G52=0,J52-G52,0) -> 0 | L52: =G52-J52 -> 0 | N52: =L52-K52 -> 0
A53: Element Facades 13:299 MILWAUKEE | B53: 86960 | C53: CO-C | D53: 45986 | E53: Pre-Production | F53: Pre-Production | G53: =8962+8962 -> 17924 | H53: 26885 | I53: 39102 | J53: =IFERROR(VLOOKUP(B53,'Jun 26'!B:G,6,FALSE),0) -> 8962 | K53: 0 | L53: =G53-J53 -> 8962 | N53: =L53-K53 -> 8962
A54: Elite Glazing Group:LA Basketball | B54: 90706 | C54: CA-C | D54: 46181 | E54: Pre-Production | F54: Pre-Production | G54: 30536 | H54: =I54-G54 -> 30536 | I54: 61072 | J54: =IFERROR(VLOOKUP(B54,'Jun 26'!B:G,6,FALSE),0) -> 30536 | K54: 0 | L54: =G54-J54 -> 0 | N54: =L54-K54 -> 0
A55: Elite Glazing Inc.:RSF Clubhouse | B55: 85987 | C55: CA-C | D55: 46115 | E55: 46177 | F55: Powder Coat | G55: 68043 | H55: =I55-G55 -> 68042 | I55: 136085 | J55: =IFERROR(VLOOKUP(B55,'Jun 26'!B:G,6,FALSE),0) -> 68043 | K55: 0 | L55: =G55-J55 -> 0 | N55: =L55-K55 -> 0
A56: Environmental Glass Inc:Ann Arbor Thurston | B56: 84161 | C56: MI-C | D56: 46013 | E56: Pre-Production | F56: Pre-Production | G56: 176687 | H56: 176686 | I56: 353373 | J56: =IFERROR(VLOOKUP(B56,'Jun 26'!B:G,6,FALSE),0) -> 176687 | K56: 0 | L56: =G56-J56 -> 0 | N56: =L56-K56 -> 0
A57: Environmental Glass Inc:Mitchell Elementary | B57: 81492-R1 | C57: MI-C | D57: 45868 | E57: Pre-Production | F57: Pre-Production | G57: 114974 | H57: 114973 | I57: 229947 | J57: =IFERROR(VLOOKUP(B57,'Jun 26'!B:G,6,FALSE),0) -> 114974 | K57: 0 | L57: =G57-J57 -> 0 | N57: =L57-K57 -> 0
A58: Ford Metro Inc:Chapter / Ann Arbor | B58: 87492 | C58: MN-R | D58: 46063 | E58: Pre-Production | F58: Pre-Production | G58: 22079 | H58: 22079 | I58: 44158 | J58: =IFERROR(VLOOKUP(B58,'Jun 26'!B:G,6,FALSE),0) -> 22079 | K58: 0 | L58: =G58-J58 -> 0 | N58: =L58-K58 -> 0
A59: Gallatin Glass Works Inc:5026 Iron Ridge Patio | B59: 88818 | C59: MT-R | D59: 46121 | E59: 46181 | F59: 46227 | G59: 0 | H59: 0 | I59: 0 | J59: =IFERROR(VLOOKUP(B59,'Jun 26'!B:G,6,FALSE),0) -> 15127 | K59: =IF(G59=0,J59-G59,0) -> 15127 | L59: Invoiced This Month | N59: -15127
A60: Giroux Glass:SoCalGas Loggia | B60: 88082 | C60: CA-C | D60: 46076 | E60: Pre-Production | F60: Pre-Production | G60: =35295+4818 -> 40113 | H60: 35294 | I60: 70589 | J60: =IFERROR(VLOOKUP(B60,'Jun 26'!B:G,6,FALSE),0) -> 35295 | K60: 0 | L60: =G60-J60 -> 4818 | N60: =L60-K60 -> 4818
A61: Giroux Glass:Sparks Training Facility | B61: 89539 | C61: CA-C | D61: 46170 | E61: Pre-Production | F61: Pre-Production | G61: 32606 | H61: =I61-G61 -> 32606 | I61: 65212 | J61: =IFERROR(VLOOKUP(B61,'Jun 26'!B:G,6,FALSE),0) -> 32606 | L61: =G61-J61 -> 0 | N61: =L61-K61 -> 0
A62: Glass and Metals, Inc:2100 Crystal | B62: 88012 | C62: VA-C | D62: 46086 | E62: Pre-Production | F62: Pre-Production | G62: 25461 | H62: 25461 | I62: 51937 | J62: =IFERROR(VLOOKUP(B62,'Jun 26'!B:G,6,FALSE),0) -> 25461 | K62: 0 | L62: =G62-J62 -> 0 | N62: =L62-K62 -> 0
A63: Glass Concepts:WIC | B63: 90365 | C63: CO-C | D63: 05/11/2026 | E63: Pre-Production | F63: Pre-Production | G63: 12373 | H63: =I63-G63 -> 12372.53 | I63: 24745.53 | J63: =IFERROR(VLOOKUP(B63,'Jun 26'!B:G,6,FALSE),0) -> 12373 | K63: 0 | L63: =G63-J63 -> 0 | N63: =L63-K63 -> 0
A64: Glass House LLC:Red Arrow | B64: 88675 | C64: NV-R | D64: 46149 | E64: Pre-Production | F64: Pre-Production | G64: 51194.18 | H64: =I64-G64 -> 0 | I64: 51194.18 | J64: =IFERROR(VLOOKUP(B64,'Jun 26'!B:G,6,FALSE),0) -> 51194.18 | K64: 0 | L64: =G64-J64 -> 0 | N64: =L64-K64 -> 0
A65: Glass House Products:Lawther Remodel | B65: 90930 | C65: TX-R | D65: 46163 | E65: Pre-Production | F65: Pre-Production | G65: 28888.91 | H65: =I65-G65 -> 32567.42 | I65: 61456.33 | J65: =IFERROR(VLOOKUP(B65,'Jun 26'!B:G,6,FALSE),0) -> 28888.91 | L65: =G65-J65 -> 0 | N65: =L65-K65 -> 0
A66: Goldfinch Brothers:Stoel Rives L48 | B66: 89287 | C66: WA-C | D66: 46113 | E66: Pre-Production | F66: Pre-Production | G66: 89586 | H66: =I66-G66 -> 89585 | I66: 179171 | J66: =IFERROR(VLOOKUP(B66,'Jun 26'!B:G,6,FALSE),0) -> 89586 | K66: 0 | L66: =G66-J66 -> 0 | N66: =L66-K66 -> 0
A67: GP Glass & Mirror LLC:George_Pivot Door and Trapezoids | B67: 90716 | C67: NV-R | D67: 05/15/2026 | E67: 46188 | F67: 46224 | G67: 0 | H67: 0 | I67: 0 | J67: =IFERROR(VLOOKUP(B67,'Jun 26'!B:G,6,FALSE),0) -> 11932 | K67: =IF(G67=0,J67-G67,0) -> 11932 | L67: Invoiced This Month | N67: -11932
A68: Grand View Glass:LMAC Operable Glass Wall | B68: 89541 | C68: CO-C | D68: 46185 | E68: Pre-Production | F68: Pre-Production | G68: 9278.28 | H68: =I68-G68 -> 7903.72 | I68: 17182 | J68: =IFERROR(VLOOKUP(B68,'Jun 26'!B:G,6,FALSE),0) -> 9278.28 | K68: 0 | L68: =G68-J68 -> 0 | N68: =L68-K68 -> 0
A69: Green Glass:Overland | B69: 89055 | C69: CA-C | D69: 46120 | E69: 46163 | F69: 46210 | G69: 0 | H69: =I69-G69 -> 17164 | I69: 17164 | J69: =IFERROR(VLOOKUP(B69,'Jun 26'!B:G,6,FALSE),0) -> 8582 | K69: =J69-G69 -> 8582 | L69: Invoiced This Month | N69: -8582
A70: Hall Aluminum Products:TT Union Building D | B70: 87359 | C70: IN-C | D70: 46125 | E70: Pre-Production | F70: Pre-Production | G70: =19467+9639 -> 29106 | H70: =I70-G70 -> 19466 | I70: 48572 | J70: =IFERROR(VLOOKUP(B70,'Jun 26'!B:G,6,FALSE),0) -> 19467 | K70: 0 | L70: =G70-J70 -> 9639 | N70: =L70-K70 -> 9639
A71: Hardman Glazing Management LLC:800 Corte Madera | B71: 89412 | C71: CA-R | D71: 46126 | E71: 46191 | F71: Powder Coat | G71: 20897 | H71: =I71-G71 -> 9706 | I71: 30603 | J71: =IFERROR(VLOOKUP(B71,'Jun 26'!B:G,6,FALSE),0) -> 20897 | K71: 0 | L71: =G71-J71 -> 0 | N71: =L71-K71 -> 0
A72: Hardman Glazing Management LLC:Utility building - 800 Corte Madera | B72: 89867 | C72: CA-R | D72: 46126 | E72: 46192 | F72: Powder Coat | G72: 14271.62 | H72: =I72-G72 -> 7648.63 | I72: 21920.25 | J72: =IFERROR(VLOOKUP(B72,'Jun 26'!B:G,6,FALSE),0) -> 14271.62 | K72: 0 | L72: =G72-J72 -> 0 | N72: =L72-K72 -> 0
A73: Hasco Constrution:Sperryn Jones | B73: 82632 | C73: SN-R | D73: 45758 | E73: 46146 | F73: 46217 | G73: 0 | H73: 0 | I73: 0 | J73: =IFERROR(VLOOKUP(B73,'Jun 26'!B:G,6,FALSE),0) -> 109478 | K73: =IF(G73=0,J73-G73,0) -> 109478 | L73: Invoiced This Month | N73: -109478
A74: HBS Inc.:Burns | B74: 87391 | C74: FL-R | D74: 46168 | E74: Pre-Production | F74: Pre-Production | G74: 60000 | H74: =I74-G74 -> 42519 | I74: 102519 | J74: =IFERROR(VLOOKUP(B74,'Jun 26'!B:G,6,FALSE),0) -> 60000 | L74: =G74-J74 -> 0 | N74: =L74-K74 -> 0
A75: HBS Inc.:Holloway | B75: 90134 | C75: FL-R | D75: 05/15/2026 | E75: 46169 | F75: 46217 | G75: 0 | H75: 0 | I75: 0 | J75: =IFERROR(VLOOKUP(B75,'Jun 26'!B:G,6,FALSE),0) -> 19000 | K75: =IF(G75=0,J75-G75,0) -> 19000 | L75: Invoiced This Month | N75: -19000
A76: Heart of America Aston LLC:592 Aston | B76: 84210 | C76: IL-C | D76: 45876 | E76: 46164 | F76: Pull Material | G76: 31567 | H76: 46437 | I76: 78004 | J76: =IFERROR(VLOOKUP(B76,'Jun 26'!B:G,6,FALSE),0) -> 31567 | K76: 0 | L76: =G76-J76 -> 0 | N76: =L76-K76 -> 0
A77: Helou Construction:Rosebowl South Endzone Club | B77: 88433 | C77: CA-C | D77: 46036 | E77: 46155 | F77: 46209 | G77: 0 | H77: 0 | I77: 0 | J77: =IFERROR(VLOOKUP(B77,'Jun 26'!B:G,6,FALSE),0) -> 84942.5 | K77: =J77-G77 -> 84942.5 | L77: Invoiced This Month | N77: -84942.5
A78: Integrated Door & Window Systems:102 McKnight Dr- Phase 2 | B78: 88155 | C78: CA-R | D78: 46135 | E78: 46163 | F78: Powder Coat | G78: 26625 | H78: =I78-G78 -> 26625 | I78: 53250 | J78: =IFERROR(VLOOKUP(B78,'Jun 26'!B:G,6,FALSE),0) -> 26625 | K78: =IF(G78=0,J78-G78,0) -> 0 | L78: =G78-J78 -> 0 | N78: =L78-K78 -> 0
A79: Integrated Glass Concepts, Inc:Diablo Valley College | B79: 87488 | C79: CA-C | D79: 46007 | E79: 46195 | F79: Powder Coat | G79: 17613 | H79: 17612 | I79: 35225 | J79: =IFERROR(VLOOKUP(B79,'Jun 26'!B:G,6,FALSE),0) -> 17613 | K79: 0 | L79: =G79-J79 -> 0 | N79: =L79-K79 -> 0
A80: Island Tiles:Hilton Ballroom Doors | B80: 89316 | C80: BB-C | D80: 46100 | E80: 46174 | F80: Cutting | G80: 56063 | H80: 56063 | I80: 112126 | J80: =IFERROR(VLOOKUP(B80,'Jun 26'!B:G,6,FALSE),0) -> 56063 | K80: 0 | L80: =G80-J80 -> 0 | N80: =L80-K80 -> 0
A81: J Shuman Door Installation:Arnaud Slider | B81: 90536 | C81: CA-R | D81: 46160 | E81: Pre-Production | F81: Pre-Production | G81: 9055.57 | H81: =I81-G81 -> 9055.57 | I81: 18111.14 | J81: =IFERROR(VLOOKUP(B81,'Jun 26'!B:G,6,FALSE),0) -> 9055.57 | L81: =G81-J81 -> 0 | N81: =L81-K81 -> 0
A82: J Shuman Door Installation:Cord Project | B82: 90305 | C82: CA-R | D82: 46188 | E82: Pre-Production | F82: Pre-Production | G82: 6823.18 | H82: =I82-G82 -> 6823.18 | I82: 13646.36 | J82: =IFERROR(VLOOKUP(B82,'Jun 26'!B:G,6,FALSE),0) -> 6823.18 | K82: 0 | L82: =G82-J82 -> 0 | N82: =L82-K82 -> 0
A83: J Shuman Door Installation:Hospitality Building | B83: 86579 | C83: CA-R | D83: 46188 | E83: Pre-Production | F83: Pre-Production | G83: 69123 | H83: =I83-G83 -> 66195 | I83: 135318 | J83: =IFERROR(VLOOKUP(B83,'Jun 26'!B:G,6,FALSE),0) -> 69123 | K83: 0 | L83: =G83-J83 -> 0 | N83: =L83-K83 -> 0
A84: J Shuman Door Installation:Jared Lou | B84: 86904 | C84: CA-R | D84: 46105 | E84: 46163 | F84: 46211 | G84: 0 | H84: 6515 | I84: 13031 | J84: =IFERROR(VLOOKUP(B84,'Jun 26'!B:G,6,FALSE),0) -> 6516 | K84: =J84-G84 -> 6516 | L84: Invoiced This Month | N84: -6516
A85: J Shuman Door Installation:Marzalek Folding Door | B85: 87965 | C85: CA-R | D85: 05/13/2026 | E85: 46181 | F85: 46213 | G85: 0 | H85: =I85-G85 -> 17510 | I85: 17510 | J85: =IFERROR(VLOOKUP(B85,'Jun 26'!B:G,6,FALSE),0) -> 8755 | K85: =J85-G85 -> 8755 | L85: Invoiced This Month | N85: -8755
A86: J Shuman Door Installation:Nandini Saraiya | B86: 89168 | C86: CA-R | D86: 46136 | E86: Pre-Production | F86: Pre-Production | G86: 30691 | H86: =I86-G86 -> 30691 | I86: 61382 | J86: =IFERROR(VLOOKUP(B86,'Jun 26'!B:G,6,FALSE),0) -> 30691 | K86: =IF(G86=0,J86-G86,0) -> 0 | L86: =G86-J86 -> 0 | N86: =L86-K86 -> 0
A87: James Bridgeford:Bridgeford Sliders | B87: 90956 | C87: NV-R | D87: 46182 | E87: Pre-Production | F87: Pre-Production | G87: 5694.98 | H87: =I87-G87 -> 5694.97 | I87: 11389.95 | J87: =IFERROR(VLOOKUP(B87,'Jun 26'!B:G,6,FALSE),0) -> 5694.98 | K87: 0 | L87: =G87-J87 -> 0 | N87: =L87-K87 -> 0
A88: James Stevens:Seal Way Folding | B88: 90566 | C88: CA-R | D88: 46148 | E88: 46191 | F88: 46220 | G88: 0 | H88: 0 | I88: 0 | J88: =IFERROR(VLOOKUP(B88,'Jun 26'!B:G,6,FALSE),0) -> 19409.04 | K88: =IF(G88=0,J88-G88,0) -> 19409.04 | L88: Invoiced This Month | N88: -19409.04
A89: JDP Associates:Aldo House | B89: 90809 | C89: NV-R | D89: 46162 | E89: Pre-Production | F89: Pre-Production | G89: 44300 | H89: =I89-G89 -> 44290.17 | I89: 88590.17 | J89: =IFERROR(VLOOKUP(B89,'Jun 26'!B:G,6,FALSE),0) -> 44300 | L89: =G89-J89 -> 0 | N89: =L89-K89 -> 0
A90: JDP Associates:Bono LTS.30 | B90: 90987 | C90: NV-R | D90: 46170 | E90: Pre-Production | F90: Pre-Production | G90: 28000 | H90: =I90-G90 -> 26666.36 | I90: 54666.36 | J90: =IFERROR(VLOOKUP(B90,'Jun 26'!B:G,6,FALSE),0) -> 28000 | L90: =G90-J90 -> 0 | N90: =L90-K90 -> 0
A91: Jeff Kohler:Living Room | B91: 89722 | C91: OH-R | D91: 46120 | E91: Pre-Production | F91: Pre-Production | G91: 3826 | H91: =I91-G91 -> 3826.56 | I91: 7652.56 | J91: =IFERROR(VLOOKUP(B91,'Jun 26'!B:G,6,FALSE),0) -> 3826 | K91: 0 | L91: =G91-J91 -> 0 | N91: =L91-K91 -> 0
A92: Jeremy D. Whalon:Whaleon Residence | B92: 86092 | C92: CA-R | D92: 46120 | E92: Pre-Production | F92: Pre-Production | G92: 9201 | H92: =I92-G92 -> 9201.52 | I92: 18402.52 | J92: =IFERROR(VLOOKUP(B92,'Jun 26'!B:G,6,FALSE),0) -> 9201 | K92: 0 | L92: =G92-J92 -> 0 | N92: =L92-K92 -> 0
A93: John Burke:Burke Pivot | B93: 91288 | C93: CA-R | D93: 46198 | E93: Pre-Production | F93: Pre-Production | G93: 12700 | H93: =I93-G93 -> 12909.3 | I93: 25609.3 | J93: =IFERROR(VLOOKUP(B93,'Jun 26'!B:G,6,FALSE),0) -> 12700 | K93: 0 | L93: =G93-J93 -> 0 | N93: =L93-K93 -> 0
A94: Jones Paint & Glass:Control Booth | B94: 90271 | C94: UT-R | D94: 46164 | E94: 46199 | F94: 46210 | G94: 0 | H94: 0 | I94: 0 | J94: =IFERROR(VLOOKUP(B94,'Jun 26'!B:G,6,FALSE),0) -> 7216.29 | K94: =IF(G94=0,J94-G94,0) -> 7216.29 | L94: Invoiced This Month | N94: -7216.29
A95: KCR Development:Rec Pav 2 | B95: 88266 | C95: HI-R | D95: 46188 | E95: Pre-Production | F95: Pre-Production | G95: 40071 | H95: =I95-G95 -> 40071 | I95: 80142 | J95: =IFERROR(VLOOKUP(B95,'Jun 26'!B:G,6,FALSE),0) -> 40071 | K95: 0 | L95: =G95-J95 -> 0 | N95: =L95-K95 -> 0
A96: Keith Starkey:Starkey Residence | B96: 78503 | C96: NY-R | D96: 45825 | E96: Pre-Production | F96: Pre-Production | G96: 15815 | H96: 15814 | I96: 31629 | J96: =IFERROR(VLOOKUP(B96,'Jun 26'!B:G,6,FALSE),0) -> 15815 | K96: 0 | L96: =G96-J96 -> 0 | N96: =L96-K96 -> 0
A97: Kelly Maiello Architects:Large Conference Room Job | B97: 90032 | C97: PA-C | D97: 46150 | E97: Pre-Production | F97: Pre-Production | G97: 9955 | H97: =I97-G97 -> 10598.62 | I97: 20553.62 | J97: =IFERROR(VLOOKUP(B97,'Jun 26'!B:G,6,FALSE),0) -> 9955 | K97: 0 | L97: =G97-J97 -> 0 | N97: =L97-K97 -> 0
A98: Ken Caryl Glass:Marcus Meyer | B98: 90364 | C98: CO-R | D98: 46181 | E98: Pre-Production | F98: Pre-Production | G98: 11314.88 | H98: =I98-G98 -> 11314.87 | I98: 22629.75 | J98: =IFERROR(VLOOKUP(B98,'Jun 26'!B:G,6,FALSE),0) -> 11314.88 | K98: 0 | L98: =G98-J98 -> 0 | N98: =L98-K98 -> 0
